Workbook

Sheet read_me
A3: ctry | B3: sheet name | C3: description | D3: source | E3: time span | F3: note
A4: UK | B4: rgdp | C4: Gross Domestic Product: chained volume measures: Seasonally adjusted £m | D4: ONS | E4: 1970Q1-2025Q2 | F4: https://www.ons.gov.uk/economy/grossdomesticproductgdp/timeseries/abmi/pn2
A5: UK | B5: g4rdgp | C5: delta4 ln rgdp * 100 | D5: own computations | E5: 1971Q1-2025Q2
A6: UK | B6: qoq_rgdp | C6: delta ln of rgdp * 100 | D6: own computations | E6: 1970Q2-2025Q2
A7: UK | B7: g4Infl | C7: Inflation | D7: IMF | E7: 1970Q1-2025Q2 | F7: https://data.imf.org/en/Data-Explorer?datasetUrn=IMF.STA:CPI(4.0.0) (uk - cpi - all items - period avg (yoy) - quarterly - all
A8: UK | B8: infl | C8: CPIH ANNUAL RATE 00: ALL ITEMS 2015=100 | D8: ONS | E8: 1989Q1-2025Q2 | F8: https://www.ons.gov.uk/economy/inflationandpriceindices/timeseries/l55o/mm23
A9: UK | B9: credit_to_gdp_bank | C9: United Kingdom - Credit from Banks, domestic to Private non-financial sector at Market value, Percentage of GDP, Adjusted for breaks | D9: BIS | E9: 1970Q1-2025Q1 | F9: https://data.bis.org/topics/TOTAL_CREDIT/BIS,WS_TC,2.0/Q.GB.P.B.M.770.A
A10: UK | B10: credit_to_gdp_all | C10: United Kingdom - Credit from All sectors to Private non-financial sector at Market value, Percentage of GDP, Adjusted for breaks | D10: BIS | E10: 1970Q1-2025Q1 | F10: https://data.bis.org/topics/TOTAL_CREDIT/BIS,WS_TC,2.0/Q.GB.P.A.M.770.A
A11: UK | B11: delta_3y_credit_to_gdp_all | C11: delta 3y - United Kingdom - Credit from All sectors to Private non-financial sector at Market value, Percentage of GDP, Adjusted for breaks | D11: own computations | E11: 1973Q1-2025Q1
A12: ALL | B12: vix | C12: CBOE Volatility Index: VIX - US | D12: FRED | E12: 1970Q3-2025Q3 | F12: https://fred.stlouisfed.org/series/VIXCLS# || the series is spliced with S&P mrkt vol pre 1990q1
A13: UK | B13: bond_spread | C13: Corporate bond spread | D13: a-millennium-of-macroeconomic-data-for-the-uk + own computations + countercyclical capital buffer.xslsx (BOE) | E13: 1970Q1-2025Q3 | F13: we aggregate at the quarterly level (avg for the months in the quarter) the monthly series construcuted for inflation at risk (check other_series.do)
A14: UK | B14: mrkt_vol_uk | C14: MSCI UK indexrealized volatility in the quarter | D14: Refinitiv + own computation | E14: 1970Q2-2024Q4 | F14: David's paper
A15: ALL | B15: mrkvols&p | C15: S&P500 realized volatility in the quarter | D15: Refinitiv + own computation | E15: 1970Q2-2024Q4 | F15: David's paper
A16: ALL | B16: g4oil | C16: y-o-y growth in quarterly oil price | D16: FRED | E16: 1988Q3-2025Q3 | F16: https://fred.stlouisfed.org/series/MCOILBRENTEU#
A17: ALL | B17: oil | C17: Crude Oil Prices: Brent - Europe | D17: FRED | E17: 1972Q1-2025Q3 | F17: extendend with oil sheet from GaRDataRaw pre-1987q3
A18: ALL | B18: g4oil_long | C18: y-o-y growth in quarterly oil price | D18: own computations | E18: 1973Q1-2025Q3
A19: ALL | B19: chicago_fed_nfci | C19: Chicago Fed National Financial Conditions Index (NFCI) | D19: FRED | E19: 1971Q1-2025Q3 | F19: https://fred.stlouisfed.org/graph/?g=k5Pf
A20: ALL | B20: global_gdp | C20: Quarterly real GDP growth - OECD countries | D20: OECD | E20: 1970Q1-2025Q2 | F20: https://data-explorer.oecd.org/vis?df[ds]=DisseminateFinalDMZ&df[id]=DSD_NAMAIN1%40DF_QNA_EXPENDITURE_GROWTH_OECD&df[ag]=OECD.SDD.NAD&dq=Q..OECD.S1..B1GQ......GY.&pd=1962-Q1%2C&to[TIME_PERIOD]=false&vw=tb || growrh over 1 year || a note: formerly this variable relates to G7 countries. We have extended to full OECD
A21: UK | B21: global_credit | C21: weighted average of delta 3y credit over gdp (d3y_cre_to_gdp_all_ALL_ctry) using export as weights | D21: own computations | E21: 1973Q1-2025Q1
A22: UK | B22: pmi_out | C22: PMI output | D22: provided by BOE | E22: 1989Q4-2025Q3 | F22: we spliced the PMI output series using consensus GDP forecast. We regress the PMI on consensus GDP forecast (next calendar year), we store the coefficents and we backast the variables
A23: UK | B23: pmi_out_fut | C23: PMI output future | D23: provided by BOE | E23: 1989Q4-2025Q3 | F23: we spliced the PMI output future series using consensus GDP forecast. We regress the PMI on consensus GDP forecast (next calendar year), we store the coefficents and we backast the variables
A24: UK | B24: ciss_uk | C24: NEW CISS - Composite Indicator of Systemic Stress., United Kingdom, Daily | D24: ECB | E24: 1980Q1-2025Q3 | F24: https://data.ecb.europa.eu/data/datasets/CISS/CISS.D.GB.Z0Z.4F.EC.SS_CIN.IDX?chart_props=W3sibm9kZUlkIjoiMTA2NTQwMyIsInByb3BlcnRpZXMiOlt7ImNvbG9ySGV4IjoiIiwiY29sb3JUeXBlIjoiIiwiY2hhcnRUeXBlIjoibGluZWNoYXJ0IiwibGluZVN0eWxlIjoiU29saWQiLCJsaW5lV2lkdGgiOiIxLjUiLCJheGlzUG9zaXRpb24iOiJsZWZ0Iiwib2JzZXJ2YXRpb25WYWx1ZSI6ZmFsc2UsImRhdGVzIjpbXSwiaXNUZGF0YSI6dHJ1ZSwibW9kaWZpZWRVbml0VHlwZSI6Im5vbmUiLCJ5ZWFyIjoiZGF0ZXdpc2UiLCJzdGFydERhdGUiOiIxOTgwLTAxLTAyIiwiZW5kRGF0ZSI6IjIwMjUtMDctMDgiLCJzZXREYXRlIjp0cnVlLCJzaG93VGFibGVEYXRhIjpmYWxzZSwiY2hhbmdlTW9kZSI6ZmFsc2UsInNob3dNZW51U3R5bGVDaGFydCI6ZmFsc2UsImRpc3BsYXlNb2JpbGVDaGFydCI6dHJ1ZSwic2NyZWVuU2l6ZSI6Im1heCIsInNjcmVlbldpZHRoIjoyNTYwLCJzaG93VGRhdGEiOnRydWUsInRyYW5zZm9ybWVkRnJlcXVlbmN5IjoicXVhcnRlcmx5IiwidHJhbnNmb3JtZWRVbml0Ijoibm9uZSIsImZyZXF1ZW5jeSI6InF1YXJ0ZXJseSIsInVuaXQiOiJub25lIiwibW9kaWZpZWQiOiJ0cnVlIiwic2VyaWVzS2V5IjoiZGFpbHkiLCJzaG93dGFibGVTdGF0ZUJlZm9yZU1heFNjcmVlbiI6ZmFsc2UsImlzZGF0YWNvbXBhcmlzb24iOmZhbHNlLCJzZXJpZXNGcmVxdWVuY3kiOiJkYWlseSIsImludGlhbFNlcmllc0ZyZXF1ZW5jeSI6ImRhaWx5IiwibWV0YWRhdGFEZWNpbWFsIjoiNCIsImlzVGFibGVTb3J0ZWQiOmZhbHNlLCJpc1llYXJseVRkYXRhIjp0cnVlLCJyZXNwb25zZURhdGFFbmREYXRlIjoiIiwiaXNpbml0aWFsQ2hhcnREYXRhIjp0cnVlLCJpc0RhdGVzRnJvbURhdGVQaWNrZXIiOnRydWUsImRhdGVQaWNrZXJFbmREYXRlIjoiIiwiaXNEYXRlUGlja2VyRW5kRGF0ZSI6ZmFsc2UsInNlcmllc2tleVNldCI6IkNJU1MuRC5HQi5aMFouNEYuRUMuU1NfQ0lOLklEWHwyMzZ8bm9uZXxxdWFydGVybHl8bm9uZXxRdWFydGVybHkiLCJkYXRhc2V0SWQiOiIyMzYiLCJpc0NhbGxiYWNrIjpmYWxzZSwiaXNTbGlkZXJUZGF0YSI6ZmFsc2UsImlzU2xpZGVyRGF0YSI6dHJ1ZSwiaXNJbml0aWFsQ2hhcnREYXRhRnJvbUdyYXBoIjp0cnVlLCJjaGFydFNlcmllc0tleSI6IkNJU1MuRC5HQi5aMFouNEYuRUMuU1NfQ0lOLklEWCIsInR5cGVPZiI6IiJ9XX1d
A25: UK | B25: yield_curve_slope | C25: Difference between zero-coupon nominal spot 10 year yield and zero-coupon nominal spot 1 year yield | D25: BOE | E25: 1979Q1-2025Q3 | F25: https://www.bankofengland.co.uk/statistics/yield-curves Archive yield curve data Daily | Data are available in multiple vintages at the daily level - we generate quarterly data as the average of the average value for the days in the quarter (see other_series.do). We did not use monthly data as they referer to the last day in the month
A26: UK | B26: inflation_expectations | C26: CPI expectations in next calendar year | D26: Consensus Economics | E26: 1970Q1-2025Q3 | F26: the starting point is the seires used in the monthly analysis sheet infl1_m (IaRDataRaw_monthly.xlsx). We aggregate the series at the quarterly level (see other_series.do) - then we use g4infl to backast the series up to 1970q1. We regress inflation expectations on inflation from 1989q4 to 2024q4. We store the coefficents and we backast the series for inflation expectations
A27: UK | B27: import_deflator_fuel | C27: UK BOP: IMPORTS - FUELS - WORLD (IMPLIED DEFLATOR) | D27: ONS | E27: 1980Q1-2025Q2 | F27: ONS series is available only from 1997Q1 For the previous period we use Oxford economic UK IMPORT PRICE DEFLATOR - FUELS SADJ (it is exactly the same series as the ONS one post 1997 so there is no need to splice. The Oxford econ series has been downloaded from refinitiv datastream (the series name in datastream are: "UKXPMFU.E,UKBPGCQ.G")
A28: UK | B28: g4_import_deflator_fuel | C28: y-o-y growth in import fuels deflator | D28: own computations | E28: 1980Q1-2025Q2 | F28: for the first 4 quarters we use the value of 1981Q1
A29: UK | B29: mgdp_yoy | C29: y-o-y growth in monthly GDP | D29: OECD | E29: 1981Q2-2025Q2 | F29: https://www.ons.gov.uk/economy/grossdomesticproductgdp/datasets/gdpmonthlyestimateuktimeseriesdataset | Note: we compute this measure for a given quarter t as the growth rate between the average monhtly GPD of the first two months of the quarter and the average monthly GDP of the three months in the same quarter the previous year. ONS series is available from 1997q1 onward (hence the y-o-y growth from 1998q1).For the period before that we spliced the series with y-o-y gdp growth (see spliced_mgdp). Final note: we shift the period one quarter FORWARD to mimic the info set of the BOE. For a given quarter I already know the GDP for the first two months of the following one
A30: UK | B30: epu_idx | C30: UK Monthly EPU Index | D30: Economic Policy Uncertainty | E30: 1970Q1-2025Q3 | F30: Economic Policy Uncertainty Index | we spliced the monthly UK EPU with the historical one (see the epu_index.xlsx in data --> other series) | then we compute the quarterly series by taking the average of the months in the quarter
A31: UK | B31: house_price_growth | C31: United Kingdom - Selected residential property prices, Real, Year-on-year changes, in per cent | D31: BIS | E31: 1970Q1-2025Q2 | F31: https://data.bis.org/topics/RPP/BIS,WS_SPP,1.0/Q.GB.R.771
A32: UK | B32: housing_approvals | C32: Monthly number of total sterling approvals for house pruchase to individuals seasonally adj | D32: BOE | E32: 1970Q1-2025Q2 | F32: LPMVTVX | Bank of England | Database | the series is available monthly, WE sum the monthly series in the quarter. Then we spliced it with real 1y growth house price (look at spliced_housing_approvals)
A34: UK | B34: uk_export_weight | C34: From the excel file ExportWeights.xlsx | D34: provided by BOE | E34: 1970Q1-2025Q3 | F34: we use the sheet UK_X. For the quarters prior to 1972 we use the value of 1972. For the quarters after 2018 we use the value of 2018
A35: ALL | B35: credit_to_gdp_ALL_ctry | C35: AUS CAN FRA GER ITA SPAIN SWE SWI UK US - Credit from All sectors to Private non-financial sector at Market value, Percentage of GDP, Adjusted for breaks | D35: BIS | E35: 1970Q1-2025Q1 | F35: https://data.bis.org/topics/TOTAL_CREDIT/BIS,WS_TC,2.0/Q.GB.P.B.M.770.A
A36: ALL | B36: d3y_cre_to_gdp_all_ALL_ctry | C36: delta 3y - AUS CAN FRA GER ITA SPAIN SWE SWI UK US - Credit from All sectors to Private non-financial sector at Market value, Percentage of GDP, Adjusted for breaks | D36: own computations | E36: 1973Q1-2025Q1
A37: UK | B37: quarterly_pmi | C37: PMI for output and future output | D37: provided by BOE | E37: 1997Q2-2025Q3 | F37: The original series is available at the monthly level. We aggregte it at the quarterly level by computing the average in the quarter (see stata code \Codes\intermediate_codes -->other_series.do)
A38: UK | B38: gdp_growth_forecast_consensus | C38: Consensus forecast for current and next calendar year | D38: provided by BOE | E38: 1989Q4-2022Q4 | F38: The original series is available at the monthly level. We aggregte it at the quarterly level by computing the average in the quarter (see stata code \Codes\intermediate_codes -->other_series.do)

Sheet rgdp
B1: UK | C1: US | D1: EA
A2: 1970q1 | B2: 225223 | C2: 123456789 | D2: 123456789
A3: 1970q2 | B3: 230605 | C3: 123456789 | D3: 123456789
A4: 1970q3 | B4: 232800 | C4: 123456789 | D4: 123456789
A5: 1970q4 | B5: 234954 | C5: 123456789 | D5: 123456789
A6: 1971q1 | B6: 233843 | C6: 123456789 | D6: 123456789
A7: 1971q2 | B7: 238030 | C7: 123456789 | D7: 123456789
A8: 1971q3 | B8: 242078 | C8: 123456789 | D8: 123456789
A9: 1971q4 | B9: 243009 | C9: 123456789 | D9: 123456789
A10: 1972q1 | B10: 243540 | C10: 123456789 | D10: 123456789
A11: 1972q2 | B11: 249966 | C11: 123456789 | D11: 123456789
A12: 1972q3 | B12: 250633 | C12: 123456789 | D12: 123456789
A13: 1972q4 | B13: 254524 | C13: 123456789 | D13: 123456789
... A226: 2026Q1 | B226: 705571 | C226: 123456789 | D226: 123456789

Sheet g4rgdp
B1: UK | C1: US | D1: EA
A2: 1970q1 | B2: 123456789 | C2: 123456789 | D2: 123456789
A3: 1970q2 | B3: 123456789 | C3: 123456789 | D3: 123456789
A4: 1970q3 | B4: 123456789 | C4: 123456789 | D4: 123456789
A5: 1970q4 | B5: 123456789 | C5: 123456789 | D5: 123456789
A6: 1971q1 | B6: =(LN(rgdp!B6) - LN(rgdp!B2))*100 -> 3.7558928 | C6: 123456789 | D6: 123456789
A7: 1971q2 | B7: =(LN(rgdp!B7) - LN(rgdp!B3))*100 -> 3.1690426 | C7: 123456789 | D7: 123456789
A8: 1971q3 | B8: =(LN(rgdp!B8) - LN(rgdp!B4))*100 -> 3.9080272 | C8: 123456789 | D8: 123456789
A9: 1971q4 | B9: =(LN(rgdp!B9) - LN(rgdp!B5))*100 -> 3.3708729 | C9: 123456789 | D9: 123456789
A10: 1972q1 | B10: =(LN(rgdp!B10) - LN(rgdp!B6))*100 -> 4.063125 | C10: 123456789 | D10: 123456789
A11: 1972q2 | B11: =(LN(rgdp!B11) - LN(rgdp!B7))*100 -> 4.8928192 | C11: 123456789 | D11: 123456789
A12: 1972q3 | B12: =(LN(rgdp!B12) - LN(rgdp!B8))*100 -> 3.4729729 | C12: 123456789 | D12: 123456789
A13: 1972q4 | B13: =(LN(rgdp!B13) - LN(rgdp!B9))*100 -> 4.6296654 | C13: 123456789 | D13: 123456789
A14: 1973q1 | B14: =(LN(rgdp!B14) - LN(rgdp!B10))*100 -> 9.2023637 | C14: 123456789 | D14: 123456789
A15: 1973q2 | B15: =(LN(rgdp!B15) - LN(rgdp!B11))*100 -> 6.7873159 | C15: 123456789 | D15: 123456789
A16: 1973q3 | B16: =(LN(rgdp!B16) - LN(rgdp!B12))*100 -> 5.5834443 | C16: 123456789 | D16: 123456789
A17: 1973q4 | B17: =(LN(rgdp!B17) - LN(rgdp!B13))*100 -> 3.6512302 | C17: 123456789 | D17: 123456789
... A225: 2025q4 | B225: =(LN(rgdp!B225) - LN(rgdp!B221))*100 -> 0.94825639 | C225: 123456789 | D225: 123456789
A226: 2026q1 | B226: 0.948256 | C226: 123456789 | D226: 123456789

Sheet g4rgdp_first
A1: date | B1: UK
A2: 1970q1 | B2: 123456789
A3: 1970q2 | B3: 123456789
A4: 1970q3 | B4: 123456789
A5: 1970q4 | B5: 123456789
A6: 1971q1 | B6: 3.7558928
A7: 1971q2 | B7: 3.1690426
A8: 1971q3 | B8: 3.9080272
A9: 1971q4 | B9: 3.3708729
A10: 1972q1 | B10: 4.063125
A11: 1972q2 | B11: 4.8928192
A12: 1972q3 | B12: 3.4729729
A13: 1972q4 | B13: 4.6296654
... A226: 2026q1 | B226: 0.6

Sheet qoq_rgdp
B1: UK | C1: US | D1: EA
A2: 1970q1 | B2: 123456789 | C2: 123456789 | D2: 123456789
A3: 1970q2 | B3: =(LN(rgdp!B3)-LN(rgdp!B2))*100 -> 2.3615268 | C3: 123456789 | D3: 123456789
A4: 1970q3 | B4: =(LN(rgdp!B4)-LN(rgdp!B3))*100 -> 0.94734257 | C4: 123456789 | D4: 123456789
A5: 1970q4 | B5: =(LN(rgdp!B5)-LN(rgdp!B4))*100 -> 0.92100344 | C5: 123456789 | D5: 123456789
A6: 1971q1 | B6: =(LN(rgdp!B6)-LN(rgdp!B5))*100 -> -0.47398003 | C6: 123456789 | D6: 123456789
A7: 1971q2 | B7: =(LN(rgdp!B7)-LN(rgdp!B6))*100 -> 1.7746766 | C7: 123456789 | D7: 123456789
A8: 1971q3 | B8: =(LN(rgdp!B8)-LN(rgdp!B7))*100 -> 1.6863272 | C8: 123456789 | D8: 123456789
A9: 1971q4 | B9: =(LN(rgdp!B9)-LN(rgdp!B8))*100 -> 0.38384914 | C9: 123456789 | D9: 123456789
A10: 1972q1 | B10: =(LN(rgdp!B10)-LN(rgdp!B9))*100 -> 0.21827204 | C10: 123456789 | D10: 123456789
A11: 1972q2 | B11: =(LN(rgdp!B11)-LN(rgdp!B10))*100 -> 2.6043709 | C11: 123456789 | D11: 123456789
A12: 1972q3 | B12: =(LN(rgdp!B12)-LN(rgdp!B11))*100 -> 0.26648091 | C12: 123456789 | D12: 123456789
A13: 1972q4 | B13: =(LN(rgdp!B13)-LN(rgdp!B12))*100 -> 1.5405416 | C13: 123456789 | D13: 123456789
A14: 1973q1 | B14: =(LN(rgdp!B14)-LN(rgdp!B13))*100 -> 4.7909702 | C14: 123456789 | D14: 123456789
... A225: 2025q4 | B225: =(LN(rgdp!B225)-LN(rgdp!B224))*100 -> -0.069564826 | C225: 123456789 | D225: 123456789
A226: 2026q1 | B226: -0.06956 | C226: 123456789 | D226: 123456789

Sheet avg_g4rgdp
B1: UK | C1: US | D1: EA
A2: 1970q1 | B2: 123456789 | C2: 123456789 | D2: 123456789
A3: 1970q2 | B3: 123456789 | C3: 123456789 | D3: 123456789
A4: 1970q3 | B4: 123456789 | C4: 123456789 | D4: 123456789
A5: 1970q4 | B5: 123456789 | C5: 123456789 | D5: 123456789
A6: 1971q1 | B6: 123456789 | C6: 123456789 | D6: 123456789
A7: 1971q2 | B7: 123456789 | C7: 123456789 | D7: 123456789
A8: 1971q3 | B8: 123456789 | C8: 123456789 | D8: 123456789
A9: 1971q4 | B9: =AVERAGE(g4rgdp!B6:B9) -> 3.5509589 | C9: 123456789 | D9: 123456789
A10: 1972q1 | B10: =AVERAGE(g4rgdp!B7:B10) -> 3.6277669 | C10: 123456789 | D10: 123456789
A11: 1972q2 | B11: =AVERAGE(g4rgdp!B8:B11) -> 4.0587111 | C11: 123456789 | D11: 123456789
A12: 1972q3 | B12: =AVERAGE(g4rgdp!B9:B12) -> 3.9499475 | C12: 123456789 | D12: 123456789
A13: 1972q4 | B13: =AVERAGE(g4rgdp!B10:B13) -> 4.2646457 | C13: 123456789 | D13: 123456789
A14: 1973q1 | B14: =AVERAGE(g4rgdp!B11:B14) -> 5.5494553 | C14: 123456789 | D14: 123456789
A15: 1973q2 | B15: =AVERAGE(g4rgdp!B12:B15) -> 6.0230795 | C15: 123456789 | D15: 123456789
A16: 1973q3 | B16: =AVERAGE(g4rgdp!B13:B16) -> 6.5506973 | C16: 123456789 | D16: 123456789
A17: 1973q4 | B17: =AVERAGE(g4rgdp!B14:B17) -> 6.3060885 | C17: 123456789 | D17: 123456789
A18: 1974q1 | B18: =AVERAGE(g4rgdp!B15:B18) -> 3.017657 | C18: 123456789 | D18: 123456789
A19: 1974q2 | B19: =AVERAGE(g4rgdp!B16:B19) -> 0.64126025 | C19: 123456789 | D19: 123456789
A20: 1974q3 | B20: =AVERAGE(g4rgdp!B17:B20) -> -1.0520907 | C20: 123456789 | D20: 123456789
... A223: 2025q2 | B223: =AVERAGE(g4rgdp!B220:B223) -> 1.6101431 | C223: 123456789 | D223: 123456789
A224: 2025q3 | B224: 1.2668547 | C224: 123456789 | D224: 123456789
A225: 2025q4 | B225: 1.2668547 | C225: 123456789 | D225: 123456789
A226: 2026q1 | B226: 1.266855 | C226: 123456789 | D226: 123456789

Sheet g4infl
B1: UK | C1: US | D1: EA
A2: 1970q1 | B2: 5.0102728 | C2: 123456789 | D2: 123456789
A3: 1970q2 | B3: 5.8689632 | C3: 123456789 | D3: 123456789
A4: 1970q3 | B4: 6.8417077 | C4: 123456789 | D4: 123456789
A5: 1970q4 | B5: 7.7038182 | C5: 123456789 | D5: 123456789
A6: 1971q1 | B6: 8.5882079 | C6: 123456789 | D6: 123456789
A7: 1971q2 | B7: 9.8446789 | C7: 123456789 | D7: 123456789
A8: 1971q3 | B8: 10.113419 | C8: 123456789 | D8: 123456789
A9: 1971q4 | B9: 9.2129552 | C9: 123456789 | D9: 123456789
A10: 1972q1 | B10: 7.9540339 | C10: 123456789 | D10: 123456789
A11: 1972q2 | B11: 6.17795 | C11: 123456789 | D11: 123456789
A12: 1972q3 | B12: 6.4592298 | C12: 123456789 | D12: 123456789
A13: 1972q4 | B13: 7.7151517 | C13: 123456789 | D13: 123456789
... A226: 2026q1 | B226: 4.07 | C226: 123456789 | D226: 123456789

Sheet infl
B1: UK | C1: US | D1: EA
A2: 1970q1 | B2: 123456789 | C2: 123456789 | D2: 123456789
A3: 1970q2 | B3: 123456789 | C3: 123456789 | D3: 123456789
A4: 1970q3 | B4: 123456789 | C4: 123456789 | D4: 123456789
A5: 1970q4 | B5: 123456789 | C5: 123456789 | D5: 123456789
A6: 1971q1 | B6: 123456789 | C6: 123456789 | D6: 123456789
A7: 1971q2 | B7: 123456789 | C7: 123456789 | D7: 123456789
A8: 1971q3 | B8: 123456789 | C8: 123456789 | D8: 123456789
A9: 1971q4 | B9: 123456789 | C9: 123456789 | D9: 123456789
A10: 1972q1 | B10: 123456789 | C10: 123456789 | D10: 123456789
A11: 1972q2 | B11: 123456789 | C11: 123456789 | D11: 123456789
A12: 1972q3 | B12: 123456789 | C12: 123456789 | D12: 123456789
A13: 1972q4 | B13: 123456789 | C13: 123456789 | D13: 123456789
... A226: 2026q1 | B226: 4.1 | C226: 123456789 | D226: 123456789

Sheet credit_to_gdp_bank
B1: UK | C1: US | D1: EA
A2: 1970q1 | B2: 29.5 | C2: 123456789 | D2: 123456789
A3: 1970q2 | B3: 29.9 | C3: 123456789 | D3: 123456789
A4: 1970q3 | B4: 29.3 | C4: 123456789 | D4: 123456789
A5: 1970q4 | B5: 29 | C5: 123456789 | D5: 123456789
A6: 1971q1 | B6: 29.3 | C6: 123456789 | D6: 123456789
A7: 1971q2 | B7: 29.2 | C7: 123456789 | D7: 123456789
A8: 1971q3 | B8: 29 | C8: 123456789 | D8: 123456789
A9: 1971q4 | B9: 29.4 | C9: 123456789 | D9: 123456789
A10: 1972q1 | B10: 31.2 | C10: 123456789 | D10: 123456789
A11: 1972q2 | B11: 31.8 | C11: 123456789 | D11: 123456789
A12: 1972q3 | B12: 32.5 | C12: 123456789 | D12: 123456789
A13: 1972q4 | B13: 33.4 | C13: 123456789 | D13: 123456789
... A226: 2026q1 | B226: 74.4 | C226: 123456789 | D226: 123456789

Sheet credit_to_gdp_all
B1: UK | C1: US | D1: EA
A2: 1970q1 | B2: 58 | C2: 123456789 | D2: 123456789
A3: 1970q2 | B3: 59.4 | C3: 123456789 | D3: 123456789
A4: 1970q3 | B4: 57.5 | C4: 123456789 | D4: 123456789
A5: 1970q4 | B5: 58.6 | C5: 123456789 | D5: 123456789
A6: 1971q1 | B6: 56.9 | C6: 123456789 | D6: 123456789
A7: 1971q2 | B7: 55.2 | C7: 123456789 | D7: 123456789
A8: 1971q3 | B8: 56.2 | C8: 123456789 | D8: 123456789
A9: 1971q4 | B9: 57.2 | C9: 123456789 | D9: 123456789
A10: 1972q1 | B10: 60.6 | C10: 123456789 | D10: 123456789
A11: 1972q2 | B11: 61.3 | C11: 123456789 | D11: 123456789
A12: 1972q3 | B12: 64.7 | C12: 123456789 | D12: 123456789
A13: 1972q4 | B13: 65 | C13: 123456789 | D13: 123456789
... A226: 2026q1 | B226: 135.6 | C226: 123456789 | D226: 123456789

Sheet delta_3y_credit_to_gdp_all
B1: UK | C1: US | D1: EA
A2: 1970q1 | B2: 123456789 | C2: 123456789 | D2: 123456789
A3: 1970q2 | B3: 123456789 | C3: 123456789 | D3: 123456789
A4: 1970q3 | B4: 123456789 | C4: 123456789 | D4: 123456789
A5: 1970q4 | B5: 123456789 | C5: 123456789 | D5: 123456789
A6: 1971q1 | B6: 123456789 | C6: 123456789 | D6: 123456789
A7: 1971q2 | B7: 123456789 | C7: 123456789 | D7: 123456789
A8: 1971q3 | B8: 123456789 | C8: 123456789 | D8: 123456789
A9: 1971q4 | B9: 123456789 | C9: 123456789 | D9: 123456789
A10: 1972q1 | B10: 123456789 | C10: 123456789 | D10: 123456789
A11: 1972q2 | B11: 123456789 | C11: 123456789 | D11: 123456789
A12: 1972q3 | B12: 123456789 | C12: 123456789 | D12: 123456789
A13: 1972q4 | B13: 123456789 | C13: 123456789 | D13: 123456789
A14: 1973q1 | B14: =credit_to_gdp_all!B14-credit_to_gdp_all!B2 -> 6.2 | C14: 123456789 | D14: 123456789
A15: 1973q2 | B15: =credit_to_gdp_all!B15-credit_to_gdp_all!B3 -> 6.9 | C15: 123456789 | D15: 123456789
A16: 1973q3 | B16: =credit_to_gdp_all!B16-credit_to_gdp_all!B4 -> 8.5 | C16: 123456789 | D16: 123456789
A17: 1973q4 | B17: =credit_to_gdp_all!B17-credit_to_gdp_all!B5 -> 5.3 | C17: 123456789 | D17: 123456789
A18: 1974q1 | B18: =credit_to_gdp_all!B18-credit_to_gdp_all!B6 -> 8.1 | C18: 123456789 | D18: 123456789
A19: 1974q2 | B19: =credit_to_gdp_all!B19-credit_to_gdp_all!B7 -> 9.7 | C19: 123456789 | D19: 123456789
A20: 1974q3 | B20: =credit_to_gdp_all!B20-credit_to_gdp_all!B8 -> 7.9 | C20: 123456789 | D20: 123456789
A21: 1974q4 | B21: =credit_to_gdp_all!B21-credit_to_gdp_all!B9 -> 4.1 | C21: 123456789 | D21: 123456789
A22: 1975q1 | B22: =credit_to_gdp_all!B22-credit_to_gdp_all!B10 -> -1.1 | C22: 123456789 | D22: 123456789
A23: 1975q2 | B23: =credit_to_gdp_all!B23-credit_to_gdp_all!B11 -> -2 | C23: 123456789 | D23: 123456789
A24: 1975q3 | B24: =credit_to_gdp_all!B24-credit_to_gdp_all!B12 -> -8.2 | C24: 123456789 | D24: 123456789
A25: 1975q4 | B25: =credit_to_gdp_all!B25-credit_to_gdp_all!B13 -> -7.1 | C25: 123456789 | D25: 123456789
... A222: 2025q1 | B222: =credit_to_gdp_all!B222-credit_to_gdp_all!B210 -> -21.1 | C222: 123456789 | D222: 123456789
A223: 2025q2 | B223: -21.1 | C223: 123456789 | D223: 123456789
A224: 2025q3 | B224: -21.1 | C224: 123456789 | D224: 123456789
A225: 2025q4 | B225: -21.1 | C225: 123456789 | D225: 123456789
A226: 2026q1 | B226: -21.1 | C226: 123456789 | D226: 123456789

Sheet vix
B1: UK | C1: US | D1: EA
A2: 1970q1 | B2: 123456789 | C2: 123456789 | D2: 123456789
A3: 1970q2 | B3: 123456789 | C3: 123456789 | D3: 123456789
A4: 1970q3 | B4: =spliced_vix!E4 -> 21.595786 | C4: 123456789 | D4: 123456789
A5: 1970q4 | B5: =spliced_vix!E5 -> 15.175278 | C5: 123456789 | D5: 123456789
A6: 1971q1 | B6: =spliced_vix!E6 -> 11.803492 | C6: 123456789 | D6: 123456789
A7: 1971q2 | B7: =spliced_vix!E7 -> 13.311177 | C7: 123456789 | D7: 123456789
A8: 1971q3 | B8: =spliced_vix!E8 -> 18.546722 | C8: 123456789 | D8: 123456789
A9: 1971q4 | B9: =spliced_vix!E9 -> 19.043493 | C9: 123456789 | D9: 123456789
A10: 1972q1 | B10: =spliced_vix!E10 -> 11.343203 | C10: 123456789 | D10: 123456789
A11: 1972q2 | B11: =spliced_vix!E11 -> 12.323083 | C11: 123456789 | D11: 123456789
A12: 1972q3 | B12: =spliced_vix!E12 -> 12.810704 | C12: 123456789 | D12: 123456789
A13: 1972q4 | B13: =spliced_vix!E13 -> 13.403912 | C13: 123456789 | D13: 123456789
A14: 1973q1 | B14: =spliced_vix!E14 -> 18.145358 | C14: 123456789 | D14: 123456789
A15: 1973q2 | B15: =spliced_vix!E15 -> 25.884861 | C15: 123456789 | D15: 123456789
... A225: 2025q4 | B225: =spliced_vix!E225 -> 16.98 | C225: 123456789 | D225: 123456789
A226: 2026q1 | B226: 16.98 | C226: 123456789 | D226: 123456789

Sheet bond_spread
B1: UK | C1: US | D1: EA
A2: 1970q1 | B2: 139.3333 | C2: 123456789 | D2: 123456789
A3: 1970q2 | B3: 129.6667 | C3: 123456789 | D3: 123456789
A4: 1970q3 | B4: 130 | C4: 123456789 | D4: 123456789
A5: 1970q4 | B5: 112.3333 | C5: 123456789 | D5: 123456789
A6: 1971q1 | B6: 134.6667 | C6: 123456789 | D6: 123456789
A7: 1971q2 | B7: 129 | C7: 123456789 | D7: 123456789
A8: 1971q3 | B8: 112.3333 | C8: 123456789 | D8: 123456789
A9: 1971q4 | B9: 108.6667 | C9: 123456789 | D9: 123456789
A10: 1972q1 | B10: 84 | C10: 123456789 | D10: 123456789
A11: 1972q2 | B11: 80 | C11: 123456789 | D11: 123456789
A12: 1972q3 | B12: 78 | C12: 123456789 | D12: 123456789
A13: 1972q4 | B13: 83.33334 | C13: 123456789 | D13: 123456789
... A226: 2026q1 | B226: 88.19082 | C226: 123456789 | D226: 123456789

Sheet market_vol_uk
B1: UK | C1: US | D1: EA
A2: 1970q1 | B2: 123456789 | C2: 123456789 | D2: 123456789
A3: 1970q2 | B3: 1.760576 | C3: 123456789 | D3: 123456789
A4: 1970q3 | B4: 0.920302 | C4: 123456789 | D4: 123456789
A5: 1970q4 | B5: 0.9194848 | C5: 123456789 | D5: 123456789
A6: 1971q1 | B6: 1.075156 | C6: 123456789 | D6: 123456789
A7: 1971q2 | B7: 1.236534 | C7: 123456789 | D7: 123456789
A8: 1971q3 | B8: 1.090747 | C8: 123456789 | D8: 123456789
A9: 1971q4 | B9: 1.052805 | C9: 123456789 | D9: 123456789
A10: 1972q1 | B10: 0.8836466 | C10: 123456789 | D10: 123456789
A11: 1972q2 | B11: 0.9238148 | C11: 123456789 | D11: 123456789
A12: 1972q3 | B12: 0.9445159 | C12: 123456789 | D12: 123456789
A13: 1972q4 | B13: 0.6200079 | C13: 123456789 | D13: 123456789
... A226: 2026q1 | B226: 0.5601551 | C226: 123456789 | D226: 123456789

Sheet mrkvols&p
B1: UK | C1: US | D1: EA
A2: 1970q1 | B2: 123456789 | C2: 123456789 | D2: 123456789
A3: 1970q2 | B3: 1.386367 | C3: 123456789 | D3: 123456789
A4: 1970q3 | B4: 0.8534265 | C4: 123456789 | D4: 123456789
A5: 1970q4 | B5: 0.5996996 | C5: 123456789 | D5: 123456789
A6: 1971q1 | B6: 0.4664527 | C6: 123456789 | D6: 123456789
A7: 1971q2 | B7: 0.5260337 | C7: 123456789 | D7: 123456789
A8: 1971q3 | B8: 0.732933 | C8: 123456789 | D8: 123456789
A9: 1971q4 | B9: 0.7525645 | C9: 123456789 | D9: 123456789
A10: 1972q1 | B10: 0.4482629 | C10: 123456789 | D10: 123456789
A11: 1972q2 | B11: 0.486986 | C11: 123456789 | D11: 123456789
A12: 1972q3 | B12: 0.5062559 | C12: 123456789 | D12: 123456789
A13: 1972q4 | B13: 0.5296984 | C13: 123456789 | D13: 123456789
... A226: 2026q1 | B226: 0.6586093 | C226: 123456789 | D226: 123456789

Sheet g4oil
B1: UK | C1: US | D1: EA
A2: 1970q1 | B2: 123456789 | C2: 123456789 | D2: 123456789
A3: 1970q2 | B3: 123456789 | C3: 123456789 | D3: 123456789
A4: 1970q3 | B4: 123456789 | C4: 123456789 | D4: 123456789
A5: 1970q4 | B5: 123456789 | C5: 123456789 | D5: 123456789
A6: 1971q1 | B6: 123456789 | C6: 123456789 | D6: 123456789
A7: 1971q2 | B7: 123456789 | C7: 123456789 | D7: 123456789
A8: 1971q3 | B8: 123456789 | C8: 123456789 | D8: 123456789
A9: 1971q4 | B9: 123456789 | C9: 123456789 | D9: 123456789
A10: 1972q1 | B10: 123456789 | C10: 123456789 | D10: 123456789
A11: 1972q2 | B11: 123456789 | C11: 123456789 | D11: 123456789
A12: 1972q3 | B12: 123456789 | C12: 123456789 | D12: 123456789
A13: 1972q4 | B13: 123456789 | C13: 123456789 | D13: 123456789
... A226: 2026q1 | B226: -13.6 | C226: 123456789 | D226: 123456789

Sheet oil
B1: UK | C1: US | D1: EA
A2: 1970q1 | B2: 123456789 | C2: 123456789 | D2: 123456789
A3: 1970q2 | B3: 123456789 | C3: 123456789 | D3: 123456789
A4: 1970q3 | B4: 123456789 | C4: 123456789 | D4: 123456789
A5: 1970q4 | B5: 123456789 | C5: 123456789 | D5: 123456789
A6: 1971q1 | B6: 123456789 | C6: 123456789 | D6: 123456789
A7: 1971q2 | B7: 123456789 | C7: 123456789 | D7: 123456789
A8: 1971q3 | B8: 123456789 | C8: 123456789 | D8: 123456789
A9: 1971q4 | B9: 123456789 | C9: 123456789 | D9: 123456789
A10: 1972q1 | B10: 1.7794754 | C10: 123456789 | D10: 123456789
A11: 1972q2 | B11: 1.7794754 | C11: 123456789 | D11: 123456789
A12: 1972q3 | B12: 1.8800107 | C12: 123456789 | D12: 123456789
A13: 1972q4 | B13: 1.8800107 | C13: 123456789 | D13: 123456789
... A226: 2026q1 | B226: 68.96 | C226: 123456789 | D226: 123456789

Sheet g4oil_long
B1: UK | C1: US | D1: EA
A2: 1970q1 | B2: 123456789 | C2: 123456789 | D2: 123456789
A3: 1970q2 | B3: 123456789 | C3: 123456789 | D3: 123456789
A4: 1970q3 | B4: 123456789 | C4: 123456789 | D4: 123456789
A5: 1970q4 | B5: 123456789 | C5: 123456789 | D5: 123456789
A6: 1971q1 | B6: 123456789 | C6: 123456789 | D6: 123456789
A7: 1971q2 | B7: 123456789 | C7: 123456789 | D7: 123456789
A8: 1971q3 | B8: 123456789 | C8: 123456789 | D8: 123456789
A9: 1971q4 | B9: 123456789 | C9: 123456789 | D9: 123456789
A10: 1972q1 | B10: 123456789 | C10: 123456789 | D10: 123456789
A11: 1972q2 | B11: 123456789 | C11: 123456789 | D11: 123456789
A12: 1972q3 | B12: 123456789 | C12: 123456789 | D12: 123456789
A13: 1972q4 | B13: 123456789 | C13: 123456789 | D13: 123456789
A14: 1973q1 | B14: =(oil!B14/oil!B10-1)*100 -> 17.514124 | C14: 123456789 | D14: 123456789
A15: 1973q2 | B15: =(oil!B15/oil!B11-1)*100 -> 32.768362 | C15: 123456789 | D15: 123456789
A16: 1973q3 | B16: =(oil!B16/oil!B12-1)*100 -> 44.385027 | C16: 123456789 | D16: 123456789
A17: 1973q4 | B17: =(oil!B17/oil!B13-1)*100 -> 119.25134 | C17: 123456789 | D17: 123456789
A18: 1974q1 | B18: =(oil!B18/oil!B14-1)*100 -> 525 | C18: 123456789 | D18: 123456789
A19: 1974q2 | B19: =(oil!B19/oil!B15-1)*100 -> 351.06376 | C19: 123456789 | D19: 123456789
A20: 1974q3 | B20: =(oil!B20/oil!B16-1)*100 -> 270.37037 | C20: 123456789 | D20: 123456789
A21: 1974q4 | B21: =(oil!B21/oil!B17-1)*100 -> 151.21949 | C21: 123456789 | D21: 123456789
A22: 1975q1 | B22: =(oil!B22/oil!B18-1)*100 -> -19.846153 | C22: 123456789 | D22: 123456789
A23: 1975q2 | B23: =(oil!B23/oil!B19-1)*100 -> -1.6980983 | C23: 123456789 | D23: 123456789
A24: 1975q3 | B24: =(oil!B24/oil!B20-1)*100 -> 4.3000031 | C24: 123456789 | D24: 123456789
A25: 1975q4 | B25: =(oil!B25/oil!B21-1)*100 -> 1.553406 | C25: 123456789 | D25: 123456789
... A225: 2025q4 | B225: =(oil!B225/oil!B221-1)*100 -> -7.5727114 | C225: 123456789 | D225: 123456789
A226: 2026q1 | B226: -7.57271 | C226: 123456789 | D226: 123456789

Sheet chicago_fed_nfci
B1: UK | C1: US | D1: EA
A2: 1970q1 | B2: 123456789 | C2: 123456789 | D2: 123456789
A3: 1970q2 | B3: 123456789 | C3: 123456789 | D3: 123456789
A4: 1970q3 | B4: 123456789 | C4: 123456789 | D4: 123456789
A5: 1970q4 | B5: 123456789 | C5: 123456789 | D5: 123456789
A6: 1971q1 | B6: 0.79973 | C6: 123456789 | D6: 123456789
A7: 1971q2 | B7: 1.27451 | C7: 123456789 | D7: 123456789
A8: 1971q3 | B8: 1.59126 | C8: 123456789 | D8: 123456789
A9: 1971q4 | B9: 1.50662 | C9: 123456789 | D9: 123456789
A10: 1972q1 | B10: 0.71666 | C10: 123456789 | D10: 123456789
A11: 1972q2 | B11: 0.11249 | C11: 123456789 | D11: 123456789
A12: 1972q3 | B12: 0.14566 | C12: 123456789 | D12: 123456789
A13: 1972q4 | B13: -0.22369 | C13: 123456789 | D13: 123456789
... A226: 2026q1 | B226: -0.52879567 | C226: 123456789 | D226: 123456789

Sheet global_gdp
B1: UK | C1: US | D1: EA
A2: 1970q1 | B2: 4.0731673 | C2: 123456789 | D2: 123456789
A3: 1970q2 | B3: 4.1070519 | C3: 123456789 | D3: 123456789
A4: 1970q3 | B4: 4.154521 | C4: 123456789 | D4: 123456789
A5: 1970q4 | B5: 3.509103 | C5: 123456789 | D5: 123456789
A6: 1971q1 | B6: 3.5735927 | C6: 123456789 | D6: 123456789
A7: 1971q2 | B7: 3.5897091 | C7: 123456789 | D7: 123456789
A8: 1971q3 | B8: 3.5656042 | C8: 123456789 | D8: 123456789
A9: 1971q4 | B9: 4.0393907 | C9: 123456789 | D9: 123456789
A10: 1972q1 | B10: 4.7037798 | C10: 123456789 | D10: 123456789
A11: 1972q2 | B11: 5.3038451 | C11: 123456789 | D11: 123456789
A12: 1972q3 | B12: 5.2515232 | C12: 123456789 | D12: 123456789
A13: 1972q4 | B13: 6.5310569 | C13: 123456789 | D13: 123456789
... A226: 2026q1 | B226: 1.8335395 | C226: 123456789 | D226: 123456789

Sheet global_credit
B1: UK | C1: US | D1: EA
A2: 1970q1 | B2: 123456789 | C2: 123456789 | D2: 123456789
A3: 1970q2 | B3: 123456789 | C3: 123456789 | D3: 123456789
A4: 1970q3 | B4: 123456789 | C4: 123456789 | D4: 123456789
A5: 1970q4 | B5: 123456789 | C5: 123456789 | D5: 123456789
A6: 1971q1 | B6: 123456789 | C6: 123456789 | D6: 123456789
A7: 1971q2 | B7: 123456789 | C7: 123456789 | D7: 123456789
A8: 1971q3 | B8: 123456789 | C8: 123456789 | D8: 123456789
A9: 1971q4 | B9: 123456789 | C9: 123456789 | D9: 123456789
A10: 1972q1 | B10: 123456789 | C10: 123456789 | D10: 123456789
A11: 1972q2 | B11: 123456789 | C11: 123456789 | D11: 123456789
A12: 1972q3 | B12: 123456789 | C12: 123456789 | D12: 123456789
A13: 1972q4 | B13: 123456789 | C13: 123456789 | D13: 123456789
A14: 1973q1 | B14: =SUMPRODUCT(d3y_cre_to_gdp_all_ALL_ctry!B14:R14,uk_export_weight!B14:R14)/SUM(uk_export_weight!B14:R14) -> 4.180438 | C14: 123456789 | D14: 123456789
A15: 1973q2 | B15: =SUMPRODUCT(d3y_cre_to_gdp_all_ALL_ctry!B15:R15,uk_export_weight!B15:R15)/SUM(uk_export_weight!B15:R15) -> 4.8930319 | C15: 123456789 | D15: 123456789
A16: 1973q3 | B16: =SUMPRODUCT(d3y_cre_to_gdp_all_ALL_ctry!B16:R16,uk_export_weight!B16:R16)/SUM(uk_export_weight!B16:R16) -> 5.3447333 | C16: 123456789 | D16: 123456789
A17: 1973q4 | B17: =SUMPRODUCT(d3y_cre_to_gdp_all_ALL_ctry!B17:R17,uk_export_weight!B17:R17)/SUM(uk_export_weight!B17:R17) -> 4.6514074 | C17: 123456789 | D17: 123456789
A18: 1974q1 | B18: =SUMPRODUCT(d3y_cre_to_gdp_all_ALL_ctry!B18:R18,uk_export_weight!B18:R18)/SUM(uk_export_weight!B18:R18) -> 4.7403005 | C18: 123456789 | D18: 123456789
A19: 1974q2 | B19: =SUMPRODUCT(d3y_cre_to_gdp_all_ALL_ctry!B19:R19,uk_export_weight!B19:R19)/SUM(uk_export_weight!B19:R19) -> 4.5620524 | C19: 123456789 | D19: 123456789
A20: 1974q3 | B20: =SUMPRODUCT(d3y_cre_to_gdp_all_ALL_ctry!B20:R20,uk_export_weight!B20:R20)/SUM(uk_export_weight!B20:R20) -> 4.4059709 | C20: 123456789 | D20: 123456789
A21: 1974q4 | B21: =SUMPRODUCT(d3y_cre_to_gdp_all_ALL_ctry!B21:R21,uk_export_weight!B21:R21)/SUM(uk_export_weight!B21:R21) -> 1.9943919 | C21: 123456789 | D21: 123456789
A22: 1975q1 | B22: =SUMPRODUCT(d3y_cre_to_gdp_all_ALL_ctry!B22:R22,uk_export_weight!B22:R22)/SUM(uk_export_weight!B22:R22) -> 1.2330367 | C22: 123456789 | D22: 123456789
A23: 1975q2 | B23: =SUMPRODUCT(d3y_cre_to_gdp_all_ALL_ctry!B23:R23,uk_export_weight!B23:R23)/SUM(uk_export_weight!B23:R23) -> 0.21500381 | C23: 123456789 | D23: 123456789
A24: 1975q3 | B24: =SUMPRODUCT(d3y_cre_to_gdp_all_ALL_ctry!B24:R24,uk_export_weight!B24:R24)/SUM(uk_export_weight!B24:R24) -> -0.24933224 | C24: 123456789 | D24: 123456789
A25: 1975q4 | B25: =SUMPRODUCT(d3y_cre_to_gdp_all_ALL_ctry!B25:R25,uk_export_weight!B25:R25)/SUM(uk_export_weight!B25:R25) -> -0.0053142156 | C25: 123456789 | D25: 123456789
... A225: 2025q4 | B225: =SUMPRODUCT(d3y_cre_to_gdp_all_ALL_ctry!B225:R225,uk_export_weight!B225:R225)/SUM(uk_export_weight!B225:R225) -> -11.590124 | C225: 123456789 | D225: 123456789
A226: 2026q1 | B226: -11.5901 | C226: 123456789 | D226: 123456789

Sheet global_credit_level
B1: UK | C1: US | D1: EA
A2: 1970q1 | B2: 123456789 | C2: 123456789 | D2: 123456789
A3: 1970q2 | B3: 123456789 | C3: 123456789 | D3: 123456789
A4: 1970q3 | B4: 123456789 | C4: 123456789 | D4: 123456789
A5: 1970q4 | B5: 123456789 | C5: 123456789 | D5: 123456789
A6: 1971q1 | B6: 123456789 | C6: 123456789 | D6: 123456789
A7: 1971q2 | B7: 123456789 | C7: 123456789 | D7: 123456789
A8: 1971q3 | B8: 123456789 | C8: 123456789 | D8: 123456789
A9: 1971q4 | B9: 123456789 | C9: 123456789 | D9: 123456789
A10: 1972q1 | B10: 123456789 | C10: 123456789 | D10: 123456789
A11: 1972q2 | B11: 123456789 | C11: 123456789 | D11: 123456789
A12: 1972q3 | B12: 123456789 | C12: 123456789 | D12: 123456789
A13: 1972q4 | B13: 123456789 | C13: 123456789 | D13: 123456789
A14: 1973q1 | B14: =SUMPRODUCT(credit_to_gdp_ALL_ctry!B14:R14,uk_export_weight!B14:R14)/SUM(uk_export_weight!B14:R14) -> 98.407927 | C14: 123456789 | D14: 123456789
A15: 1973q2 | B15: =SUMPRODUCT(credit_to_gdp_ALL_ctry!B15:R15,uk_export_weight!B15:R15)/SUM(uk_export_weight!B15:R15) -> 99.090243 | C15: 123456789 | D15: 123456789
A16: 1973q3 | B16: =SUMPRODUCT(credit_to_gdp_ALL_ctry!B16:R16,uk_export_weight!B16:R16)/SUM(uk_export_weight!B16:R16) -> 99.0999 | C16: 123456789 | D16: 123456789
A17: 1973q4 | B17: =SUMPRODUCT(credit_to_gdp_ALL_ctry!B17:R17,uk_export_weight!B17:R17)/SUM(uk_export_weight!B17:R17) -> 99.513727 | C17: 123456789 | D17: 123456789
A18: 1974q1 | B18: =SUMPRODUCT(credit_to_gdp_ALL_ctry!B18:R18,uk_export_weight!B18:R18)/SUM(uk_export_weight!B18:R18) -> 98.922895 | C18: 123456789 | D18: 123456789
A19: 1974q2 | B19: =SUMPRODUCT(credit_to_gdp_ALL_ctry!B19:R19,uk_export_weight!B19:R19)/SUM(uk_export_weight!B19:R19) -> 99.406705 | C19: 123456789 | D19: 123456789
A20: 1974q3 | B20: =SUMPRODUCT(credit_to_gdp_ALL_ctry!B20:R20,uk_export_weight!B20:R20)/SUM(uk_export_weight!B20:R20) -> 99.216343 | C20: 123456789 | D20: 123456789
A21: 1974q4 | B21: =SUMPRODUCT(credit_to_gdp_ALL_ctry!B21:R21,uk_export_weight!B21:R21)/SUM(uk_export_weight!B21:R21) -> 97.883943 | C21: 123456789 | D21: 123456789
A22: 1975q1 | B22: =SUMPRODUCT(credit_to_gdp_ALL_ctry!B22:R22,uk_export_weight!B22:R22)/SUM(uk_export_weight!B22:R22) -> 97.585256 | C22: 123456789 | D22: 123456789
A23: 1975q2 | B23: =SUMPRODUCT(credit_to_gdp_ALL_ctry!B23:R23,uk_export_weight!B23:R23)/SUM(uk_export_weight!B23:R23) -> 97.829918 | C23: 123456789 | D23: 123456789
A24: 1975q3 | B24: =SUMPRODUCT(credit_to_gdp_ALL_ctry!B24:R24,uk_export_weight!B24:R24)/SUM(uk_export_weight!B24:R24) -> 97.588939 | C24: 123456789 | D24: 123456789
A25: 1975q4 | B25: =SUMPRODUCT(credit_to_gdp_ALL_ctry!B25:R25,uk_export_weight!B25:R25)/SUM(uk_export_weight!B25:R25) -> 99.005247 | C25: 123456789 | D25: 123456789
... A226: 2026q1 | B226: =SUMPRODUCT(credit_to_gdp_ALL_ctry!B226:R226,uk_export_weight!B226:R226)/SUM(uk_export_weight!B226:R226) -> 166.15522 | C226: 123456789 | D226: 123456789

Sheet global_credit_level_2y_gr
B1: UK | C1: US | D1: EA
A2: 1970q1 | B2: 123456789 | C2: 123456789 | D2: 123456789
A3: 1970q2 | B3: 123456789 | C3: 123456789 | D3: 123456789
A4: 1970q3 | B4: 123456789 | C4: 123456789 | D4: 123456789
A5: 1970q4 | B5: 123456789 | C5: 123456789 | D5: 123456789
A6: 1971q1 | B6: 123456789 | C6: 123456789 | D6: 123456789
A7: 1971q2 | B7: 123456789 | C7: 123456789 | D7: 123456789
A8: 1971q3 | B8: 123456789 | C8: 123456789 | D8: 123456789
A9: 1971q4 | B9: 123456789 | C9: 123456789 | D9: 123456789
A10: 1972q1 | B10: 123456789 | C10: 123456789 | D10: 123456789
A11: 1972q2 | B11: 123456789 | C11: 123456789 | D11: 123456789
A12: 1972q3 | B12: 123456789 | C12: 123456789 | D12: 123456789
A13: 1972q4 | B13: 123456789 | C13: 123456789 | D13: 123456789
A14: 1973q1 | C14: 123456789 | D14: 123456789
A15: 1973q2 | C15: 123456789 | D15: 123456789
A16: 1973q3 | C16: 123456789 | D16: 123456789
A17: 1973q4 | C17: 123456789 | D17: 123456789
A18: 1974q1 | C18: 123456789 | D18: 123456789
A19: 1974q2 | C19: 123456789 | D19: 123456789
A20: 1974q3 | C20: 123456789 | D20: 123456789
A21: 1974q4 | C21: 123456789 | D21: 123456789
A22: 1975q1 | B22: =(LN(global_credit_level!B22)-LN(global_credit_level!B14)) * 100 -> -0.83949339 | C22: 123456789 | D22: 123456789
A23: 1975q2 | B23: =(LN(global_credit_level!B23)-LN(global_credit_level!B15)) * 100 -> -1.2800532 | C23: 123456789 | D23: 123456789
A24: 1975q3 | B24: =(LN(global_credit_level!B24)-LN(global_credit_level!B16)) * 100 -> -1.5364279 | C24: 123456789 | D24: 123456789
A25: 1975q4 | B25: =(LN(global_credit_level!B25)-LN(global_credit_level!B17)) * 100 -> -0.51227411 | C25: 123456789 | D25: 123456789
A26: 1976q1 | B26: =(LN(global_credit_level!B26)-LN(global_credit_level!B18)) * 100 -> -1.7192153 | C26: 123456789 | D26: 123456789
A27: 1976q2 | B27: =(LN(global_credit_level!B27)-LN(global_credit_level!B19)) * 100 -> -2.220838 | C27: 123456789 | D27: 123456789
A28: 1976q3 | B28: =(LN(global_credit_level!B28)-LN(global_credit_level!B20)) * 100 -> -2.3296215 | C28: 123456789 | D28: 123456789
A29: 1976q4 | B29: =(LN(global_credit_level!B29)-LN(global_credit_level!B21)) * 100 -> -0.45929513 | C29: 123456789 | D29: 123456789
A30: 1977q1 | B30: =(LN(global_credit_level!B30)-LN(global_credit_level!B22)) * 100 -> -0.58296111 | C30: 123456789 | D30: 123456789
A31: 1977q2 | B31: =(LN(global_credit_level!B31)-LN(global_credit_level!B23)) * 100 -> -0.1678479 | C31: 123456789 | D31: 123456789
A32: 1977q3 | B32: =(LN(global_credit_level!B32)-LN(global_credit_level!B24)) * 100 -> 0.15210616 | C32: 123456789 | D32: 123456789
A33: 1977q4 | B33: =(LN(global_credit_level!B33)-LN(global_credit_level!B25)) * 100 -> 0.098213392 | C33: 123456789 | D33: 123456789
... A226: 2026q1 | B226: =(LN(global_credit_level!B226)-LN(global_credit_level!B218)) * 100 -> -1.9493369 | C226: 123456789 | D226: 123456789

Sheet pmi_out
B1: UK | C1: US | D1: EA
A2: 1970q1 | B2: 123456789 | C2: 123456789 | D2: 123456789
A3: 1970q2 | B3: 123456789 | C3: 123456789 | D3: 123456789
A4: 1970q3 | B4: 123456789 | C4: 123456789 | D4: 123456789
A5: 1970q4 | B5: 123456789 | C5: 123456789 | D5: 123456789
A6: 1971q1 | B6: 123456789 | C6: 123456789 | D6: 123456789
A7: 1971q2 | B7: 123456789 | C7: 123456789 | D7: 123456789
A8: 1971q3 | B8: 123456789 | C8: 123456789 | D8: 123456789
A9: 1971q4 | B9: 123456789 | C9: 123456789 | D9: 123456789
A10: 1972q1 | B10: 123456789 | C10: 123456789 | D10: 123456789
A11: 1972q2 | B11: 123456789 | C11: 123456789 | D11: 123456789
A12: 1972q3 | B12: 123456789 | C12: 123456789 | D12: 123456789
A13: 1972q4 | B13: 123456789 | C13: 123456789 | D13: 123456789
... A80: 1989q3 | B80: 123456789 | C80: 123456789 | D80: 123456789
A81: 1989q4 | B81: =spliced_quartely_pmi!D81 -> 52.536467 | C81: 123456789 | D81: 123456789
A82: 1990q1 | B82: =spliced_quartely_pmi!D82 -> 54.156892 | C82: 123456789 | D82: 123456789
A83: 1990q2 | B83: =spliced_quartely_pmi!D83 -> 55.090246 | C83: 123456789 | D83: 123456789
A84: 1990q3 | B84: =spliced_quartely_pmi!D84 -> 54.285789 | C84: 123456789 | D84: 123456789
A85: 1990q4 | B85: =spliced_quartely_pmi!D85 -> 50.240485 | C85: 123456789 | D85: 123456789
A86: 1991q1 | B86: =spliced_quartely_pmi!D86 -> 54.551639 | C86: 123456789 | D86: 123456789
A87: 1991q2 | B87: =spliced_quartely_pmi!D87 -> 54.524018 | C87: 123456789 | D87: 123456789
A88: 1991q3 | B88: =spliced_quartely_pmi!D88 -> 53.328267 | C88: 123456789 | D88: 123456789
A89: 1991q4 | B89: =spliced_quartely_pmi!D89 -> 53.347829 | C89: 123456789 | D89: 123456789
A90: 1992q1 | B90: =spliced_quartely_pmi!D90 -> 55.435506 | C90: 123456789 | D90: 123456789
A91: 1992q2 | B91: =spliced_quartely_pmi!D91 -> 55.223748 | C91: 123456789 | D91: 123456789
A92: 1992q3 | B92: =spliced_quartely_pmi!D92 -> 53.03019 | C92: 123456789 | D92: 123456789
... A224: 2025q3 | B224: =spliced_quartely_pmi!D224 -> 51.67 | C224: 123456789 | D224: 123456789
A225: 2025q4 | B225: 51.67 | C225: 123456789 | D225: 123456789
A226: 2026q1 | B226: 51.67 | C226: 123456789 | D226: 123456789

Sheet pmi_out_long
B1: UK | C1: US | D1: EA
A2: 1970q1 | B2: 123456789 | C2: 123456789 | D2: 123456789
A3: 1970q2 | B3: 123456789 | C3: 123456789 | D3: 123456789
A4: 1970q3 | B4: 123456789 | C4: 123456789 | D4: 123456789
A5: 1970q4 | B5: 123456789 | C5: 123456789 | D5: 123456789
A6: 1971q1 | B6: =spliced_quartely_pmi_long!D6 -> 56.070287 | C6: 123456789 | D6: 123456789
A7: 1971q2 | B7: =spliced_quartely_pmi_long!D7 -> 55.457302 | C7: 123456789 | D7: 123456789
A8: 1971q3 | B8: =spliced_quartely_pmi_long!D8 -> 56.229196 | C8: 123456789 | D8: 123456789
A9: 1971q4 | B9: =spliced_quartely_pmi_long!D9 -> 55.668121 | C9: 123456789 | D9: 123456789
A10: 1972q1 | B10: =spliced_quartely_pmi_long!D10 -> 56.391201 | C10: 123456789 | D10: 123456789
A11: 1972q2 | B11: =spliced_quartely_pmi_long!D11 -> 57.257845 | C11: 123456789 | D11: 123456789
A12: 1972q3 | B12: =spliced_quartely_pmi_long!D12 -> 55.774768 | C12: 123456789 | D12: 123456789
A13: 1972q4 | B13: =spliced_quartely_pmi_long!D13 -> 56.982972 | C13: 123456789 | D13: 123456789
A14: 1973q1 | B14: =spliced_quartely_pmi_long!D14 -> 61.759308 | C14: 123456789 | D14: 123456789
A15: 1973q2 | B15: =spliced_quartely_pmi_long!D15 -> 59.23671 | C15: 123456789 | D15: 123456789
A16: 1973q3 | B16: =spliced_quartely_pmi_long!D16 -> 57.979226 | C16: 123456789 | D16: 123456789
A17: 1973q4 | B17: =spliced_quartely_pmi_long!D17 -> 55.960963 | C17: 123456789 | D17: 123456789
... A224: 2025q3 | B224: =spliced_quartely_pmi_long!D224 -> 51.67 | C224: 123456789 | D224: 123456789
A225: 2025q4 | B225: 51.67 | C225: 123456789 | D225: 123456789
A226: 2026q1 | B226: 51.67 | C226: 123456789 | D226: 123456789

Sheet pmi_out_fut_long
B1: UK | C1: US | D1: EA
A2: 1970q1 | B2: 123456789 | C2: 123456789 | D2: 123456789
A3: 1970q2 | B3: 123456789 | C3: 123456789 | D3: 123456789
A4: 1970q3 | B4: 123456789 | C4: 123456789 | D4: 123456789
A5: 1970q4 | B5: 123456789 | C5: 123456789 | D5: 123456789
A6: 1971q1 | B6: =spliced_quartely_pmi_long!G6 -> 70.100758 | C6: 123456789 | D6: 123456789
A7: 1971q2 | B7: =spliced_quartely_pmi_long!G7 -> 69.323792 | C7: 123456789 | D7: 123456789
A8: 1971q3 | B8: =spliced_quartely_pmi_long!G8 -> 70.302178 | C8: 123456789 | D8: 123456789
A9: 1971q4 | B9: =spliced_quartely_pmi_long!G9 -> 69.591008 | C9: 123456789 | D9: 123456789
A10: 1972q1 | B10: =spliced_quartely_pmi_long!G10 -> 70.507522 | C10: 123456789 | D10: 123456789
A11: 1972q2 | B11: =spliced_quartely_pmi_long!G11 -> 71.606004 | C11: 123456789 | D11: 123456789
A12: 1972q3 | B12: =spliced_quartely_pmi_long!G12 -> 69.726184 | C12: 123456789 | D12: 123456789
A13: 1972q4 | B13: =spliced_quartely_pmi_long!G13 -> 71.257599 | C13: 123456789 | D13: 123456789
A14: 1973q1 | B14: =spliced_quartely_pmi_long!G14 -> 77.311669 | C14: 123456789 | D14: 123456789
A15: 1973q2 | B15: =spliced_quartely_pmi_long!G15 -> 74.114242 | C15: 123456789 | D15: 123456789
A16: 1973q3 | B16: =spliced_quartely_pmi_long!G16 -> 72.520364 | C16: 123456789 | D16: 123456789
A17: 1973q4 | B17: =spliced_quartely_pmi_long!G17 -> 69.962189 | C17: 123456789 | D17: 123456789
... A224: 2025q3 | B224: =spliced_quartely_pmi_long!G224 -> 66.791365 | C224: 123456789 | D224: 123456789
A225: 2025q4 | B225: 66.79 | C225: 123456789 | D225: 123456789
A226: 2026q1 | B226: 66.79 | C226: 123456789 | D226: 123456789

Sheet pmi_out_fut
B1: UK | C1: US | D1: EA
A2: 1970q1 | B2: 123456789 | C2: 123456789 | D2: 123456789
A3: 1970q2 | B3: 123456789 | C3: 123456789 | D3: 123456789
A4: 1970q3 | B4: 123456789 | C4: 123456789 | D4: 123456789
A5: 1970q4 | B5: 123456789 | C5: 123456789 | D5: 123456789
A6: 1971q1 | B6: 123456789 | C6: 123456789 | D6: 123456789
A7: 1971q2 | B7: 123456789 | C7: 123456789 | D7: 123456789
A8: 1971q3 | B8: 123456789 | C8: 123456789 | D8: 123456789
A9: 1971q4 | B9: 123456789 | C9: 123456789 | D9: 123456789
A10: 1972q1 | B10: 123456789 | C10: 123456789 | D10: 123456789
A11: 1972q2 | B11: 123456789 | C11: 123456789 | D11: 123456789
A12: 1972q3 | B12: 123456789 | C12: 123456789 | D12: 123456789
A13: 1972q4 | B13: 123456789 | C13: 123456789 | D13: 123456789
... A80: 1989q3 | B80: 123456789 | C80: 123456789 | D80: 123456789
A81: 1989q4 | B81: =spliced_quartely_pmi!G81 -> 65.448229 | C81: 123456789 | D81: 123456789
A82: 1990q1 | B82: =spliced_quartely_pmi!G82 -> 67.688822 | C82: 123456789 | D82: 123456789
A83: 1990q2 | B83: =spliced_quartely_pmi!G83 -> 68.979388 | C83: 123456789 | D83: 123456789
A84: 1990q3 | B84: =spliced_quartely_pmi!G84 -> 67.867049 | C84: 123456789 | D84: 123456789
A85: 1990q4 | B85: =spliced_quartely_pmi!G85 -> 62.27353 | C85: 123456789 | D85: 123456789
A86: 1991q1 | B86: =spliced_quartely_pmi!G86 -> 68.234646 | C86: 123456789 | D86: 123456789
A87: 1991q2 | B87: =spliced_quartely_pmi!G87 -> 68.196454 | C87: 123456789 | D87: 123456789
A88: 1991q3 | B88: =spliced_quartely_pmi!G88 -> 66.543066 | C88: 123456789 | D88: 123456789
A89: 1991q4 | B89: =spliced_quartely_pmi!G89 -> 66.570115 | C89: 123456789 | D89: 123456789
A90: 1992q1 | B90: =spliced_quartely_pmi!G90 -> 69.456786 | C90: 123456789 | D90: 123456789
A91: 1992q2 | B91: =spliced_quartely_pmi!G91 -> 69.163983 | C91: 123456789 | D91: 123456789
A92: 1992q3 | B92: =spliced_quartely_pmi!G92 -> 66.130909 | C92: 123456789 | D92: 123456789
... A224: 2025q3 | B224: =spliced_quartely_pmi!G224 -> 66.791365 | C224: 123456789 | D224: 123456789
A225: 2025q4 | B225: 66.79 | C225: 123456789 | D225: 123456789

Sheet ciss_uk
B1: UK | C1: US | D1: EA
A2: 1970q1 | B2: 123456789 | C2: 123456789 | D2: 123456789
A3: 1970q2 | B3: 123456789 | C3: 123456789 | D3: 123456789
A4: 1970q3 | B4: 123456789 | C4: 123456789 | D4: 123456789
A5: 1970q4 | B5: 123456789 | C5: 123456789 | D5: 123456789
A6: 1971q1 | B6: 123456789 | C6: 123456789 | D6: 123456789
A7: 1971q2 | B7: 123456789 | C7: 123456789 | D7: 123456789
A8: 1971q3 | B8: 123456789 | C8: 123456789 | D8: 123456789
A9: 1971q4 | B9: 123456789 | C9: 123456789 | D9: 123456789
A10: 1972q1 | B10: 123456789 | C10: 123456789 | D10: 123456789
A11: 1972q2 | B11: 123456789 | C11: 123456789 | D11: 123456789
A12: 1972q3 | B12: 123456789 | C12: 123456789 | D12: 123456789
A13: 1972q4 | B13: 123456789 | C13: 123456789 | D13: 123456789
... A226: 2026Q1 | B226: 0.0253 | C226: 123456789 | D226: 123456789

Sheet yield_curve_slope
B1: UK | C1: US | D1: EA
A2: 1970q1 | B2: 123456789 | C2: 123456789 | D2: 123456789
A3: 1970q2 | B3: 123456789 | C3: 123456789 | D3: 123456789
A4: 1970q3 | B4: 123456789 | C4: 123456789 | D4: 123456789
A5: 1970q4 | B5: 123456789 | C5: 123456789 | D5: 123456789
A6: 1971q1 | B6: 123456789 | C6: 123456789 | D6: 123456789
A7: 1971q2 | B7: 123456789 | C7: 123456789 | D7: 123456789
A8: 1971q3 | B8: 123456789 | C8: 123456789 | D8: 123456789
A9: 1971q4 | B9: 123456789 | C9: 123456789 | D9: 123456789
A10: 1972q1 | B10: 123456789 | C10: 123456789 | D10: 123456789
A11: 1972q2 | B11: 123456789 | C11: 123456789 | D11: 123456789
A12: 1972q3 | B12: 123456789 | C12: 123456789 | D12: 123456789
A13: 1972q4 | B13: 123456789 | C13: 123456789 | D13: 123456789
... A226: 2026q1 | B226: 0.92551168 | C226: 123456789 | D226: 123456789

Sheet inflation_expectations
B1: UK | C1: US | D1: EA
A2: 1970q1 | B2: =spliced_inflation_expectations!D2 -> 3.1158753 | C2: 123456789 | D2: 123456789
A3: 1970q2 | B3: =spliced_inflation_expectations!D3 -> 3.4165041 | C3: 123456789 | D3: 123456789
A4: 1970q3 | B4: =spliced_inflation_expectations!D4 -> 3.7570635 | C4: 123456789 | D4: 123456789
A5: 1970q4 | B5: =spliced_inflation_expectations!D5 -> 4.0588898 | C5: 123456789 | D5: 123456789
A6: 1971q1 | B6: =spliced_inflation_expectations!D6 -> 4.368516 | C6: 123456789 | D6: 123456789
A7: 1971q2 | B7: =spliced_inflation_expectations!D7 -> 4.8084085 | C7: 123456789 | D7: 123456789
A8: 1971q3 | B8: =spliced_inflation_expectations!D8 -> 4.902495 | C8: 123456789 | D8: 123456789
A9: 1971q4 | B9: =spliced_inflation_expectations!D9 -> 4.5872411 | C9: 123456789 | D9: 123456789
A10: 1972q1 | B10: =spliced_inflation_expectations!D10 -> 4.1464907 | C10: 123456789 | D10: 123456789
A11: 1972q2 | B11: =spliced_inflation_expectations!D11 -> 3.5246809 | C11: 123456789 | D11: 123456789
A12: 1972q3 | B12: =spliced_inflation_expectations!D12 -> 3.6231574 | C12: 123456789 | D12: 123456789
A13: 1972q4 | B13: =spliced_inflation_expectations!D13 -> 4.0628577 | C13: 123456789 | D13: 123456789
... A224: 2025q3 | B224: =spliced_inflation_expectations!D224 -> 2.4864667 | C224: 123456789 | D224: 123456789
A225: 2025q4 | B225: 2.49 | C225: 123456789 | D225: 123456789
A226: 2026q1 | B226: 2.49 | C226: 123456789 | D226: 123456789

Sheet import_deflator_fuel
B1: UK | C1: US | D1: EA
A2: 1970q1 | B2: 123456789 | C2: 123456789 | D2: 123456789
A3: 1970q2 | B3: 123456789 | C3: 123456789 | D3: 123456789
A4: 1970q3 | B4: 123456789 | C4: 123456789 | D4: 123456789
A5: 1970q4 | B5: 123456789 | C5: 123456789 | D5: 123456789
A6: 1971q1 | B6: 123456789 | C6: 123456789 | D6: 123456789
A7: 1971q2 | B7: 123456789 | C7: 123456789 | D7: 123456789
A8: 1971q3 | B8: 123456789 | C8: 123456789 | D8: 123456789
A9: 1971q4 | B9: 123456789 | C9: 123456789 | D9: 123456789
A10: 1972q1 | B10: 123456789 | C10: 123456789 | D10: 123456789
A11: 1972q2 | B11: 123456789 | C11: 123456789 | D11: 123456789
A12: 1972q3 | B12: 123456789 | C12: 123456789 | D12: 123456789
A13: 1972q4 | B13: 123456789 | C13: 123456789 | D13: 123456789
... A226: 2026q1 | B226: 70.4 | C226: 123456789 | D226: 123456789

Sheet g4_import_deflator_fuel
B1: UK | C1: US | D1: EA
A2: 1970q1 | B2: 123456789 | C2: 123456789 | D2: 123456789
A3: 1970q2 | B3: 123456789 | C3: 123456789 | D3: 123456789
A4: 1970q3 | B4: 123456789 | C4: 123456789 | D4: 123456789
A5: 1970q4 | B5: 123456789 | C5: 123456789 | D5: 123456789
A6: 1971q1 | B6: 123456789 | C6: 123456789 | D6: 123456789
A7: 1971q2 | B7: 123456789 | C7: 123456789 | D7: 123456789
A8: 1971q3 | B8: 123456789 | C8: 123456789 | D8: 123456789
A9: 1971q4 | B9: 123456789 | C9: 123456789 | D9: 123456789
A10: 1972q1 | B10: 123456789 | C10: 123456789 | D10: 123456789
A11: 1972q2 | B11: 123456789 | C11: 123456789 | D11: 123456789
A12: 1972q3 | B12: 123456789 | C12: 123456789 | D12: 123456789
A13: 1972q4 | B13: 123456789 | C13: 123456789 | D13: 123456789
... A45: 1980q4 | B45: 23.278848 | C45: 123456789 | D45: 123456789
A46: 1981q1 | B46: =(import_deflator_fuel!B46/import_deflator_fuel!B42-1)*100 -> 23.278848 | C46: 123456789 | D46: 123456789
A47: 1981q2 | B47: =(import_deflator_fuel!B47/import_deflator_fuel!B43-1)*100 -> 20.142311 | C47: 123456789 | D47: 123456789
A48: 1981q3 | B48: =(import_deflator_fuel!B48/import_deflator_fuel!B44-1)*100 -> 29.856899 | C48: 123456789 | D48: 123456789
A49: 1981q4 | B49: =(import_deflator_fuel!B49/import_deflator_fuel!B45-1)*100 -> 30.562665 | C49: 123456789 | D49: 123456789
A50: 1982q1 | B50: =(import_deflator_fuel!B50/import_deflator_fuel!B46-1)*100 -> 27.375789 | C50: 123456789 | D50: 123456789
A51: 1982q2 | B51: =(import_deflator_fuel!B51/import_deflator_fuel!B47-1)*100 -> 13.194066 | C51: 123456789 | D51: 123456789
A52: 1982q3 | B52: =(import_deflator_fuel!B52/import_deflator_fuel!B48-1)*100 -> 8.8647395 | C52: 123456789 | D52: 123456789
A53: 1982q4 | B53: =(import_deflator_fuel!B53/import_deflator_fuel!B49-1)*100 -> 10.683395 | C53: 123456789 | D53: 123456789
A54: 1983q1 | B54: =(import_deflator_fuel!B54/import_deflator_fuel!B50-1)*100 -> 7.4071003 | C54: 123456789 | D54: 123456789
A55: 1983q2 | B55: =(import_deflator_fuel!B55/import_deflator_fuel!B51-1)*100 -> 6.9993786 | C55: 123456789 | D55: 123456789
A56: 1983q3 | B56: =(import_deflator_fuel!B56/import_deflator_fuel!B52-1)*100 -> 3.7753414 | C56: 123456789 | D56: 123456789
A57: 1983q4 | B57: =(import_deflator_fuel!B57/import_deflator_fuel!B53-1)*100 -> 0.43723199 | C57: 123456789 | D57: 123456789
... A225: 2025q4 | B225: =(import_deflator_fuel!B225/import_deflator_fuel!B221-1)*100 -> -14.146341 | C225: 123456789 | D225: 123456789
A226: 2026q1 | B226: -14.1463 | C226: 123456789 | D226: 123456789

Sheet mgdp_yoy
B1: UK | C1: US | D1: EA
A2: 1970q1 | B2: 123456789 | C2: 123456789 | D2: 123456789
A3: 1970q2 | B3: 123456789 | C3: 123456789 | D3: 123456789
A4: 1970q3 | B4: 123456789 | C4: 123456789 | D4: 123456789
A5: 1970q4 | B5: 123456789 | C5: 123456789 | D5: 123456789
A6: 1971q1 | B6: =spliced_mgdp!D7 -> 0.03229202 | C6: 123456789 | D6: 123456789
A7: 1971q2 | B7: =spliced_mgdp!D8 -> 0.039711773 | C7: 123456789 | D7: 123456789
A8: 1971q3 | B8: =spliced_mgdp!D9 -> 0.034318492 | C8: 123456789 | D8: 123456789
A9: 1971q4 | B9: =spliced_mgdp!D10 -> 0.041269027 | C9: 123456789 | D9: 123456789
A10: 1972q1 | B10: =spliced_mgdp!D11 -> 0.049599546 | C10: 123456789 | D10: 123456789
A11: 1972q2 | B11: =spliced_mgdp!D12 -> 0.035343623 | C11: 123456789 | D11: 123456789
A12: 1972q3 | B12: =spliced_mgdp!D13 -> 0.046957358 | C12: 123456789 | D12: 123456789
A13: 1972q4 | B13: =spliced_mgdp!D14 -> 0.092869392 | C13: 123456789 | D13: 123456789
A14: 1973q1 | B14: =spliced_mgdp!D15 -> 0.068621181 | C14: 123456789 | D14: 123456789
A15: 1973q2 | B15: =spliced_mgdp!D16 -> 0.056533745 | C15: 123456789 | D15: 123456789
A16: 1973q3 | B16: =spliced_mgdp!D17 -> 0.037133409 | C16: 123456789 | D16: 123456789
A17: 1973q4 | B17: =spliced_mgdp!D18 -> -0.039200183 | C17: 123456789 | D17: 123456789
... A223: 2025q2 | B223: =spliced_mgdp!D224 -> 0.013326752 | C223: 123456789 | D223: 123456789
A224: 2025q3 | B224: 0.013326752 | C224: 123456789 | D224: 123456789
A225: 2025q4 | B225: 0.0092 | C225: 123456789 | D225: 123456789
A226: 2026q1 | B226: 0.0092 | C226: 123456789 | D226: 123456789

Sheet epu_idx
B1: UK | C1: US | D1: EA
A2: 1970q1 | B2: 71.60111 | C2: 123456789 | D2: 123456789
A3: 1970q2 | B3: 86.8982 | C3: 123456789 | D3: 123456789
A4: 1970q3 | B4: 71.28686 | C4: 123456789 | D4: 123456789
A5: 1970q4 | B5: 84.94344 | C5: 123456789 | D5: 123456789
A6: 1971q1 | B6: 87.18849 | C6: 123456789 | D6: 123456789
A7: 1971q2 | B7: 104.146 | C7: 123456789 | D7: 123456789
A8: 1971q3 | B8: 103.2461 | C8: 123456789 | D8: 123456789
A9: 1971q4 | B9: 113.4893 | C9: 123456789 | D9: 123456789
A10: 1972q1 | B10: 108.6299 | C10: 123456789 | D10: 123456789
A11: 1972q2 | B11: 101.6652 | C11: 123456789 | D11: 123456789
A12: 1972q3 | B12: 108.9231 | C12: 123456789 | D12: 123456789
A13: 1972q4 | B13: 100.5814 | C13: 123456789 | D13: 123456789
... A226: 2026q1 | B226: 307.40158 | C226: 123456789 | D226: 123456789

Sheet house_price_growth
B1: UK | C1: US | D1: EA
A2: 1970q1 | B2: 0.1497 | C2: 123456789 | D2: 123456789
A3: 1970q2 | B3: -3.1935 | C3: 123456789 | D3: 123456789
A4: 1970q3 | B4: 0.6825 | C4: 123456789 | D4: 123456789
A5: 1970q4 | B5: -2.3023 | C5: 123456789 | D5: 123456789
A6: 1971q1 | B6: -0.8242 | C6: 123456789 | D6: 123456789
A7: 1971q2 | B7: 0.7281 | C7: 123456789 | D7: 123456789
A8: 1971q3 | B8: 1.6004 | C8: 123456789 | D8: 123456789
A9: 1971q4 | B9: 7.2469 | C9: 123456789 | D9: 123456789
A10: 1972q1 | B10: 12.5296 | C10: 123456789 | D10: 123456789
A11: 1972q2 | B11: 22.093 | C11: 123456789 | D11: 123456789
A12: 1972q3 | B12: 30.8904 | C12: 123456789 | D12: 123456789
A13: 1972q4 | B13: 33.2083 | C13: 123456789 | D13: 123456789
... A226: 2026q1 | B226: -0.636 | C226: 123456789 | D226: 123456789

Sheet ln_housing_approvals
B1: UK | C1: US | D1: EA
A2: 1970q1 | B2: =LN(housing_approvals!B2) -> 12.266341 | C2: 123456789 | D2: 123456789
A3: 1970q2 | B3: =LN(housing_approvals!B3) -> 12.145177 | C3: 123456789 | D3: 123456789
A4: 1970q3 | B4: =LN(housing_approvals!B4) -> 12.284364 | C4: 123456789 | D4: 123456789
A5: 1970q4 | B5: =LN(housing_approvals!B5) -> 12.178938 | C5: 123456789 | D5: 123456789
A6: 1971q1 | B6: =LN(housing_approvals!B6) -> 12.232535 | C6: 123456789 | D6: 123456789
A7: 1971q2 | B7: =LN(housing_approvals!B7) -> 12.285891 | C7: 123456789 | D7: 123456789
A8: 1971q3 | B8: =LN(housing_approvals!B8) -> 12.31467 | C8: 123456789 | D8: 123456789
A9: 1971q4 | B9: =LN(housing_approvals!B9) -> 12.483261 | C9: 123456789 | D9: 123456789
A10: 1972q1 | B10: =LN(housing_approvals!B10) -> 12.618797 | C10: 123456789 | D10: 123456789
A11: 1972q2 | B11: =LN(housing_approvals!B11) -> 12.825373 | C11: 123456789 | D11: 123456789
A12: 1972q3 | B12: =LN(housing_approvals!B12) -> 12.983817 | C12: 123456789 | D12: 123456789
A13: 1972q4 | B13: =LN(housing_approvals!B13) -> 13.021698 | C13: 123456789 | D13: 123456789
... A225: 2025q4 | B225: =LN(housing_approvals!B225) -> 12.148375 | C225: 123456789 | D225: 123456789
A226: 2026q1 | B226: 12.14837 | C226: 123456789 | D226: 123456789

Sheet housing_approvals
B1: UK | C1: US | D1: EA
A2: 1970q1 | B2: =spliced_housing_approvals!D2 -> 212424.41 | C2: 123456789 | D2: 123456789
A3: 1970q2 | B3: =spliced_housing_approvals!D3 -> 188184.35 | C3: 123456789 | D3: 123456789
A4: 1970q3 | B4: =spliced_housing_approvals!D4 -> 216287.5 | C4: 123456789 | D4: 123456789
A5: 1970q4 | B5: =spliced_housing_approvals!D5 -> 194646.05 | C5: 123456789 | D5: 123456789
A6: 1971q1 | B6: =spliced_housing_approvals!D6 -> 205363.09 | C6: 123456789 | D6: 123456789
A7: 1971q2 | B7: =spliced_housing_approvals!D7 -> 216618.13 | C7: 123456789 | D7: 123456789
A8: 1971q3 | B8: =spliced_housing_approvals!D8 -> 222942.79 | C8: 123456789 | D8: 123456789
A9: 1971q4 | B9: =spliced_housing_approvals!D9 -> 263883.05 | C9: 123456789 | D9: 123456789
A10: 1972q1 | B10: =spliced_housing_approvals!D10 -> 302185.56 | C10: 123456789 | D10: 123456789
A11: 1972q2 | B11: =spliced_housing_approvals!D11 -> 371525.52 | C11: 123456789 | D11: 123456789
A12: 1972q3 | B12: =spliced_housing_approvals!D12 -> 435311.56 | C12: 123456789 | D12: 123456789
A13: 1972q4 | B13: =spliced_housing_approvals!D13 -> 452117.62 | C13: 123456789 | D13: 123456789
... A223: 2025q2 | B223: =spliced_housing_approvals!D223 -> 188787 | C223: 123456789 | D223: 123456789
A224: 2025q3 | B224: 188787 | C224: 123456789 | D224: 123456789
A225: 2025q4 | B225: 188787 | C225: 123456789 | D225: 123456789
A226: 2026q1 | B226: 188787 | C226: 123456789 | D226: 123456789

Sheet covid
B1: UK | C1: US | D1: EA
A2: 1970q1 | B2: 0 | C2: 0 | D2: 0
A3: 1970q2 | B3: 0 | C3: 0 | D3: 0
A4: 1970q3 | B4: 0 | C4: 0 | D4: 0
A5: 1970q4 | B5: 0 | C5: 0 | D5: 0
A6: 1971q1 | B6: 0 | C6: 0 | D6: 0
A7: 1971q2 | B7: 0 | C7: 0 | D7: 0
A8: 1971q3 | B8: 0 | C8: 0 | D8: 0
A9: 1971q4 | B9: 0 | C9: 0 | D9: 0
A10: 1972q1 | B10: 0 | C10: 0 | D10: 0
A11: 1972q2 | B11: 0 | C11: 0 | D11: 0
A12: 1972q3 | B12: 0 | C12: 0 | D12: 0
A13: 1972q4 | B13: 0 | C13: 0 | D13: 0
... A226: 2026q1 | B226: 0 | C226: 0 | D226: 0

Sheet spliced_vix
B1: vix | C1: mrkt vol | D1: gr_mrkt_vol
A2: 1970q1
A3: 1970q2 | C3: 1.386367
A4: 1970q3 | C4: 0.8534265 | D4: =C4/C3-1 -> -0.38441517 | E4: =E5/(1+ D5) -> 21.595786
A5: 1970q4 | C5: 0.5996996 | D5: =C5/C4-1 -> -0.29730375 | E5: =E6/(1+ D6) -> 15.175278
A6: 1971q1 | C6: 0.4664527 | D6: =C6/C5-1 -> -0.22218941 | E6: =E7/(1+ D7) -> 11.803492
A7: 1971q2 | C7: 0.5260337 | D7: =C7/C6-1 -> 0.12773214 | E7: =E8/(1+ D8) -> 13.311177
A8: 1971q3 | C8: 0.732933 | D8: =C8/C7-1 -> 0.39331948 | E8: =E9/(1+ D9) -> 18.546722
A9: 1971q4 | C9: 0.7525645 | D9: =C9/C8-1 -> 0.026784849 | E9: =E10/(1+ D10) -> 19.043493
A10: 1972q1 | C10: 0.4482629 | D10: =C10/C9-1 -> -0.40435285 | E10: =E11/(1+ D11) -> 11.343203
A11: 1972q2 | C11: 0.486986 | D11: =C11/C10-1 -> 0.086384798 | E11: =E12/(1+ D12) -> 12.323083
A12: 1972q3 | C12: 0.5062559 | D12: =C12/C11-1 -> 0.039569721 | E12: =E13/(1+ D13) -> 12.810704
A13: 1972q4 | C13: 0.5296984 | D13: =C13/C12-1 -> 0.046305633 | E13: =E14/(1+ D14) -> 13.403912
A14: 1973q1 | C14: 0.7170718 | D14: =C14/C13-1 -> 0.35373601 | E14: =E15/(1+ D15) -> 18.145358
A15: 1973q2 | C15: 1.022923 | D15: =C15/C14-1 -> 0.426528 | E15: =E16/(1+ D16) -> 25.884861
... A81: 1989q4 | C81: 1.07531 | D81: =C81/C80-1 -> 0.62262644 | E81: =E82/(1+ D82) -> 27.210503
A82: 1990q1 | B82: 22.17 | C82: 0.8761184 | D82: =C82/C81-1 -> -0.18524109 | E82: =B82 -> 22.17
A83: 1990q2 | B83: 18.72 | C83: 0.753612 | D83: =C83/C82-1 -> -0.13982859 | E83: =B83 -> 18.72
A84: 1990q3 | B84: 25.2 | C84: 1.169559 | D84: =C84/C83-1 -> 0.55193787 | E84: =B84 -> 25.2
A85: 1990q4 | B85: 26.11 | C85: 1.083485 | D85: =C85/C84-1 -> -0.073595261 | E85: =B85 -> 26.11
A86: 1991q1 | B86: 22.52 | C86: 1.033632 | D86: =C86/C85-1 -> -0.046011712 | E86: =B86 -> 22.52
A87: 1991q2 | B87: 17.15 | C87: 0.8693328 | D87: =C87/C86-1 -> -0.15895328 | E87: =B87 -> 17.15
A88: 1991q3 | B88: 16.63 | C88: 0.7427458 | D88: =C88/C87-1 -> -0.14561397 | E88: =B88 -> 16.63
A89: 1991q4 | B89: 17.46 | C89: 0.8890285 | D89: =C89/C88-1 -> 0.19694854 | E89: =B89 -> 17.46
A90: 1992q1 | B90: 17.56 | C90: 0.5916258 | D90: =C90/C89-1 -> -0.3345255 | E90: =B90 -> 17.56
A91: 1992q2 | B91: 15.62 | C91: 0.6961482 | D91: =C91/C90-1 -> 0.17666978 | E91: =B91 -> 15.62
A92: 1992q3 | B92: 13.9 | C92: 0.5725258 | D92: =C92/C91-1 -> -0.17758058 | E92: =B92 -> 13.9
A93: 1992q4 | B93: 14.76 | C93: 0.5400658 | D93: =C93/C92-1 -> -0.056696135 | E93: =B93 -> 14.76
... A222: 2025q1 | B222: 18.52 | C222: 123456789 | D222: =C222/C221-1 -> 1.8745072e+08 | E222: =B222 -> 18.52
A223: 2025q2 | B223: 23.56 | E223: =B223 -> 23.56
A224: 2025q3 | B224: 15.98 | E224: =B224 -> 15.98
A225: 2025q4 | B225: 16.98 | E225: =B225 -> 16.98
A226: 2026q1 | B226: 17.98 | E226: =B226 -> 17.98

Sheet credit_to_gdp_ALL_ctry
B1: AUS | C1: BEL | D1: CAN | E1: DNK | F1: FIN | G1: FRA | H1: GER | I1: IRE | J1: ITA | K1: JAP | L1: NLD | M1: NOR | N1: SPAIN | O1: SWE | P1: SWI | Q1: UK | R1: USA | S1: CHINA | T1: KOREA | U1: EA | V1: BRAZIL | W1: INDONESIA | X1: INDIA | Y1: MEXICO | Z1: RUSSIA | AA1: SA | AB1: TURKEY | AC1: SINGAPORE | AD1: HK
A2: 1970q1 | B2: 63 | D2: 85.1 | G2: 94.3 | H2: 86.6 | J2: 78.1 | N2: 77.7 | O2: 119 | P2: 146.6 | Q2: 58 | R2: 89.2
A3: 1970q2 | B3: 62.5 | D3: 84.9 | G3: 93.9 | H3: 86.4 | J3: 78.2 | N3: 78 | O3: 117 | P3: 146.5 | Q3: 59.4 | R3: 90.2
A4: 1970q3 | B4: 62.4 | D4: 85.5 | G4: 93.6 | H4: 85.6 | J4: 78.1 | N4: 78.3 | O4: 113.7 | P4: 145.1 | Q4: 57.5 | R4: 90.6
A5: 1970q4 | B5: 62.4 | D5: 86.2 | G5: 98.8 | H5: 86.5 | J5: 77.5 | N5: 80.8 | O5: 112.2 | P5: 146.5 | Q5: 58.6 | R5: 91.4
A6: 1971q1 | B6: 62.3 | D6: 86.6 | G6: 98.4 | H6: 85.2 | J6: 78.1 | N6: 81 | O6: 110.8 | P6: 144.9 | Q6: 56.9 | R6: 90.9
A7: 1971q2 | B7: 62.4 | D7: 87.8 | G7: 99.4 | H7: 85.6 | J7: 79.3 | N7: 81.7 | O7: 111.7 | P7: 144.3 | Q7: 55.2 | R7: 91.8
A8: 1971q3 | B8: 62 | D8: 89 | G8: 99.6 | H8: 86.5 | J8: 80.6 | N8: 81.4 | O8: 110.8 | P8: 141.1 | Q8: 56.2 | R8: 92.1
A9: 1971q4 | B9: 61.8 | D9: 89.9 | G9: 102.9 | H9: 88.4 | J9: 81.7 | N9: 83.1 | O9: 111.4 | P9: 141.2 | Q9: 57.1 | R9: 92.5
A10: 1972q1 | B10: 62.2 | D10: 90.1 | G10: 103.2 | H10: 88.2 | J10: 82.7 | N10: 82.4 | O10: 112.5 | P10: 138.7 | Q10: 60.6 | R10: 92.5
A11: 1972q2 | B11: 62.3 | D11: 91.1 | G11: 106 | H11: 89.7 | J11: 83.7 | N11: 83.7 | O11: 113.7 | P11: 138.8 | Q11: 61.3 | R11: 93.7
A12: 1972q3 | B12: 62.8 | D12: 92.2 | G12: 106.4 | H12: 89.9 | J12: 84.8 | N12: 84.5 | O12: 113.7 | P12: 137.4 | Q12: 64.7 | R12: 93.9
A13: 1972q4 | B13: 62.7 | D13: 93.3 | G13: 109.6 | H13: 92 | J13: 85.7 | N13: 86.8 | O13: 112.5 | P13: 138.4 | Q13: 65 | R13: 94.6
... A226: 2026q1 | B226: 175.2 | D226: 218.2 | G226: 215.1 | H226: 138.6 | J226: 94.4 | N226: 120 | O226: 236.1 | P226: 250.2 | Q226: 133 | R226: 140.4

Sheet d3y_cre_to_gdp_all_ALL_ctry
B1: AUS | C1: BEL | D1: CAN | E1: DNK | F1: FIN | G1: FRA | H1: GER | I1: IRE | J1: ITA | K1: JAP | L1: NLD | M1: NOR | N1: SPAIN | O1: SWE | P1: SWI | Q1: UK | R1: USA | S1: CHINA | T1: KOREA | U1: EA | V1: BRAZIL | W1: INDONESIA | X1: INDIA | Y1: MEXICO | Z1: RUSSIA | AA1: SA | AB1: TURKEY | AC1: SINGAPORE | AD1: HK
A2: 1970q1
A3: 1970q2
A4: 1970q3
A5: 1970q4
A6: 1971q1
A7: 1971q2
A8: 1971q3
A9: 1971q4
A10: 1972q1
A11: 1972q2
A12: 1972q3
A13: 1972q4
A14: 1973q1 | B14: =credit_to_gdp_ALL_ctry!B14-credit_to_gdp_ALL_ctry!B2 -> 1.7 | D14: =credit_to_gdp_ALL_ctry!D14-credit_to_gdp_ALL_ctry!D2 -> 8.4 | G14: =credit_to_gdp_ALL_ctry!G14-credit_to_gdp_ALL_ctry!G2 -> 13.8 | H14: =credit_to_gdp_ALL_ctry!H14-credit_to_gdp_ALL_ctry!H2 -> 5.6 | J14: =credit_to_gdp_ALL_ctry!J14-credit_to_gdp_ALL_ctry!J2 -> 8.6 | N14: =credit_to_gdp_ALL_ctry!N14-credit_to_gdp_ALL_ctry!N2 -> 9.4 | O14: =credit_to_gdp_ALL_ctry!O14-credit_to_gdp_ALL_ctry!O2 -> -6.1 | P14: =credit_to_gdp_ALL_ctry!P14-credit_to_gdp_ALL_ctry!P2 -> -11.5 | Q14: =credit_to_gdp_ALL_ctry!Q14-credit_to_gdp_ALL_ctry!Q2 -> 6.2 | R14: =credit_to_gdp_ALL_ctry!R14-credit_to_gdp_ALL_ctry!R2 -> 5.6
A15: 1973q2 | B15: =credit_to_gdp_ALL_ctry!B15-credit_to_gdp_ALL_ctry!B3 -> 3.8 | D15: =credit_to_gdp_ALL_ctry!D15-credit_to_gdp_ALL_ctry!D3 -> 9.9 | G15: =credit_to_gdp_ALL_ctry!G15-credit_to_gdp_ALL_ctry!G3 -> 15.9 | H15: =credit_to_gdp_ALL_ctry!H15-credit_to_gdp_ALL_ctry!H3 -> 6.2 | J15: =credit_to_gdp_ALL_ctry!J15-credit_to_gdp_ALL_ctry!J3 -> 8 | N15: =credit_to_gdp_ALL_ctry!N15-credit_to_gdp_ALL_ctry!N3 -> 10.7 | O15: =credit_to_gdp_ALL_ctry!O15-credit_to_gdp_ALL_ctry!O3 -> -3.8 | P15: =credit_to_gdp_ALL_ctry!P15-credit_to_gdp_ALL_ctry!P3 -> -12.9 | Q15: =credit_to_gdp_ALL_ctry!Q15-credit_to_gdp_ALL_ctry!Q3 -> 6.9 | R15: =credit_to_gdp_ALL_ctry!R15-credit_to_gdp_ALL_ctry!R3 -> 5.6
A16: 1973q3 | B16: =credit_to_gdp_ALL_ctry!B16-credit_to_gdp_ALL_ctry!B4 -> 4.7 | D16: =credit_to_gdp_ALL_ctry!D16-credit_to_gdp_ALL_ctry!D4 -> 9.3 | G16: =credit_to_gdp_ALL_ctry!G16-credit_to_gdp_ALL_ctry!G4 -> 15.9 | H16: =credit_to_gdp_ALL_ctry!H16-credit_to_gdp_ALL_ctry!H4 -> 6.9 | J16: =credit_to_gdp_ALL_ctry!J16-credit_to_gdp_ALL_ctry!J4 -> 6.5 | N16: =credit_to_gdp_ALL_ctry!N16-credit_to_gdp_ALL_ctry!N4 -> 11.4 | O16: =credit_to_gdp_ALL_ctry!O16-credit_to_gdp_ALL_ctry!O4 -> -0.7 | P16: =credit_to_gdp_ALL_ctry!P16-credit_to_gdp_ALL_ctry!P4 -> -11.7 | Q16: =credit_to_gdp_ALL_ctry!Q16-credit_to_gdp_ALL_ctry!Q4 -> 8.4 | R16: =credit_to_gdp_ALL_ctry!R16-credit_to_gdp_ALL_ctry!R4 -> 5.6
A17: 1973q4 | B17: =credit_to_gdp_ALL_ctry!B17-credit_to_gdp_ALL_ctry!B5 -> 4.8 | D17: =credit_to_gdp_ALL_ctry!D17-credit_to_gdp_ALL_ctry!D5 -> 9.2 | G17: =credit_to_gdp_ALL_ctry!G17-credit_to_gdp_ALL_ctry!G5 -> 11.9 | H17: =credit_to_gdp_ALL_ctry!H17-credit_to_gdp_ALL_ctry!H5 -> 6.7 | J17: =credit_to_gdp_ALL_ctry!J17-credit_to_gdp_ALL_ctry!J5 -> 5.5 | N17: =credit_to_gdp_ALL_ctry!N17-credit_to_gdp_ALL_ctry!N5 -> 10.4 | O17: =credit_to_gdp_ALL_ctry!O17-credit_to_gdp_ALL_ctry!O5 -> 0.8 | P17: =credit_to_gdp_ALL_ctry!P17-credit_to_gdp_ALL_ctry!P5 -> -11.7 | Q17: =credit_to_gdp_ALL_ctry!Q17-credit_to_gdp_ALL_ctry!Q5 -> 5.3 | R17: =credit_to_gdp_ALL_ctry!R17-credit_to_gdp_ALL_ctry!R5 -> 4.9
A18: 1974q1 | B18: =credit_to_gdp_ALL_ctry!B18-credit_to_gdp_ALL_ctry!B6 -> 6.2 | D18: =credit_to_gdp_ALL_ctry!D18-credit_to_gdp_ALL_ctry!D6 -> 8.6 | G18: =credit_to_gdp_ALL_ctry!G18-credit_to_gdp_ALL_ctry!G6 -> 9.8 | H18: =credit_to_gdp_ALL_ctry!H18-credit_to_gdp_ALL_ctry!H6 -> 7.6 | J18: =credit_to_gdp_ALL_ctry!J18-credit_to_gdp_ALL_ctry!J6 -> 3.6 | N18: =credit_to_gdp_ALL_ctry!N18-credit_to_gdp_ALL_ctry!N6 -> 8.5 | O18: =credit_to_gdp_ALL_ctry!O18-credit_to_gdp_ALL_ctry!O6 -> 3.3 | P18: =credit_to_gdp_ALL_ctry!P18-credit_to_gdp_ALL_ctry!P6 -> -11.6 | Q18: =credit_to_gdp_ALL_ctry!Q18-credit_to_gdp_ALL_ctry!Q6 -> 8.1 | R18: =credit_to_gdp_ALL_ctry!R18-credit_to_gdp_ALL_ctry!R6 -> 5.4
A19: 1974q2 | B19: =credit_to_gdp_ALL_ctry!B19-credit_to_gdp_ALL_ctry!B7 -> 7.6 | D19: =credit_to_gdp_ALL_ctry!D19-credit_to_gdp_ALL_ctry!D7 -> 8.5 | G19: =credit_to_gdp_ALL_ctry!G19-credit_to_gdp_ALL_ctry!G7 -> 7.8 | H19: =credit_to_gdp_ALL_ctry!H19-credit_to_gdp_ALL_ctry!H7 -> 7.7 | J19: =credit_to_gdp_ALL_ctry!J19-credit_to_gdp_ALL_ctry!J7 -> 1.1 | N19: =credit_to_gdp_ALL_ctry!N19-credit_to_gdp_ALL_ctry!N7 -> 7.9 | O19: =credit_to_gdp_ALL_ctry!O19-credit_to_gdp_ALL_ctry!O7 -> 3.9 | P19: =credit_to_gdp_ALL_ctry!P19-credit_to_gdp_ALL_ctry!P7 -> -12.4 | Q19: =credit_to_gdp_ALL_ctry!Q19-credit_to_gdp_ALL_ctry!Q7 -> 9.6 | R19: =credit_to_gdp_ALL_ctry!R19-credit_to_gdp_ALL_ctry!R7 -> 6.1
A20: 1974q3 | B20: =credit_to_gdp_ALL_ctry!B20-credit_to_gdp_ALL_ctry!B8 -> 9.2 | D20: =credit_to_gdp_ALL_ctry!D20-credit_to_gdp_ALL_ctry!D8 -> 7.3 | G20: =credit_to_gdp_ALL_ctry!G20-credit_to_gdp_ALL_ctry!G8 -> 6.6 | H20: =credit_to_gdp_ALL_ctry!H20-credit_to_gdp_ALL_ctry!H8 -> 6.9 | J20: =credit_to_gdp_ALL_ctry!J20-credit_to_gdp_ALL_ctry!J8 -> -1.6 | N20: =credit_to_gdp_ALL_ctry!N20-credit_to_gdp_ALL_ctry!N8 -> 9.2 | O20: =credit_to_gdp_ALL_ctry!O20-credit_to_gdp_ALL_ctry!O8 -> 2.9 | P20: =credit_to_gdp_ALL_ctry!P20-credit_to_gdp_ALL_ctry!P8 -> -9.7 | Q20: =credit_to_gdp_ALL_ctry!Q20-credit_to_gdp_ALL_ctry!Q8 -> 7.9 | R20: =credit_to_gdp_ALL_ctry!R20-credit_to_gdp_ALL_ctry!R8 -> 6.3
A21: 1974q4 | B21: =credit_to_gdp_ALL_ctry!B21-credit_to_gdp_ALL_ctry!B9 -> 10.6 | D21: =credit_to_gdp_ALL_ctry!D21-credit_to_gdp_ALL_ctry!D9 -> 6.8 | G21: =credit_to_gdp_ALL_ctry!G21-credit_to_gdp_ALL_ctry!G9 -> 5.7 | H21: =credit_to_gdp_ALL_ctry!H21-credit_to_gdp_ALL_ctry!H9 -> 5.6 | J21: =credit_to_gdp_ALL_ctry!J21-credit_to_gdp_ALL_ctry!J9 -> -3.9 | N21: =credit_to_gdp_ALL_ctry!N21-credit_to_gdp_ALL_ctry!N9 -> 9.8 | O21: =credit_to_gdp_ALL_ctry!O21-credit_to_gdp_ALL_ctry!O9 -> 0.1 | P21: =credit_to_gdp_ALL_ctry!P21-credit_to_gdp_ALL_ctry!P9 -> -27.5 | Q21: =credit_to_gdp_ALL_ctry!Q21-credit_to_gdp_ALL_ctry!Q9 -> 4.2 | R21: =credit_to_gdp_ALL_ctry!R21-credit_to_gdp_ALL_ctry!R9 -> 6.1
A22: 1975q1 | B22: =credit_to_gdp_ALL_ctry!B22-credit_to_gdp_ALL_ctry!B10 -> 10.2 | D22: =credit_to_gdp_ALL_ctry!D22-credit_to_gdp_ALL_ctry!D10 -> 7.2 | G22: =credit_to_gdp_ALL_ctry!G22-credit_to_gdp_ALL_ctry!G10 -> 3.8 | H22: =credit_to_gdp_ALL_ctry!H22-credit_to_gdp_ALL_ctry!H10 -> 5.1 | J22: =credit_to_gdp_ALL_ctry!J22-credit_to_gdp_ALL_ctry!J10 -> -5.1 | N22: =credit_to_gdp_ALL_ctry!N22-credit_to_gdp_ALL_ctry!N10 -> 11 | O22: =credit_to_gdp_ALL_ctry!O22-credit_to_gdp_ALL_ctry!O10 -> -2.6 | P22: =credit_to_gdp_ALL_ctry!P22-credit_to_gdp_ALL_ctry!P10 -> -23.6 | Q22: =credit_to_gdp_ALL_ctry!Q22-credit_to_gdp_ALL_ctry!Q10 -> -1.1 | R22: =credit_to_gdp_ALL_ctry!R22-credit_to_gdp_ALL_ctry!R10 -> 4.7
A23: 1975q2 | B23: =credit_to_gdp_ALL_ctry!B23-credit_to_gdp_ALL_ctry!B11 -> 9.6 | D23: =credit_to_gdp_ALL_ctry!D23-credit_to_gdp_ALL_ctry!D11 -> 7.5 | G23: =credit_to_gdp_ALL_ctry!G23-credit_to_gdp_ALL_ctry!G11 -> 0.2 | H23: =credit_to_gdp_ALL_ctry!H23-credit_to_gdp_ALL_ctry!H11 -> 4.2 | J23: =credit_to_gdp_ALL_ctry!J23-credit_to_gdp_ALL_ctry!J11 -> -5.8 | N23: =credit_to_gdp_ALL_ctry!N23-credit_to_gdp_ALL_ctry!N11 -> 10.8 | O23: =credit_to_gdp_ALL_ctry!O23-credit_to_gdp_ALL_ctry!O11 -> -4.7 | P23: =credit_to_gdp_ALL_ctry!P23-credit_to_gdp_ALL_ctry!P11 -> -20.6 | Q23: =credit_to_gdp_ALL_ctry!Q23-credit_to_gdp_ALL_ctry!Q11 -> -2 | R23: =credit_to_gdp_ALL_ctry!R23-credit_to_gdp_ALL_ctry!R11 -> 3.2
A24: 1975q3 | B24: =credit_to_gdp_ALL_ctry!B24-credit_to_gdp_ALL_ctry!B12 -> 9 | D24: =credit_to_gdp_ALL_ctry!D24-credit_to_gdp_ALL_ctry!D12 -> 6.9 | G24: =credit_to_gdp_ALL_ctry!G24-credit_to_gdp_ALL_ctry!G12 -> -0.6 | H24: =credit_to_gdp_ALL_ctry!H24-credit_to_gdp_ALL_ctry!H12 -> 4.2 | J24: =credit_to_gdp_ALL_ctry!J24-credit_to_gdp_ALL_ctry!J12 -> -6.3 | N24: =credit_to_gdp_ALL_ctry!N24-credit_to_gdp_ALL_ctry!N12 -> 10.4 | O24: =credit_to_gdp_ALL_ctry!O24-credit_to_gdp_ALL_ctry!O12 -> -7.6 | P24: =credit_to_gdp_ALL_ctry!P24-credit_to_gdp_ALL_ctry!P12 -> -17.6 | Q24: =credit_to_gdp_ALL_ctry!Q24-credit_to_gdp_ALL_ctry!Q12 -> -8.2 | R24: =credit_to_gdp_ALL_ctry!R24-credit_to_gdp_ALL_ctry!R12 -> 2.3
A25: 1975q4 | B25: =credit_to_gdp_ALL_ctry!B25-credit_to_gdp_ALL_ctry!B13 -> 9 | D25: =credit_to_gdp_ALL_ctry!D25-credit_to_gdp_ALL_ctry!D13 -> 6.3 | G25: =credit_to_gdp_ALL_ctry!G25-credit_to_gdp_ALL_ctry!G13 -> -0.1 | H25: =credit_to_gdp_ALL_ctry!H25-credit_to_gdp_ALL_ctry!H13 -> 4 | J25: =credit_to_gdp_ALL_ctry!J25-credit_to_gdp_ALL_ctry!J13 -> -7 | N25: =credit_to_gdp_ALL_ctry!N25-credit_to_gdp_ALL_ctry!N13 -> 9.9 | O25: =credit_to_gdp_ALL_ctry!O25-credit_to_gdp_ALL_ctry!O13 -> -7.1 | P25: =credit_to_gdp_ALL_ctry!P25-credit_to_gdp_ALL_ctry!P13 -> -12.7 | Q25: =credit_to_gdp_ALL_ctry!Q25-credit_to_gdp_ALL_ctry!Q13 -> -7.1 | R25: =credit_to_gdp_ALL_ctry!R25-credit_to_gdp_ALL_ctry!R13 -> 1.3
... A225: 2025q4 | B225: =credit_to_gdp_ALL_ctry!B225-credit_to_gdp_ALL_ctry!B213 -> 4.5 | D225: =credit_to_gdp_ALL_ctry!D225-credit_to_gdp_ALL_ctry!D213 -> 4 | G225: =credit_to_gdp_ALL_ctry!G225-credit_to_gdp_ALL_ctry!G213 -> -9.8 | H225: =credit_to_gdp_ALL_ctry!H225-credit_to_gdp_ALL_ctry!H213 -> -7.5 | J225: =credit_to_gdp_ALL_ctry!J225-credit_to_gdp_ALL_ctry!J213 -> -11.4 | N225: =credit_to_gdp_ALL_ctry!N225-credit_to_gdp_ALL_ctry!N213 -> -22.7 | O225: =credit_to_gdp_ALL_ctry!O225-credit_to_gdp_ALL_ctry!O213 -> -39.8 | P225: =credit_to_gdp_ALL_ctry!P225-credit_to_gdp_ALL_ctry!P213 -> -11.6 | Q225: =credit_to_gdp_ALL_ctry!Q225-credit_to_gdp_ALL_ctry!Q213 -> -16.3 | R225: =credit_to_gdp_ALL_ctry!R225-credit_to_gdp_ALL_ctry!R213 -> -13.1
A226: 2026q1 | B226: 4.5 | D226: 4 | G226: -9.8 | H226: -7.5 | J226: -11.4 | N226: -22.7 | O226: -39.8 | P226: -11.6 | Q226: -16.3 | R226: -13.1

Sheet uk_export_weight
B1: AUS | C1: BEL | D1: CAN | E1: DNK | F1: FIN | G1: FRA | H1: GER | I1: IRE | J1: ITA | K1: JAP | L1: NLD | M1: NOR | N1: SPAIN | O1: SWE | P1: SWI | Q1: UK | R1: USA | S1: CHINA | T1: KOREA | U1: EA | V1: BRAZIL | W1: INDONESIA | X1: INDIA | Y1: MEXICO | Z1: RUSSIA | AA1: SA | AB1: TURKEY | AC1: SINGAPORE | AD1: HK
A2: 1970q1 | B2: 793.3 | D2: 952.1 | G2: 1278.3 | H2: 1473.3 | J2: 709.1 | N2: 501.1 | O2: 1012.5 | P2: 916.9 | Q2: 0 | R2: 3040.9
A3: 1970q2 | B3: 793.3 | D3: 952.1 | G3: 1278.3 | H3: 1473.3 | J3: 709.1 | N3: 501.1 | O3: 1012.5 | P3: 916.9 | Q3: 0 | R3: 3040.9
A4: 1970q3 | B4: 793.3 | D4: 952.1 | G4: 1278.3 | H4: 1473.3 | J4: 709.1 | N4: 501.1 | O4: 1012.5 | P4: 916.9 | Q4: 0 | R4: 3040.9
A5: 1970q4 | B5: 793.3 | D5: 952.1 | G5: 1278.3 | H5: 1473.3 | J5: 709.1 | N5: 501.1 | O5: 1012.5 | P5: 916.9 | Q5: 0 | R5: 3040.9
A6: 1971q1 | B6: 793.3 | D6: 952.1 | G6: 1278.3 | H6: 1473.3 | J6: 709.1 | N6: 501.1 | O6: 1012.5 | P6: 916.9 | Q6: 0 | R6: 3040.9
A7: 1971q2 | B7: 793.3 | D7: 952.1 | G7: 1278.3 | H7: 1473.3 | J7: 709.1 | N7: 501.1 | O7: 1012.5 | P7: 916.9 | Q7: 0 | R7: 3040.9
A8: 1971q3 | B8: 793.3 | D8: 952.1 | G8: 1278.3 | H8: 1473.3 | J8: 709.1 | N8: 501.1 | O8: 1012.5 | P8: 916.9 | Q8: 0 | R8: 3040.9
A9: 1971q4 | B9: 793.3 | D9: 952.1 | G9: 1278.3 | H9: 1473.3 | J9: 709.1 | N9: 501.1 | O9: 1012.5 | P9: 916.9 | Q9: 0 | R9: 3040.9
A10: 1972q1 | B10: 793.3 | D10: 952.1 | G10: 1278.3 | H10: 1473.3 | J10: 709.1 | N10: 501.1 | O10: 1012.5 | P10: 916.9 | Q10: 0 | R10: 3040.9
A11: 1972q2 | B11: 793.3 | D11: 952.1 | G11: 1278.3 | H11: 1473.3 | J11: 709.1 | N11: 501.1 | O11: 1012.5 | P11: 916.9 | Q11: 0 | R11: 3040.9
A12: 1972q3 | B12: 793.3 | D12: 952.1 | G12: 1278.3 | H12: 1473.3 | J12: 709.1 | N12: 501.1 | O12: 1012.5 | P12: 916.9 | Q12: 0 | R12: 3040.9
A13: 1972q4 | B13: 793.3 | D13: 952.1 | G13: 1278.3 | H13: 1473.3 | J13: 709.1 | N13: 501.1 | O13: 1012.5 | P13: 916.9 | Q13: 0 | R13: 3040.9
... A226: 2026q1 | B226: 5851.1187 | D226: 7289.0589 | G226: 31924.42 | H226: 47519.919 | J226: 14019.858 | N226: 13983.972 | O226: 7361.2571 | P226: 25397.923 | Q226: 0 | R226: 65361.653

Sheet quarterly_pmi
B1: pmi_output | C1: pmi_future_output | G1: pmi_output | H1: pmi_future_output
A2: 1970q1 | F2: mean 2000q1-2019q4 | G2: =AVERAGE(B122:B201) -> 54.041301 | H2: =AVERAGE(C122:C201) -> 67.528991
A3: 1970q2 | F3: standard dev | G3: =_xlfn.STDEV.S(B122:B201) -> 3.6527964 | H3: =_xlfn.STDEV.S(C122:C201) -> 4.6026102
A4: 1970q3
A5: 1970q4
A6: 1971q1
A7: 1971q2
A8: 1971q3
A9: 1971q4
A10: 1972q1
A11: 1972q2
A12: 1972q3
A13: 1972q4
A14: 1973q1
A15: 1973q2
... A110: 1997q1
A111: 1997q2 | C111: 75.51289
A112: 1997q3 | C112: 71.99351
A113: 1997q4 | C113: 72.64549
A114: 1998q1 | B114: 57.14592 | C114: 70.32822 | D114: 57.145925
A115: 1998q2 | B115: 54.24487 | C115: 67.17878 | D115: 54.244868
A116: 1998q3 | B116: 50.9725 | C116: 61.1142 | D116: 50.972505
A117: 1998q4 | B117: 46.59767 | C117: 59.2697 | D117: 46.59767
A118: 1999q1 | B118: 49.25422 | C118: 66.67503 | D118: 49.254221
A119: 1999q2 | B119: 55.40696 | C119: 73.12125 | D119: 55.406956
A120: 1999q3 | B120: 57.31541 | C120: 73.94269 | D120: 57.315406
A121: 1999q4 | B121: 57.77604 | C121: 72.45512 | D121: 57.776042
A122: 2000q1 | B122: 56.12394 | C122: 71.2149 | D122: 56.123937
A123: 2000q2 | B123: 56.12898 | C123: 69.52824 | D123: 56.12898
A124: 2000q3 | B124: 55.21443 | C124: 69.06199 | D124: 55.214427
A125: 2000q4 | B125: 55.37032 | C125: 69.54543 | D125: 55.370319
... A226: 2026q1 | B226: 51.667069 | C226: 66.791365 | D226: 51.667069

Sheet quarterly_pmi_std
B1: pmi_output | C1: pmi_future_output
A2: 1970q1
A3: 1970q2
A4: 1970q3
A5: 1970q4
A6: 1971q1
A7: 1971q2
A8: 1971q3
A9: 1971q4
A10: 1972q1
A11: 1972q2
A12: 1972q3
A13: 1972q4
... A110: 1997q1
A111: 1997q2 | C111: =(quarterly_pmi!C111-quarterly_pmi!$H$2)/quarterly_pmi!$H$3 -> 1.7346459
A112: 1997q3 | C112: =(quarterly_pmi!C112-quarterly_pmi!$H$2)/quarterly_pmi!$H$3 -> 0.96999713
A113: 1997q4 | C113: =(quarterly_pmi!C113-quarterly_pmi!$H$2)/quarterly_pmi!$H$3 -> 1.1116515
A114: 1998q1 | B114: =(quarterly_pmi!B114-quarterly_pmi!$G$2)/quarterly_pmi!$G$3 -> 0.84992943 | C114: =(quarterly_pmi!C114-quarterly_pmi!$H$2)/quarterly_pmi!$H$3 -> 0.60818286
A115: 1998q2 | B115: =(quarterly_pmi!B115-quarterly_pmi!$G$2)/quarterly_pmi!$G$3 -> 0.055729667 | C115: =(quarterly_pmi!C115-quarterly_pmi!$H$2)/quarterly_pmi!$H$3 -> -0.076089732
A116: 1998q3 | B116: =(quarterly_pmi!B116-quarterly_pmi!$G$2)/quarterly_pmi!$G$3 -> -0.84012372 | C116: =(quarterly_pmi!C116-quarterly_pmi!$H$2)/quarterly_pmi!$H$3 -> -1.393729
A117: 1998q4 | B117: =(quarterly_pmi!B117-quarterly_pmi!$G$2)/quarterly_pmi!$G$3 -> -2.0377897 | C117: =(quarterly_pmi!C117-quarterly_pmi!$H$2)/quarterly_pmi!$H$3 -> -1.7944799
A118: 1999q1 | B118: =(quarterly_pmi!B118-quarterly_pmi!$G$2)/quarterly_pmi!$G$3 -> -1.310525 | C118: =(quarterly_pmi!C118-quarterly_pmi!$H$2)/quarterly_pmi!$H$3 -> -0.1855385
A119: 1999q2 | B119: =(quarterly_pmi!B119-quarterly_pmi!$G$2)/quarterly_pmi!$G$3 -> 0.37386676 | C119: =(quarterly_pmi!C119-quarterly_pmi!$H$2)/quarterly_pmi!$H$3 -> 1.215019
A120: 1999q3 | B120: =(quarterly_pmi!B120-quarterly_pmi!$G$2)/quarterly_pmi!$G$3 -> 0.8963295 | C120: =(quarterly_pmi!C120-quarterly_pmi!$H$2)/quarterly_pmi!$H$3 -> 1.3934916
A121: 1999q4 | B121: =(quarterly_pmi!B121-quarterly_pmi!$G$2)/quarterly_pmi!$G$3 -> 1.0224329 | C121: =(quarterly_pmi!C121-quarterly_pmi!$H$2)/quarterly_pmi!$H$3 -> 1.0702902
A122: 2000q1 | B122: =(quarterly_pmi!B122-quarterly_pmi!$G$2)/quarterly_pmi!$G$3 -> 0.57014926 | C122: =(quarterly_pmi!C122-quarterly_pmi!$H$2)/quarterly_pmi!$H$3 -> 0.80083007
A123: 2000q2 | B123: =(quarterly_pmi!B123-quarterly_pmi!$G$2)/quarterly_pmi!$G$3 -> 0.57152902 | C123: =(quarterly_pmi!C123-quarterly_pmi!$H$2)/quarterly_pmi!$H$3 -> 0.43437279
A124: 2000q3 | B124: =(quarterly_pmi!B124-quarterly_pmi!$G$2)/quarterly_pmi!$G$3 -> 0.32115919 | C124: =(quarterly_pmi!C124-quarterly_pmi!$H$2)/quarterly_pmi!$H$3 -> 0.33307158
A125: 2000q4 | B125: =(quarterly_pmi!B125-quarterly_pmi!$G$2)/quarterly_pmi!$G$3 -> 0.36383608 | C125: =(quarterly_pmi!C125-quarterly_pmi!$H$2)/quarterly_pmi!$H$3 -> 0.43810763
... A223: 2025q2 | B223: =(quarterly_pmi!B223-quarterly_pmi!$G$2)/quarterly_pmi!$G$3 -> -1.0369729 | C223: =(quarterly_pmi!C223-quarterly_pmi!$H$2)/quarterly_pmi!$H$3 -> -0.87622702

Sheet gdp_growth_forecast_consensus
B1: rgdp0_m_q | C1: rgdp1_m_q | G1: rgdp0_m_q | H1: rgdp1_m_q
A2: 1970q1 | F2: mean 2000q1-2019q4 | G2: =AVERAGE(B122:B201) -> 1.657275 | H2: =AVERAGE(C122:C201) -> 1.9841875
A3: 1970q2 | F3: standard dev | G3: =_xlfn.STDEV.S(B122:B201) -> 1.4610946 | H3: =_xlfn.STDEV.S(C122:C201) -> 0.68257048
A4: 1970q3
A5: 1970q4
A6: 1971q1
A7: 1971q2
A8: 1971q3
A9: 1971q4
A10: 1972q1
A11: 1972q2
A12: 1972q3
A13: 1972q4
A14: 1973q1
A15: 1973q2
... A80: 1989q3
A81: 1989q4 | B81: 2.107667 | C81: 1.548333
A82: 1990q1 | B82: 1.214667 | C82: 2.017667
A83: 1990q2 | B83: 1.105667 | C83: 2.288
A84: 1990q3 | B84: 1.360667 | C84: 2.055
A85: 1990q4 | B85: 1.239 | C85: 0.8833333
A86: 1991q1 | B86: -0.522 | C86: 2.132
A87: 1991q2 | B87: -1.53 | C87: 2.124
A88: 1991q3 | B88: -1.982333 | C88: 1.777667
A89: 1991q4 | B89: -2.125333 | C89: 1.783333
A90: 1992q1 | B90: 1.214333 | C90: 2.388
A91: 1992q2 | B91: 0.788 | C91: 2.326667
A92: 1992q3 | B92: -0.4643333 | C92: 1.691333
... A213: 2022q4 | B213: 4.249333 | C213: -0.7296667
A214: 2023q1
A215: 2023q2
A216: 2023q3
A217: 2023q4
A218: 2024q1
A219: 2024q2
A220: 2024q3
A221: 2024q4
A222: 2025q1
A223: 2025q2

Sheet gdp_growth_forecast_consen_std
B1: pmi_output | C1: pmi_future_output
A2: 1970q1
A3: 1970q2
A4: 1970q3
A5: 1970q4
A6: 1971q1
A7: 1971q2
A8: 1971q3
A9: 1971q4
A10: 1972q1
A11: 1972q2
A12: 1972q3
A13: 1972q4
... A80: 1989q3
A81: 1989q4 | B81: =(gdp_growth_forecast_consensus!B81-gdp_growth_forecast_consensus!$G$2)/gdp_growth_forecast_consensus!$G$3 -> 0.30825658 | C81: =(gdp_growth_forecast_consensus!C81-gdp_growth_forecast_consensus!$H$2)/gdp_growth_forecast_consensus!$H$3 -> -0.63854869
A82: 1990q1 | B82: =(gdp_growth_forecast_consensus!B82-gdp_growth_forecast_consensus!$G$2)/gdp_growth_forecast_consensus!$G$3 -> -0.30292904 | C82: =(gdp_growth_forecast_consensus!C82-gdp_growth_forecast_consensus!$H$2)/gdp_growth_forecast_consensus!$H$3 -> 0.049049175
A83: 1990q2 | B83: =(gdp_growth_forecast_consensus!B83-gdp_growth_forecast_consensus!$G$2)/gdp_growth_forecast_consensus!$G$3 -> -0.37753064 | C83: =(gdp_growth_forecast_consensus!C83-gdp_growth_forecast_consensus!$H$2)/gdp_growth_forecast_consensus!$H$3 -> 0.44510059
A84: 1990q3 | B84: =(gdp_growth_forecast_consensus!B84-gdp_growth_forecast_consensus!$G$2)/gdp_growth_forecast_consensus!$G$3 -> -0.20300395 | C84: =(gdp_growth_forecast_consensus!C84-gdp_growth_forecast_consensus!$H$2)/gdp_growth_forecast_consensus!$H$3 -> 0.10374389
A85: 1990q4 | B85: =(gdp_growth_forecast_consensus!B85-gdp_growth_forecast_consensus!$G$2)/gdp_growth_forecast_consensus!$G$3 -> -0.28627508 | C85: =(gdp_growth_forecast_consensus!C85-gdp_growth_forecast_consensus!$H$2)/gdp_growth_forecast_consensus!$H$3 -> -1.6128066
A86: 1991q1 | B86: =(gdp_growth_forecast_consensus!B86-gdp_growth_forecast_consensus!$G$2)/gdp_growth_forecast_consensus!$G$3 -> -1.4915359 | C86: =(gdp_growth_forecast_consensus!C86-gdp_growth_forecast_consensus!$H$2)/gdp_growth_forecast_consensus!$H$3 -> 0.21655276
A87: 1991q2 | B87: =(gdp_growth_forecast_consensus!B87-gdp_growth_forecast_consensus!$G$2)/gdp_growth_forecast_consensus!$G$3 -> -2.1814296 | C87: =(gdp_growth_forecast_consensus!C87-gdp_growth_forecast_consensus!$H$2)/gdp_growth_forecast_consensus!$H$3 -> 0.20483236
A88: 1991q3 | B88: =(gdp_growth_forecast_consensus!B88-gdp_growth_forecast_consensus!$G$2)/gdp_growth_forecast_consensus!$G$3 -> -2.4910146 | C88: =(gdp_growth_forecast_consensus!C88-gdp_growth_forecast_consensus!$H$2)/gdp_growth_forecast_consensus!$H$3 -> -0.30256287
A89: 1991q4 | B89: =(gdp_growth_forecast_consensus!B89-gdp_growth_forecast_consensus!$G$2)/gdp_growth_forecast_consensus!$G$3 -> -2.5888865 | C89: =(gdp_growth_forecast_consensus!C89-gdp_growth_forecast_consensus!$H$2)/gdp_growth_forecast_consensus!$H$3 -> -0.29426189
A90: 1992q1 | B90: =(gdp_growth_forecast_consensus!B90-gdp_growth_forecast_consensus!$G$2)/gdp_growth_forecast_consensus!$G$3 -> -0.30315763 | C90: =(gdp_growth_forecast_consensus!C90-gdp_growth_forecast_consensus!$H$2)/gdp_growth_forecast_consensus!$H$3 -> 0.5916056
A91: 1992q2 | B91: =(gdp_growth_forecast_consensus!B91-gdp_growth_forecast_consensus!$G$2)/gdp_growth_forecast_consensus!$G$3 -> -0.59494778 | C91: =(gdp_growth_forecast_consensus!C91-gdp_growth_forecast_consensus!$H$2)/gdp_growth_forecast_consensus!$H$3 -> 0.50174968
A92: 1992q3 | B92: =(gdp_growth_forecast_consensus!B92-gdp_growth_forecast_consensus!$G$2)/gdp_growth_forecast_consensus!$G$3 -> -1.4520677 | C92: =(gdp_growth_forecast_consensus!C92-gdp_growth_forecast_consensus!$H$2)/gdp_growth_forecast_consensus!$H$3 -> -0.42904651
... A213: 2022q4 | B213: =(gdp_growth_forecast_consensus!B213-gdp_growth_forecast_consensus!$G$2)/gdp_growth_forecast_consensus!$G$3 -> 1.7740522 | C213: =(gdp_growth_forecast_consensus!C213-gdp_growth_forecast_consensus!$H$2)/gdp_growth_forecast_consensus!$H$3 -> -3.9759326
A214: 2023q1
A215: 2023q2
A216: 2023q3
A217: 2023q4
A218: 2024q1
A219: 2024q2
A220: 2024q3
A221: 2024q4
A222: 2025q1
A223: 2025q2

Sheet spliced_quartely_pmi
B1: pmi_output | C1: rgdp1_m_q | D1: spliced_pmi_output | F1: pmi_future_output | G1: pmi_future_output_SPLICED
A2: 1970q1 | T2: OUTPUT
A3: 1970q2
A4: 1970q3 | T4: Regression Statistics
A5: 1970q4 | T5: Multiple R | U5: 0.64516243
A6: 1971q1 | T6: R Square | U6: 0.41623456
A7: 1971q2 | T7: Adjusted R Square | U7: 0.40875039
A8: 1971q3 | T8: Standard Error | U8: 2.8087358
A9: 1971q4 | T9: Observations | U9: 80
A10: 1972q1
A11: 1972q2 | T11: ANOVA
A12: 1972q3 | U12: df | V12: SS | W12: MS | X12: F | Y12: Significance F
A13: 1972q4 | T13: Regression | U13: 1 | V13: 438.74901 | W13: 438.74901 | X13: 55.615309 | Y13: 1.0490956e-10
A14: 1973q1 | T14: Residual | U14: 78 | V14: 615.34177 | W14: 7.8889971
A15: 1973q2 | T15: Total | U15: 79 | V15: 1054.0908
A16: 1973q3
A17: 1973q4 | U17: Coefficients | V17: Standard Error | W17: t Stat | X17: P-value | Y17: Lower 95% | Z17: Upper 95% | AA17: Lower 95.0% | AB17: Upper 95.0%
A18: 1974q1 | T18: Intercept | U18: 47.190683 | V18: 0.97080492 | W18: 48.609852 | X18: 4.3500212e-60 | Y18: 45.257959 | Z18: 49.123407 | AA18: 45.257959 | AB18: 49.123407
A19: 1974q2 | T19: X Variable 1 | U19: 3.4526061 | V19: 0.4629668 | W19: 7.4575672 | X19: 1.0490956e-10 | Y19: 2.53091 | Z19: 4.3743022 | AA19: 2.53091 | AB19: 4.3743022
A20: 1974q3
A21: 1974q4
A22: 1975q1
A23: 1975q2
A24: 1975q3 | T24: FUTURE OUTPUT
A25: 1975q4
A26: 1976q1 | T26: Regression Statistics
A27: 1976q2 | T27: Multiple R | U27: 0.70798545
A28: 1976q3 | T28: R Square | U28: 0.5012434
A29: 1976q4 | T29: Adjusted R Square | U29: 0.49484909
A30: 1977q1 | T30: Standard Error | U30: 3.2712577
A31: 1977q2 | T31: Observations | U31: 80
A32: 1977q3
A33: 1977q4 | T33: ANOVA
A34: 1978q1 | U34: df | V34: SS | W34: MS | X34: F | Y34: Significance F
A35: 1978q2 | T35: Regression | U35: 1 | V35: 838.84968 | W35: 838.84968 | X35: 78.388908 | Y35: 2.0743715e-13
A36: 1978q3 | T36: Residual | U36: 78 | V36: 834.68792 | W36: 10.701127
A37: 1978q4 | T37: Total | U37: 79 | V37: 1673.5376
A38: 1979q1
A39: 1979q2 | U39: Coefficients | V39: Standard Error | W39: t Stat | X39: P-value | Y39: Lower 95% | Z39: Upper 95% | AA39: Lower 95.0% | AB39: Upper 95.0%
A40: 1979q3 | T40: Intercept | U40: 58.056511 | V40: 1.1306699 | W40: 51.347002 | X40: 6.8923194e-62 | Y40: 55.80552 | Z40: 60.307501 | AA40: 55.80552 | AB40: 60.307501
A41: 1979q4 | T41: X Variable 1 | U41: 4.7739847 | V41: 0.53920476 | W41: 8.8537511 | X41: 2.0743715e-13 | Y41: 3.7005105 | Z41: 5.847459 | AA41: 3.7005105 | AB41: 5.847459
A42: 1980q1
A43: 1980q2
A44: 1980q3
A45: 1980q4
A46: 1981q1
A47: 1981q2
A48: 1981q3
A49: 1981q4
A50: 1982q1
A51: 1982q2
A52: 1982q3
A53: 1982q4
... A80: 1989q3
A81: 1989q4 | C81: =gdp_growth_forecast_consensus!C81 -> 1.548333 | D81: =$U$18 + C81 *$U$19 -> 52.536467 | G81: =$U$40 + C81 *$U$41 -> 65.448229
A82: 1990q1 | C82: =gdp_growth_forecast_consensus!C82 -> 2.017667 | D82: =$U$18 + C82 *$U$19 -> 54.156892 | G82: =$U$40 + C82 *$U$41 -> 67.688822
A83: 1990q2 | C83: =gdp_growth_forecast_consensus!C83 -> 2.288 | D83: =$U$18 + C83 *$U$19 -> 55.090246 | G83: =$U$40 + C83 *$U$41 -> 68.979388
A84: 1990q3 | C84: =gdp_growth_forecast_consensus!C84 -> 2.055 | D84: =$U$18 + C84 *$U$19 -> 54.285789 | G84: =$U$40 + C84 *$U$41 -> 67.867049
A85: 1990q4 | C85: =gdp_growth_forecast_consensus!C85 -> 0.8833333 | D85: =$U$18 + C85 *$U$19 -> 50.240485 | G85: =$U$40 + C85 *$U$41 -> 62.27353
A86: 1991q1 | C86: =gdp_growth_forecast_consensus!C86 -> 2.132 | D86: =$U$18 + C86 *$U$19 -> 54.551639 | G86: =$U$40 + C86 *$U$41 -> 68.234646
A87: 1991q2 | C87: =gdp_growth_forecast_consensus!C87 -> 2.124 | D87: =$U$18 + C87 *$U$19 -> 54.524018 | G87: =$U$40 + C87 *$U$41 -> 68.196454
A88: 1991q3 | C88: =gdp_growth_forecast_consensus!C88 -> 1.777667 | D88: =$U$18 + C88 *$U$19 -> 53.328267 | G88: =$U$40 + C88 *$U$41 -> 66.543066
A89: 1991q4 | C89: =gdp_growth_forecast_consensus!C89 -> 1.783333 | D89: =$U$18 + C89 *$U$19 -> 53.347829 | G89: =$U$40 + C89 *$U$41 -> 66.570115
A90: 1992q1 | C90: =gdp_growth_forecast_consensus!C90 -> 2.388 | D90: =$U$18 + C90 *$U$19 -> 55.435506 | G90: =$U$40 + C90 *$U$41 -> 69.456786
A91: 1992q2 | C91: =gdp_growth_forecast_consensus!C91 -> 2.326667 | D91: =$U$18 + C91 *$U$19 -> 55.223748 | G91: =$U$40 + C91 *$U$41 -> 69.163983
A92: 1992q3 | C92: =gdp_growth_forecast_consensus!C92 -> 1.691333 | D92: =$U$18 + C92 *$U$19 -> 53.03019 | G92: =$U$40 + C92 *$U$41 -> 66.130909
... A110: 1997q1 | C110: =gdp_growth_forecast_consensus!C110 -> 2.637333 | D110: =$U$18 + C110 *$U$19 -> 56.296355 | G110: =$U$40 + C110 *$U$41 -> 70.647098
A111: 1997q2 | C111: =gdp_growth_forecast_consensus!C111 -> 2.633333 | D111: =$U$18 + C111 *$U$19 -> 56.282545 | F111: =quarterly_pmi!C111 -> 75.51289 | G111: =$U$40 + C111 *$U$41 -> 70.628002
A112: 1997q3 | C112: =gdp_growth_forecast_consensus!C112 -> 2.551333 | D112: =$U$18 + C112 *$U$19 -> 55.999431 | F112: =quarterly_pmi!C112 -> 71.99351 | G112: =$U$40 + C112 *$U$41 -> 70.236535
A113: 1997q4 | C113: =gdp_growth_forecast_consensus!C113 -> 2.549333 | D113: =$U$18 + C113 *$U$19 -> 55.992526 | F113: =quarterly_pmi!C113 -> 72.64549 | G113: =$U$40 + C113 *$U$41 -> 70.226987
A114: 1998q1 | B114: =quarterly_pmi!B114 -> 57.14592 | C114: =gdp_growth_forecast_consensus!C114 -> 1.955 | D114: =B114 -> 57.14592 | F114: =quarterly_pmi!C114 -> 70.32822 | G114: =F114 -> 70.32822
A115: 1998q2 | B115: =quarterly_pmi!B115 -> 54.24487 | C115: =gdp_growth_forecast_consensus!C115 -> 1.834333 | D115: =B115 -> 54.24487 | F115: =quarterly_pmi!C115 -> 67.17878 | G115: =F115 -> 67.17878
A116: 1998q3 | B116: =quarterly_pmi!B116 -> 50.9725 | C116: =gdp_growth_forecast_consensus!C116 -> 1.383667 | D116: =B116 -> 50.9725 | F116: =quarterly_pmi!C116 -> 61.1142 | G116: =F116 -> 61.1142
A117: 1998q4 | B117: =quarterly_pmi!B117 -> 46.59767 | C117: =gdp_growth_forecast_consensus!C117 -> 0.802 | D117: =B117 -> 46.59767 | F117: =quarterly_pmi!C117 -> 59.2697 | G117: =F117 -> 59.2697
A118: 1999q1 | B118: =quarterly_pmi!B118 -> 49.25422 | C118: =gdp_growth_forecast_consensus!C118 -> 1.833 | D118: =B118 -> 49.25422 | F118: =quarterly_pmi!C118 -> 66.67503 | G118: =F118 -> 66.67503
A119: 1999q2 | B119: =quarterly_pmi!B119 -> 55.40696 | C119: =gdp_growth_forecast_consensus!C119 -> 2.064333 | D119: =B119 -> 55.40696 | F119: =quarterly_pmi!C119 -> 73.12125 | G119: =F119 -> 73.12125
A120: 1999q3 | B120: =quarterly_pmi!B120 -> 57.31541 | C120: =gdp_growth_forecast_consensus!C120 -> 2.431667 | D120: =B120 -> 57.31541 | F120: =quarterly_pmi!C120 -> 73.94269 | G120: =F120 -> 73.94269
A121: 1999q4 | B121: =quarterly_pmi!B121 -> 57.77604 | C121: =gdp_growth_forecast_consensus!C121 -> 2.905 | D121: =B121 -> 57.77604 | F121: =quarterly_pmi!C121 -> 72.45512 | G121: =F121 -> 72.45512
A122: 2000q1 | B122: =quarterly_pmi!B122 -> 56.12394 | C122: =gdp_growth_forecast_consensus!C122 -> 2.659667 | D122: =B122 -> 56.12394 | F122: =quarterly_pmi!C122 -> 71.2149 | G122: =F122 -> 71.2149
A123: 2000q2 | B123: =quarterly_pmi!B123 -> 56.12898 | C123: =gdp_growth_forecast_consensus!C123 -> 2.628667 | D123: =B123 -> 56.12898 | F123: =quarterly_pmi!C123 -> 69.52824 | G123: =F123 -> 69.52824
A124: 2000q3 | B124: =quarterly_pmi!B124 -> 55.21443 | C124: =gdp_growth_forecast_consensus!C124 -> 2.659 | D124: =B124 -> 55.21443 | F124: =quarterly_pmi!C124 -> 69.06199 | G124: =F124 -> 69.06199
A125: 2000q4 | B125: =quarterly_pmi!B125 -> 55.37032 | C125: =gdp_growth_forecast_consensus!C125 -> 2.703 | D125: =B125 -> 55.37032 | F125: =quarterly_pmi!C125 -> 69.54543 | G125: =F125 -> 69.54543
... A213: 2022q4 | B213: =quarterly_pmi!B213 -> 48.46857 | C213: =gdp_growth_forecast_consensus!C213 -> -0.7296667 | D213: =B213 -> 48.46857 | F213: =quarterly_pmi!C213 -> 60.174 | G213: =F213 -> 60.174
A214: 2023q1 | B214: =quarterly_pmi!B214 -> 51.2578 | D214: =B214 -> 51.2578 | F214: =quarterly_pmi!C214 -> 69.88173 | G214: =F214 -> 69.88173
A215: 2023q2 | B215: =quarterly_pmi!B215 -> 53.90221 | D215: =B215 -> 53.90221 | F215: =quarterly_pmi!C215 -> 70.51534 | G215: =F215 -> 70.51534
A216: 2023q3 | B216: =quarterly_pmi!B216 -> 49.31581 | D216: =B216 -> 49.31581 | F216: =quarterly_pmi!C216 -> 68.8783 | G216: =F216 -> 68.8783
A217: 2023q4 | B217: =quarterly_pmi!B217 -> 50.49479 | D217: =B217 -> 50.49479 | F217: =quarterly_pmi!C217 -> 68.28609 | G217: =F217 -> 68.28609
A218: 2024q1 | B218: =quarterly_pmi!B218 -> 52.9022 | D218: =B218 -> 52.9022 | F218: =quarterly_pmi!C218 -> 72.99394 | G218: =F218 -> 72.99394
A219: 2024q2 | B219: =quarterly_pmi!B219 -> 53.12655 | D219: =B219 -> 53.12655 | F219: =quarterly_pmi!C219 -> 71.78807 | G219: =F219 -> 71.78807
A220: 2024q3 | B220: =quarterly_pmi!B220 -> 53.07604 | D220: =B220 -> 53.07604 | F220: =quarterly_pmi!C220 -> 72.97237 | G220: =F220 -> 72.97237
A221: 2024q4 | B221: =quarterly_pmi!B221 -> 50.86632 | D221: =B221 -> 50.86632 | F221: =quarterly_pmi!C221 -> 67.64009 | G221: =F221 -> 67.64009
A222: 2025q1 | B222: =quarterly_pmi!B222 -> 50.84955 | D222: =B222 -> 50.84955 | F222: =quarterly_pmi!C222 -> 65.42788 | G222: =F222 -> 65.42788
A223: 2025q2 | B223: =quarterly_pmi!B223 -> 50.25345 | D223: =B223 -> 50.25345 | F223: =quarterly_pmi!C223 -> 63.49606 | G223: =F223 -> 63.49606
A224: 2025q3 | B224: 51.67 | D224: =B224 -> 51.67 | F224: =quarterly_pmi!C224 -> 66.791365 | G224: =F224 -> 66.791365
A225: 2025q4 | B225: 52.67 | D225: =B225 -> 52.67 | F225: =quarterly_pmi!C225 -> 66.791365 | G225: =F225 -> 66.791365
A226: 2026q1 | B226: 53.67 | D226: =B226 -> 53.67 | F226: =quarterly_pmi!C226 -> 66.791365 | G226: =F226 -> 66.791365

Sheet spliced_quartely_pmi_long
B1: pmi_output | C1: g4rgdp | D1: pmi_output_SPLICED | F1: pmi_future_output | G1: pmi_future_output_SPLICED
A2: 1970q1
A3: 1970q2
A4: 1970q3 | M4: PMI OUTPUT | O4: OLS regression of PMI FUTURE OUTPUT on y-o-y gdp growth
A5: 1970q4 | M5: SUMMARY OUTPUT | O5: from 2000q1 to 2019q4
A6: 1971q1 | C6: =g4rgdp!B6 -> 3.7558928 | D6: =$N$21 + C6 *$N$22 -> 56.070287 | G6: =$N$44 + C6 * $N$45 -> 70.100758
A7: 1971q2 | C7: =g4rgdp!B7 -> 3.1690426 | D7: =$N$21 + C7 *$N$22 -> 55.457302 | G7: =$N$44 + C7 * $N$45 -> 69.323792 | M7: Regression Statistics
A8: 1971q3 | C8: =g4rgdp!B8 -> 3.9080272 | D8: =$N$21 + C8 *$N$22 -> 56.229196 | G8: =$N$44 + C8 * $N$45 -> 70.302178 | M8: Multiple R | N8: 0.54770829
A9: 1971q4 | C9: =g4rgdp!B9 -> 3.3708729 | D9: =$N$21 + C9 *$N$22 -> 55.668121 | G9: =$N$44 + C9 * $N$45 -> 69.591008 | M9: R Square | N9: 0.29998437
A10: 1972q1 | C10: =g4rgdp!B10 -> 4.063125 | D10: =$N$21 + C10 *$N$22 -> 56.391201 | G10: =$N$44 + C10 * $N$45 -> 70.507522 | M10: Adjusted R Square | N10: 0.29100981
A11: 1972q2 | C11: =g4rgdp!B11 -> 4.8928192 | D11: =$N$21 + C11 *$N$22 -> 57.257845 | G11: =$N$44 + C11 * $N$45 -> 71.606004 | M11: Standard Error | N11: 3.0757113
A12: 1972q3 | C12: =g4rgdp!B12 -> 3.4729729 | D12: =$N$21 + C12 *$N$22 -> 55.774768 | G12: =$N$44 + C12 * $N$45 -> 69.726184 | M12: Observations | N12: 80
A13: 1972q4 | C13: =g4rgdp!B13 -> 4.6296654 | D13: =$N$21 + C13 *$N$22 -> 56.982972 | G13: =$N$44 + C13 * $N$45 -> 71.257599
A14: 1973q1 | C14: =g4rgdp!B14 -> 9.2023637 | D14: =$N$21 + C14 *$N$22 -> 61.759308 | G14: =$N$44 + C14 * $N$45 -> 77.311669 | M14: ANOVA
A15: 1973q2 | C15: =g4rgdp!B15 -> 6.7873159 | D15: =$N$21 + C15 *$N$22 -> 59.23671 | G15: =$N$44 + C15 * $N$45 -> 74.114242 | N15: df | O15: SS | P15: MS | Q15: F | R15: Significance F
A16: 1973q3 | C16: =g4rgdp!B16 -> 5.5834443 | D16: =$N$21 + C16 *$N$22 -> 57.979226 | G16: =$N$44 + C16 * $N$45 -> 72.520364 | M16: Regression | N16: 1 | O16: 316.21076 | P16: 316.21076 | Q16: 33.426083 | R16: 1.4563944e-07
A17: 1973q4 | C17: =g4rgdp!B17 -> 3.6512302 | D17: =$N$21 + C17 *$N$22 -> 55.960963 | G17: =$N$44 + C17 * $N$45 -> 69.962189 | M17: Residual | N17: 78 | O17: 737.88002 | P17: 9.4600003
A18: 1974q1 | C18: =g4rgdp!B18 -> -3.9513623 | D18: =$N$21 + C18 *$N$22 -> 48.019802 | G18: =$N$44 + C18 * $N$45 -> 59.89666 | M18: Total | N18: 79 | O18: 1054.0908
A19: 1974q2 | C19: =g4rgdp!B19 -> -2.7182711 | D19: =$N$21 + C19 *$N$22 -> 49.307807 | G19: =$N$44 + C19 * $N$45 -> 61.529224
A20: 1974q3 | C20: =g4rgdp!B20 -> -1.1899593 | D20: =$N$21 + C20 *$N$22 -> 50.904179 | G20: =$N$44 + C20 * $N$45 -> 63.552648 | N20: Coefficients | O20: Standard Error | P20: t Stat | Q20: P-value | R20: Lower 95% | S20: Upper 95% | T20: Lower 95.0% | U20: Upper 95.0%
A21: 1974q4 | C21: =g4rgdp!B21 -> -2.2692069 | D21: =$N$21 + C21 *$N$22 -> 49.776869 | G21: =$N$44 + C21 * $N$45 -> 62.123767 | M21: Intercept | N21: 52.147132 | O21: 0.47496069 | P21: 109.79252 | Q21: 2.9760275e-87 | R21: 51.201557 | S21: 53.092706 | T21: 51.201557 | U21: 53.092706
A22: 1975q1 | C22: =g4rgdp!B22 -> 0.56178832 | D22: =$N$21 + C22 *$N$22 -> 52.733938 | G22: =$N$44 + C22 * $N$45 -> 65.871892 | M22: X Variable 1 | N22: 1.0445334 | O22: 0.18066731 | P22: 5.7815295 | Q22: 1.4563944e-07 | R22: 0.6848524 | S22: 1.4042144 | T22: 0.6848524 | U22: 1.4042144
A23: 1975q2 | C23: =g4rgdp!B23 -> -2.4937028 | D23: =$N$21 + C23 *$N$22 -> 49.542376 | G23: =$N$44 + C23 * $N$45 -> 61.826543
A24: 1975q3 | C24: =g4rgdp!B24 -> -3.3871268 | D24: =$N$21 + C24 *$N$22 -> 48.609165 | G24: =$N$44 + C24 * $N$45 -> 60.643686
A25: 1975q4 | C25: =g4rgdp!B25 -> -0.80965171 | D25: =$N$21 + C25 *$N$22 -> 51.301423 | G25: =$N$44 + C25 * $N$45 -> 64.05616
A26: 1976q1 | C26: =g4rgdp!B26 -> 0.83027731 | D26: =$N$21 + C26 *$N$22 -> 53.014384 | G26: =$N$44 + C26 * $N$45 -> 66.22736
A27: 1976q2 | C27: =g4rgdp!B27 -> 2.3260936 | D27: =$N$21 + C27 *$N$22 -> 54.576814 | G27: =$N$44 + C27 * $N$45 -> 68.207761 | M27: PMI FUTURE OUTPUT | O27: OLS regression of PMI FUTURE OUTPUT on y-o-y gdp growth
A28: 1976q3 | C28: =g4rgdp!B28 -> 3.8602507 | D28: =$N$21 + C28 *$N$22 -> 56.179292 | G28: =$N$44 + C28 * $N$45 -> 70.238924 | M28: SUMMARY OUTPUT | O28: from 2000q1 to 2019q4
A29: 1976q4 | C29: =g4rgdp!B29 -> 4.8335235 | D29: =$N$21 + C29 *$N$22 -> 57.195908 | G29: =$N$44 + C29 * $N$45 -> 71.527499
A30: 1977q1 | C30: =g4rgdp!B30 -> 3.23785 | D30: =$N$21 + C30 *$N$22 -> 55.529174 | G30: =$N$44 + C30 * $N$45 -> 69.41489 | M30: Regression Statistics
A31: 1977q2 | C31: =g4rgdp!B31 -> 2.6860703 | D31: =$N$21 + C31 *$N$22 -> 54.952822 | G31: =$N$44 + C31 * $N$45 -> 68.684356 | M31: Multiple R | N31: 0.55096392
A32: 1977q3 | C32: =g4rgdp!B32 -> 2.1002974 | D32: =$N$21 + C32 *$N$22 -> 54.340962 | G32: =$N$44 + C32 * $N$45 -> 67.908816 | M32: R Square | N32: 0.30356124
A33: 1977q4 | C33: =g4rgdp!B33 -> 1.7039167 | D33: =$N$21 + C33 *$N$22 -> 53.926929 | G33: =$N$44 + C33 * $N$45 -> 67.384024 | M33: Adjusted R Square | N33: 0.29463253
A34: 1978q1 | C34: =g4rgdp!B34 -> 2.5734244 | D34: =$N$21 + C34 *$N$22 -> 54.835159 | G34: =$N$44 + C34 * $N$45 -> 68.535218 | M34: Standard Error | N34: 3.8655554
A35: 1978q2 | C35: =g4rgdp!B35 -> 4.4015398 | D35: =$N$21 + C35 *$N$22 -> 56.744687 | G35: =$N$44 + C35 * $N$45 -> 70.955569 | M35: Observations | N35: 80
A36: 1978q3 | C36: =g4rgdp!B36 -> 5.1070545 | D36: =$N$21 + C36 *$N$22 -> 57.48162 | G36: =$N$44 + C36 * $N$45 -> 71.889643
A37: 1978q4 | C37: =g4rgdp!B37 -> 4.3097077 | D37: =$N$21 + C37 *$N$22 -> 56.648765 | G37: =$N$44 + C37 * $N$45 -> 70.833987 | M37: ANOVA
A38: 1979q1 | C38: =g4rgdp!B38 -> 3.0757487 | D38: =$N$21 + C38 *$N$22 -> 55.359854 | G38: =$N$44 + C38 * $N$45 -> 69.200275 | N38: df | O38: SS | P38: MS | Q38: F | R38: Significance F
A39: 1979q2 | C39: =g4rgdp!B39 -> 6.1981276 | D39: =$N$21 + C39 *$N$22 -> 58.621283 | G39: =$N$44 + C39 * $N$45 -> 73.33418 | M39: Regression | N39: 1 | O39: 508.02114 | P39: 508.02114 | Q39: 33.998361 | R39: 1.186113e-07
A40: 1979q3 | C40: =g4rgdp!B40 -> 2.6175211 | D40: =$N$21 + C40 *$N$22 -> 54.88122 | G40: =$N$44 + C40 * $N$45 -> 68.5936 | M40: Residual | N40: 78 | O40: 1165.5165 | P40: 14.942519
A41: 1979q4 | C41: =g4rgdp!B41 -> 2.7486309 | D41: =$N$21 + C41 *$N$22 -> 55.018168 | G41: =$N$44 + C41 * $N$45 -> 68.767184 | M41: Total | N41: 79 | O41: 1673.5376
A42: 1980q1 | C42: =g4rgdp!B42 -> 2.0601423 | D42: =$N$21 + C42 *$N$22 -> 54.299019 | G42: =$N$44 + C42 * $N$45 -> 67.855652
A43: 1980q2 | C43: =g4rgdp!B43 -> -4.1714987 | D43: =$N$21 + C43 *$N$22 -> 47.789862 | G43: =$N$44 + C43 * $N$45 -> 59.605209 | N43: Coefficients | O43: Standard Error | P43: t Stat | Q43: P-value | R43: Lower 95% | S43: Upper 95% | T43: Lower 95.0% | U43: Upper 95.0%
A44: 1980q3 | C44: =g4rgdp!B44 -> -2.0515807 | D44: =$N$21 + C44 *$N$22 -> 50.004187 | G44: =$N$44 + C44 * $N$45 -> 62.411895 | M44: Intercept | N44: 65.128106 | O44: 0.59693081 | P44: 109.10495 | Q44: 4.8426722e-87 | R44: 63.939708 | S44: 66.316504 | T44: 63.939708 | U44: 66.316504
A45: 1980q4 | C45: =g4rgdp!B45 -> -4.0958399 | D45: =$N$21 + C45 *$N$22 -> 47.86889 | G45: =$N$44 + C45 * $N$45 -> 59.705378 | M45: X Variable 1 | N45: 1.3239601 | O45: 0.22706276 | P45: 5.8308113 | Q45: 1.186113e-07 | R45: 0.87191288 | S45: 1.7760073 | T45: 0.87191288 | U45: 1.7760073
A46: 1981q1 | C46: =g4rgdp!B46 -> -3.191468 | D46: =$N$21 + C46 *$N$22 -> 48.813537 | G46: =$N$44 + C46 * $N$45 -> 60.90273
A47: 1981q2 | C47: =g4rgdp!B47 -> -0.902509 | D47: =$N$21 + C47 *$N$22 -> 51.204431 | G47: =$N$44 + C47 * $N$45 -> 63.93322
A48: 1981q3 | C48: =g4rgdp!B48 -> 0.3632609 | D48: =$N$21 + C48 *$N$22 -> 52.52657 | G48: =$N$44 + C48 * $N$45 -> 65.609049
A49: 1981q4 | C49: =g4rgdp!B49 -> 1.5223012 | D49: =$N$21 + C49 *$N$22 -> 53.737226 | G49: =$N$44 + C49 * $N$45 -> 67.143572
A50: 1982q1 | C50: =g4rgdp!B50 -> 1.7684045 | D50: =$N$21 + C50 *$N$22 -> 53.994289 | G50: =$N$44 + C50 * $N$45 -> 67.469403
A51: 1982q2 | C51: =g4rgdp!B51 -> 2.4772569 | D51: =$N$21 + C51 *$N$22 -> 54.734709 | G51: =$N$44 + C51 * $N$45 -> 68.407896
A52: 1982q3 | C52: =g4rgdp!B52 -> 1.5349109 | D52: =$N$21 + C52 *$N$22 -> 53.750397 | G52: =$N$44 + C52 * $N$45 -> 67.160267
A53: 1982q4 | C53: =g4rgdp!B53 -> 2.0837045 | D53: =$N$21 + C53 *$N$22 -> 54.32363 | G53: =$N$44 + C53 * $N$45 -> 67.886848
A54: 1983q1 | C54: =g4rgdp!B54 -> 3.867308 | D54: =$N$21 + C54 *$N$22 -> 56.186664 | G54: =$N$44 + C54 * $N$45 -> 70.248268
A55: 1983q2 | C55: =g4rgdp!B55 -> 3.5295883 | D55: =$N$21 + C55 *$N$22 -> 55.833904 | G55: =$N$44 + C55 * $N$45 -> 69.80114
A56: 1983q3 | C56: =g4rgdp!B56 -> 4.4642846 | D56: =$N$21 + C56 *$N$22 -> 56.810226 | G56: =$N$44 + C56 * $N$45 -> 71.038641
A57: 1983q4 | C57: =g4rgdp!B57 -> 4.5316389 | D57: =$N$21 + C57 *$N$22 -> 56.88058 | G57: =$N$44 + C57 * $N$45 -> 71.127815
... A110: 1997q1 | C110: =g4rgdp!B110 -> 4.1354058 | D110: =$N$21 + C110 *$N$22 -> 56.466701 | G110: =$N$44 + C110 * $N$45 -> 70.603219
A111: 1997q2 | C111: =g4rgdp!B111 -> 4.9268746 | D111: =$N$21 + C111 *$N$22 -> 57.293417 | F111: =quarterly_pmi!C111 -> 75.51289 | G111: =F111 -> 75.51289
A112: 1997q3 | C112: =g4rgdp!B112 -> 4.9315411 | D112: =$N$21 + C112 *$N$22 -> 57.298291 | F112: =quarterly_pmi!C112 -> 71.99351 | G112: =F112 -> 71.99351
A113: 1997q4 | C113: =g4rgdp!B113 -> 5.0521653 | D113: =$N$21 + C113 *$N$22 -> 57.424287 | F113: =quarterly_pmi!C113 -> 72.64549 | G113: =F113 -> 72.64549
A114: 1998q1 | B114: =quarterly_pmi!B114 -> 57.14592 | C114: =g4rgdp!B114 -> 4.1719365 | D114: =B114 -> 57.14592 | F114: =quarterly_pmi!C114 -> 70.32822 | G114: =F114 -> 70.32822
A115: 1998q2 | B115: =quarterly_pmi!B115 -> 54.24487 | C115: =g4rgdp!B115 -> 3.6393307 | D115: =B115 -> 54.24487 | F115: =quarterly_pmi!C115 -> 67.17878 | G115: =F115 -> 67.17878
A116: 1998q3 | B116: =quarterly_pmi!B116 -> 50.9725 | C116: =g4rgdp!B116 -> 2.9031231 | D116: =B116 -> 50.9725 | F116: =quarterly_pmi!C116 -> 61.1142 | G116: =F116 -> 61.1142
A117: 1998q4 | B117: =quarterly_pmi!B117 -> 46.59767 | C117: =g4rgdp!B117 -> 2.0918382 | D117: =B117 -> 46.59767 | F117: =quarterly_pmi!C117 -> 59.2697 | G117: =F117 -> 59.2697
A118: 1999q1 | B118: =quarterly_pmi!B118 -> 49.25422 | C118: =g4rgdp!B118 -> 2.0629498 | D118: =B118 -> 49.25422 | F118: =quarterly_pmi!C118 -> 66.67503 | G118: =F118 -> 66.67503
A119: 1999q2 | B119: =quarterly_pmi!B119 -> 55.40696 | C119: =g4rgdp!B119 -> 1.8521941 | D119: =B119 -> 55.40696 | F119: =quarterly_pmi!C119 -> 73.12125 | G119: =F119 -> 73.12125
A120: 1999q3 | B120: =quarterly_pmi!B120 -> 57.31541 | C120: =g4rgdp!B120 -> 3.3537336 | D120: =B120 -> 57.31541 | F120: =quarterly_pmi!C120 -> 73.94269 | G120: =F120 -> 73.94269
A121: 1999q4 | B121: =quarterly_pmi!B121 -> 57.77604 | C121: =g4rgdp!B121 -> 4.3021026 | D121: =B121 -> 57.77604 | F121: =quarterly_pmi!C121 -> 72.45512 | G121: =F121 -> 72.45512
A122: 2000q1 | B122: =quarterly_pmi!B122 -> 56.12394 | C122: =g4rgdp!B122 -> 4.9448007 | D122: =B122 -> 56.12394 | F122: =quarterly_pmi!C122 -> 71.2149 | G122: =F122 -> 71.2149
A123: 2000q2 | B123: =quarterly_pmi!B123 -> 56.12898 | C123: =g4rgdp!B123 -> 5.2988789 | D123: =B123 -> 56.12898 | F123: =quarterly_pmi!C123 -> 69.52824 | G123: =F123 -> 69.52824
A124: 2000q3 | B124: =quarterly_pmi!B124 -> 55.21443 | C124: =g4rgdp!B124 -> 4.2461604 | D124: =B124 -> 55.21443 | F124: =quarterly_pmi!C124 -> 69.06199 | G124: =F124 -> 69.06199
A125: 2000q4 | B125: =quarterly_pmi!B125 -> 55.37032 | C125: =g4rgdp!B125 -> 3.2417272 | D125: =B125 -> 55.37032 | F125: =quarterly_pmi!C125 -> 69.54543 | G125: =F125 -> 69.54543
... A223: 2025q2 | B223: =quarterly_pmi!B223 -> 50.25345 | C223: =g4rgdp!B223 -> 1.4143772 | D223: =B223 -> 50.25345 | F223: =quarterly_pmi!C223 -> 63.49606 | G223: =F223 -> 63.49606
A224: 2025q3 | B224: 51.67 | D224: =B224 -> 51.67 | F224: =quarterly_pmi!C224 -> 66.791365 | G224: =F224 -> 66.791365
A225: 2025q4 | B225: 52.67 | D225: =B225 -> 52.67 | F225: =quarterly_pmi!C225 -> 66.791365 | G225: =F225 -> 66.791365
A226: 2026q1 | B226: 53.67 | D226: =B226 -> 53.67 | F226: =quarterly_pmi!C226 -> 66.791365 | G226: =F226 -> 66.791365

Sheet spliced_inflation_expectations
B1: infl1_m | C1: g4infl | D1: infl1_m_spliced
A2: 1970q1 | C2: =g4infl!B2 -> 5.0102728 | D2: =$Y$34+C2*$Y$35 -> 3.1158753
A3: 1970q2 | C3: =g4infl!B3 -> 5.8689632 | D3: =$Y$34+C3*$Y$35 -> 3.4165041
A4: 1970q3 | C4: =g4infl!B4 -> 6.8417077 | D4: =$Y$34+C4*$Y$35 -> 3.7570635
A5: 1970q4 | C5: =g4infl!B5 -> 7.7038182 | D5: =$Y$34+C5*$Y$35 -> 4.0588898
A6: 1971q1 | C6: =g4infl!B6 -> 8.5882079 | D6: =$Y$34+C6*$Y$35 -> 4.368516
A7: 1971q2 | C7: =g4infl!B7 -> 9.8446789 | D7: =$Y$34+C7*$Y$35 -> 4.8084085
A8: 1971q3 | C8: =g4infl!B8 -> 10.113419 | D8: =$Y$34+C8*$Y$35 -> 4.902495
A9: 1971q4 | C9: =g4infl!B9 -> 9.2129552 | D9: =$Y$34+C9*$Y$35 -> 4.5872411
A10: 1972q1 | C10: =g4infl!B10 -> 7.9540339 | D10: =$Y$34+C10*$Y$35 -> 4.1464907
A11: 1972q2 | C11: =g4infl!B11 -> 6.17795 | D11: =$Y$34+C11*$Y$35 -> 3.5246809
A12: 1972q3 | C12: =g4infl!B12 -> 6.4592298 | D12: =$Y$34+C12*$Y$35 -> 3.6231574
A13: 1972q4 | C13: =g4infl!B13 -> 7.7151517 | D13: =$Y$34+C13*$Y$35 -> 4.0628577
... A17: 1973q4 | C17: =g4infl!B17 -> 10.271493 | D17: =$Y$34+C17*$Y$35 -> 4.957837
A18: 1974q1 | C18: =g4infl!B18 -> 12.869374 | D18: =$Y$34+C18*$Y$35 -> 5.8673592 | X18: SUMMARY OUTPUT
A19: 1974q2 | C19: =g4infl!B19 -> 15.885168 | D19: =$Y$34+C19*$Y$35 -> 6.9231933
A20: 1974q3 | C20: =g4infl!B20 -> 17.020301 | D20: =$Y$34+C20*$Y$35 -> 7.3206053 | X20: Regression Statistics
A21: 1974q4 | C21: =g4infl!B21 -> 18.180891 | D21: =$Y$34+C21*$Y$35 -> 7.7269296 | X21: Multiple R | Y21: 0.84116324
A22: 1975q1 | C22: =g4infl!B22 -> 20.308881 | D22: =$Y$34+C22*$Y$35 -> 8.4719421 | X22: R Square | Y22: 0.70755559
A23: 1975q2 | C23: =g4infl!B23 -> 24.286608 | D23: =$Y$34+C23*$Y$35 -> 9.864551 | X23: Adjusted R Square | Y23: 0.70545167
A24: 1975q3 | C24: =g4infl!B24 -> 26.565802 | D24: =$Y$34+C24*$Y$35 -> 10.6625 | X24: Standard Error | Y24: 0.45444462
A25: 1975q4 | C25: =g4infl!B25 -> 25.311323 | D25: =$Y$34+C25*$Y$35 -> 10.223305 | X25: Observations | Y25: 141
A26: 1976q1 | C26: =g4infl!B26 -> 22.452897 | D26: =$Y$34+C26*$Y$35 -> 9.2225658
A27: 1976q2 | C27: =g4infl!B27 -> 15.972029 | D27: =$Y$34+C27*$Y$35 -> 6.9536035 | X27: ANOVA
A28: 1976q3 | C28: =g4infl!B28 -> 13.650502 | D28: =$Y$34+C28*$Y$35 -> 6.1408332 | Y28: df | Z28: SS | AA28: MS | AB28: F | AC28: Significance F
A29: 1976q4 | C29: =g4infl!B29 -> 14.929497 | D29: =$Y$34+C29*$Y$35 -> 6.5886115 | X29: Regression | Y29: 1 | Z29: 69.453475 | AA29: 69.453475 | AB29: 336.30401 | AC29: 6.2161064e-39
A30: 1977q1 | C30: =g4infl!B30 -> 16.506794 | D30: =$Y$34+C30*$Y$35 -> 7.1408257 | X30: Residual | Y30: 139 | Z30: 28.706268 | AA30: 0.20651992
A31: 1977q2 | C31: =g4infl!B31 -> 17.409084 | D31: =$Y$34+C31*$Y$35 -> 7.4567187 | X31: Total | Y31: 140 | Z31: 98.159743
A32: 1977q3 | C32: =g4infl!B32 -> 16.575501 | D32: =$Y$34+C32*$Y$35 -> 7.16488
A33: 1977q4 | C33: =g4infl!B33 -> 13.070582 | D33: =$Y$34+C33*$Y$35 -> 5.9378025 | Y33: Coefficients | Z33: Standard Error | AA33: t Stat | AB33: P-value | AC33: Lower 95% | AD33: Upper 95% | AE33: Lower 95.0% | AF33: Upper 95.0%
A34: 1978q1 | C34: =g4infl!B34 -> 9.4964726 | D34: =$Y$34+C34*$Y$35 -> 4.686501 | X34: Intercept | Y34: 1.3617708 | Z34: 0.065999556 | AA34: 20.63303 | AB34: 3.7759553e-44 | AC34: 1.2312779 | AD34: 1.4922637 | AE34: 1.2312779 | AF34: 1.4922637
A35: 1978q2 | C35: =g4infl!B35 -> 7.6796143 | D35: =$Y$34+C35*$Y$35 -> 4.050416 | X35: X Variable 1 | Y35: 0.35010159 | Z35: 0.019090973 | AA35: 18.338593 | AB35: 6.2161064e-39 | AC35: 0.31235534 | AD35: 0.38784783 | AE35: 0.31235534 | AF35: 0.38784783
A36: 1978q3 | C36: =g4infl!B36 -> 7.8491467 | D36: =$Y$34+C36*$Y$35 -> 4.1097695
A37: 1978q4 | C37: =g4infl!B37 -> 8.0917713 | D37: =$Y$34+C37*$Y$35 -> 4.1947128
A38: 1979q1 | C38: =g4infl!B38 -> 9.5820693 | D38: =$Y$34+C38*$Y$35 -> 4.7164685
A39: 1979q2 | C39: =g4infl!B39 -> 10.587233 | D39: =$Y$34+C39*$Y$35 -> 5.0683778
A40: 1979q3 | C40: =g4infl!B40 -> 15.977915 | D40: =$Y$34+C40*$Y$35 -> 6.9556641
A41: 1979q4 | C41: =g4infl!B41 -> 17.258968 | D41: =$Y$34+C41*$Y$35 -> 7.4041629
A42: 1980q1 | C42: =g4infl!B42 -> 19.084109 | D42: =$Y$34+C42*$Y$35 -> 8.0431477
A43: 1980q2 | C43: =g4infl!B43 -> 21.548399 | D43: =$Y$34+C43*$Y$35 -> 8.9058996
A44: 1980q3 | C44: =g4infl!B44 -> 16.358912 | D44: =$Y$34+C44*$Y$35 -> 7.0890519
A45: 1980q4 | C45: =g4infl!B45 -> 15.279914 | D45: =$Y$34+C45*$Y$35 -> 6.711293
A46: 1981q1 | C46: =g4infl!B46 -> 12.702674 | D46: =$Y$34+C46*$Y$35 -> 5.8089971
A47: 1981q2 | C47: =g4infl!B47 -> 11.700649 | D47: =$Y$34+C47*$Y$35 -> 5.4581867
... A80: 1989q3 | C80: =g4infl!B80 -> 5.6396149 | D80: =$Y$34+C80*$Y$35 -> 3.3362089
A81: 1989q4 | B81: 4.491305 | C81: =g4infl!B81 -> 5.8265583 | D81: =B81 -> 4.491305
A82: 1990q1 | B82: 4.11668 | C82: =g4infl!B82 -> 6.1662198 | D82: =B82 -> 4.11668
A83: 1990q2 | B83: 4.143615 | C83: =g4infl!B83 -> 8.0052493 | D83: =B83 -> 4.143615
A84: 1990q3 | B84: 4.408522 | C84: =g4infl!B84 -> 8.7890625 | D84: =B84 -> 4.408522
A85: 1990q4 | B85: 4.911894 | C85: =g4infl!B85 -> 9.2189501 | D85: =B85 -> 4.911894
A86: 1991q1 | B86: 3.608118 | C86: =g4infl!B86 -> 8.3964646 | D86: =B86 -> 3.608118
A87: 1991q2 | B87: 3.360015 | C87: =g4infl!B87 -> 7.7764277 | D87: =B87 -> 3.360015
A88: 1991q3 | B88: 3.211499 | C88: =g4infl!B88 -> 7.3010174 | D88: =B88 -> 3.211499
A89: 1991q4 | B89: 2.998734 | C89: =g4infl!B89 -> 6.4478312 | D89: =B89 -> 2.998734
A90: 1992q1 | B90: 2.844782 | C90: =g4infl!B90 -> 6.2317997 | D90: =B90 -> 2.844782
A91: 1992q2 | B91: 2.736298 | C91: =g4infl!B91 -> 4.9605411 | D91: =B91 -> 2.736298
A92: 1992q3 | B92: 2.526251 | C92: =g4infl!B92 -> 3.9598438 | D92: =B92 -> 2.526251
... A223: 2025q2 | B223: 2.345 | C223: =g4infl!B223 -> 4.07 | D223: =B223 -> 2.345
A224: 2025q3 | B224: 2.4864667 | D224: =B224 -> 2.4864667
A225: 2025q4 | B225: 3.4864667 | D225: =B225 -> 3.4864667
A226: 2026q1 | B226: 4.4864667 | D226: =B226 -> 4.4864667

Sheet spliced_mgdp
A1: from other_series.do | B1: mgdp_growth | C1: g4rgdp | D1: infl1_m_spliced | G1: mgdp_growth | H1: this is the year over year growth between the first average of the first two months of the current quarter and the 3 months in the same quarter the previous year
A2: 1970q1
A3: 1970q2
A4: 1970q3
A5: 1970q4
A6: 1971q1 | C6: =g4rgdp!B6 -> 3.7558928 | D6: =$Y$34+C6*$Y$35 -> 0.038184271
A7: 1971q2 | C7: =g4rgdp!B7 -> 3.1690426 | D7: =$Y$34+C7*$Y$35 -> 0.03229202
A8: 1971q3 | C8: =g4rgdp!B8 -> 3.9080272 | D8: =$Y$34+C8*$Y$35 -> 0.039711773
A9: 1971q4 | C9: =g4rgdp!B9 -> 3.3708729 | D9: =$Y$34+C9*$Y$35 -> 0.034318492
A10: 1972q1 | C10: =g4rgdp!B10 -> 4.063125 | D10: =$Y$34+C10*$Y$35 -> 0.041269027
A11: 1972q2 | C11: =g4rgdp!B11 -> 4.8928192 | D11: =$Y$34+C11*$Y$35 -> 0.049599546
A12: 1972q3 | C12: =g4rgdp!B12 -> 3.4729729 | D12: =$Y$34+C12*$Y$35 -> 0.035343623
A13: 1972q4 | C13: =g4rgdp!B13 -> 4.6296654 | D13: =$Y$34+C13*$Y$35 -> 0.046957358
A14: 1973q1 | C14: =g4rgdp!B14 -> 9.2023637 | D14: =$Y$34+C14*$Y$35 -> 0.092869392
A15: 1973q2 | C15: =g4rgdp!B15 -> 6.7873159 | D15: =$Y$34+C15*$Y$35 -> 0.068621181
A16: 1973q3 | C16: =g4rgdp!B16 -> 5.5834443 | D16: =$Y$34+C16*$Y$35 -> 0.056533745 | X16: 1998q1 - 2024q4
A17: 1973q4 | C17: =g4rgdp!B17 -> 3.6512302 | D17: =$Y$34+C17*$Y$35 -> 0.037133409
A18: 1974q1 | C18: =g4rgdp!B18 -> -3.9513623 | D18: =$Y$34+C18*$Y$35 -> -0.039200183 | X18: SUMMARY OUTPUT
A19: 1974q2 | C19: =g4rgdp!B19 -> -2.7182711 | D19: =$Y$34+C19*$Y$35 -> -0.026819369
A20: 1974q3 | C20: =g4rgdp!B20 -> -1.1899593 | D20: =$Y$34+C20*$Y$35 -> -0.011474402 | X20: Regression Statistics
A21: 1974q4 | C21: =g4rgdp!B21 -> -2.2692069 | D21: =$Y$34+C21*$Y$35 -> -0.022310554 | X21: Multiple R | Y21: 0.99472491
A22: 1975q1 | C22: =g4rgdp!B22 -> 0.56178832 | D22: =$Y$34+C22*$Y$35 -> 0.0061139653 | X22: R Square | Y22: 0.98947765
A23: 1975q2 | C23: =g4rgdp!B23 -> -2.4937028 | D23: =$Y$34+C23*$Y$35 -> -0.024564598 | X23: Adjusted R Square | Y23: 0.98937838
A24: 1975q3 | C24: =g4rgdp!B24 -> -3.3871268 | D24: =$Y$34+C24*$Y$35 -> -0.033534994 | X24: Standard Error | Y24: 0.0044866821
A25: 1975q4 | C25: =g4rgdp!B25 -> -0.80965171 | D25: =$Y$34+C25*$Y$35 -> -0.0076559355 | X25: Observations | Y25: 108
A26: 1976q1 | C26: =g4rgdp!B26 -> 0.83027731 | D26: =$Y$34+C26*$Y$35 -> 0.0088097206
A27: 1976q2 | C27: =g4rgdp!B27 -> 2.3260936 | D27: =$Y$34+C27*$Y$35 -> 0.023828417 | X27: ANOVA
A28: 1976q3 | C28: =g4rgdp!B28 -> 3.8602507 | D28: =$Y$34+C28*$Y$35 -> 0.039232074 | Y28: df | Z28: SS | AA28: MS | AB28: F | AC28: Significance F
A29: 1976q4 | C29: =g4rgdp!B29 -> 4.8335235 | D29: =$Y$34+C29*$Y$35 -> 0.049004189 | X29: Regression | Y29: 1 | Z29: 0.20065485 | AA29: 0.20065485 | AB29: 9967.794 | AC29: 1.1547701e-106
A30: 1977q1 | C30: =g4rgdp!B30 -> 3.23785 | D30: =$Y$34+C30*$Y$35 -> 0.032982878 | X30: Residual | Y30: 106 | Z30: 0.0021338135 | AA30: 2.0130316e-05
A31: 1977q2 | C31: =g4rgdp!B31 -> 2.6860703 | D31: =$Y$34+C31*$Y$35 -> 0.027442752 | X31: Total | Y31: 107 | Z31: 0.20278866
A32: 1977q3 | C32: =g4rgdp!B32 -> 2.1002974 | D32: =$Y$34+C32*$Y$35 -> 0.021561317
A33: 1977q4 | C33: =g4rgdp!B33 -> 1.7039167 | D33: =$Y$34+C33*$Y$35 -> 0.01758147 | Y33: Coefficients | Z33: Standard Error | AA33: t Stat | AB33: P-value | AC33: Lower 95% | AD33: Upper 95% | AE33: Lower 95.0% | AF33: Upper 95.0%
A34: 1978q1 | C34: =g4rgdp!B34 -> 2.5734244 | D34: =$Y$34+C34*$Y$35 -> 0.026311734 | X34: Intercept | Y34: 0.00047334726 | Z34: 0.00046476738 | AA34: 1.0184606 | AB34: 0.31077805 | AC34: -0.00044809927 | AD34: 0.0013947938 | AE34: -0.00044809927 | AF34: 0.0013947938
A35: 1978q2 | C35: =g4rgdp!B35 -> 4.4015398 | D35: =$Y$34+C35*$Y$35 -> 0.04466687 | X35: X Variable 1 | Y35: 0.010040469 | Z35: 0.00010056676 | AA35: 99.83884 | AB35: 1.1547701e-106 | AC35: 0.0098410853 | AD35: 0.010239852 | AE35: 0.0098410853 | AF35: 0.010239852
A36: 1978q3 | C36: =g4rgdp!B36 -> 5.1070545 | D36: =$Y$34+C36*$Y$35 -> 0.051750568
A37: 1978q4 | C37: =g4rgdp!B37 -> 4.3097077 | D37: =$Y$34+C37*$Y$35 -> 0.043744832
A38: 1979q1 | C38: =g4rgdp!B38 -> 3.0757487 | D38: =$Y$34+C38*$Y$35 -> 0.031355306
A39: 1979q2 | C39: =g4rgdp!B39 -> 6.1981276 | D39: =$Y$34+C39*$Y$35 -> 0.062705453
A40: 1979q3 | C40: =g4rgdp!B40 -> 2.6175211 | D40: =$Y$34+C40*$Y$35 -> 0.026754486
A41: 1979q4 | C41: =g4rgdp!B41 -> 2.7486309 | D41: =$Y$34+C41*$Y$35 -> 0.02807089
A42: 1980q1 | C42: =g4rgdp!B42 -> 2.0601423 | D42: =$Y$34+C42*$Y$35 -> 0.021158141
A43: 1980q2 | C43: =g4rgdp!B43 -> -4.1714987 | D43: =$Y$34+C43*$Y$35 -> -0.041410455
A44: 1980q3 | C44: =g4rgdp!B44 -> -2.0515807 | D44: =$Y$34+C44*$Y$35 -> -0.020125484
A45: 1980q4 | C45: =g4rgdp!B45 -> -4.0958399 | D45: =$Y$34+C45*$Y$35 -> -0.040650805
A46: 1981q1 | C46: =g4rgdp!B46 -> -3.191468 | D46: =$Y$34+C46*$Y$35 -> -0.031570488
A47: 1981q2 | C47: =g4rgdp!B47 -> -0.902509 | D47: =$Y$34+C47*$Y$35 -> -0.0085882661
... A113: 1997q4 | C113: =g4rgdp!B113 -> 5.0521653 | D113: =$Y$34+C113*$Y$35 -> 0.051199455
A114: 1998q1 | B114: 0.040205073 | C114: =g4rgdp!B114 -> 4.1719365 | D114: =B114 -> 0.040205073
A115: 1998q2 | B115: 0.036858974 | C115: =g4rgdp!B115 -> 3.6393307 | D115: =B115 -> 0.036858974
A116: 1998q3 | B116: 0.030752916 | C116: =g4rgdp!B116 -> 2.9031231 | D116: =B116 -> 0.030752916
A117: 1998q4 | B117: 0.023797071 | C117: =g4rgdp!B117 -> 2.0918382 | D117: =B117 -> 0.023797071
A118: 1999q1 | B118: 0.022055008 | C118: =g4rgdp!B118 -> 2.0629498 | D118: =B118 -> 0.022055008
A119: 1999q2 | B119: 0.016752577 | C119: =g4rgdp!B119 -> 1.8521941 | D119: =B119 -> 0.016752577
A120: 1999q3 | B120: 0.031876607 | C120: =g4rgdp!B120 -> 3.3537336 | D120: =B120 -> 0.031876607
A121: 1999q4 | B121: 0.043877551 | C121: =g4rgdp!B121 -> 4.3021026 | D121: =B121 -> 0.043877551
A122: 2000q1 | B122: 0.052511416 | C122: =g4rgdp!B122 -> 4.9448007 | D122: =B122 -> 0.052511416
A123: 2000q2 | B123: 0.051593323 | C123: =g4rgdp!B123 -> 5.2988789 | D123: =B123 -> 0.051593323
A124: 2000q3 | B124: 0.042992048 | C124: =g4rgdp!B124 -> 4.2461604 | D124: =B124 -> 0.042992048
A125: 2000q4 | B125: 0.032486566 | C125: =g4rgdp!B125 -> 3.2417272 | D125: =B125 -> 0.032486566
... A226: 2026q1 | B226: 2.0133268 | C226: =g4rgdp!B226 -> 0.948256 | D226: =B226 -> 2.0133268

Sheet spliced_housing_approvals
B1: House_price | C1: Housing approvals | D1: splice_ols
A2: 1970q1 | B2: =house_price_growth!B2 -> 0.1497 | D2: =$K$22+B2*$K$23 -> 212424.41
A3: 1970q2 | B3: =house_price_growth!B3 -> -3.1935 | D3: =$K$22+B3*$K$23 -> 188184.35
A4: 1970q3 | B4: =house_price_growth!B4 -> 0.6825 | D4: =$K$22+B4*$K$23 -> 216287.5
A5: 1970q4 | B5: =house_price_growth!B5 -> -2.3023 | D5: =$K$22+B5*$K$23 -> 194646.05
A6: 1971q1 | B6: =house_price_growth!B6 -> -0.8242 | D6: =$K$22+B6*$K$23 -> 205363.09 | J6: SUMMARY OUTPUT
A7: 1971q2 | B7: =house_price_growth!B7 -> 0.7281 | D7: =$K$22+B7*$K$23 -> 216618.13
A8: 1971q3 | B8: =house_price_growth!B8 -> 1.6004 | D8: =$K$22+B8*$K$23 -> 222942.79 | J8: Regression Statistics
A9: 1971q4 | B9: =house_price_growth!B9 -> 7.2469 | D9: =$K$22+B9*$K$23 -> 263883.05 | J9: Multiple R | K9: 0.68846282
A10: 1972q1 | B10: =house_price_growth!B10 -> 12.5296 | D10: =$K$22+B10*$K$23 -> 302185.56 | J10: R Square | K10: 0.47398106
A11: 1972q2 | B11: =house_price_growth!B11 -> 22.093 | D11: =$K$22+B11*$K$23 -> 371525.52 | J11: Adjusted R Square | K11: 0.46977291
A12: 1972q3 | B12: =house_price_growth!B12 -> 30.8904 | D12: =$K$22+B12*$K$23 -> 435311.56 | J12: Standard Error | K12: 51973.755
A13: 1972q4 | B13: =house_price_growth!B13 -> 33.2083 | D13: =$K$22+B13*$K$23 -> 452117.62 | J13: Observations | K13: 127
A14: 1973q1 | B14: =house_price_growth!B14 -> 40.0542 | D14: =$K$22+B14*$K$23 -> 501754.2
A15: 1973q2 | B15: =house_price_growth!B15 -> 32.385 | D15: =$K$22+B15*$K$23 -> 446148.24 | J15: ANOVA
A16: 1973q3 | B16: =house_price_growth!B16 -> 22.8971 | D16: =$K$22+B16*$K$23 -> 377355.69 | K16: df | L16: SS | M16: MS | N16: F | O16: Significance F
A17: 1973q4 | B17: =house_price_growth!B17 -> 13.7057 | D17: =$K$22+B17*$K$23 -> 310712.94 | J17: Regression | K17: 1 | L17: 3.0425506e+11 | M17: 3.0425506e+11 | N17: 112.63403 | O17: 3.7463242e-19
A18: 1974q1 | B18: =house_price_growth!B18 -> 0.8013 | D18: =$K$22+B18*$K$23 -> 217148.87 | J18: Residual | K18: 125 | L18: 3.376589e+11 | M18: 2.7012712e+09
A19: 1974q2 | B19: =house_price_growth!B19 -> -6.0824 | D19: =$K$22+B19*$K$23 -> 167238.22 | J19: Total | K19: 126 | L19: 6.4191396e+11
A20: 1974q3 | B20: =house_price_growth!B20 -> -11.137 | D20: =$K$22+B20*$K$23 -> 130589.56
A21: 1974q4 | B21: =house_price_growth!B21 -> -11.7595 | D21: =$K$22+B21*$K$23 -> 126076.09 | K21: Coefficients | L21: Standard Error | M21: t Stat | N21: P-value | O21: Lower 95% | P21: Upper 95% | Q21: Lower 95.0% | R21: Upper 95.0%
A22: 1975q1 | B22: =house_price_growth!B22 -> -13.2102 | D22: =$K$22+B22*$K$23 -> 115557.71 | J22: Intercept | K22: 211339 | L22: 5057.609 | M22: 41.786346 | N22: 2.6194967e-75 | O22: 201329.36 | P22: 221348.64 | Q22: 201329.36 | R22: 221348.64
A23: 1975q2 | B23: =house_price_growth!B23 -> -13.8772 | D23: =$K$22+B23*$K$23 -> 110721.59 | J23: X Variable 1 | K23: 7250.5555 | L23: 683.18208 | M23: 10.612918 | N23: 3.7463242e-19 | O23: 5898.4533 | P23: 8602.6576 | Q23: 5898.4533 | R23: 8602.6576
A24: 1975q3 | B24: =house_price_growth!B24 -> -13.7387 | D24: =$K$22+B24*$K$23 -> 111725.79
A25: 1975q4 | B25: =house_price_growth!B25 -> -12.7939 | D25: =$K$22+B25*$K$23 -> 118576.12
A26: 1976q1 | B26: =house_price_growth!B26 -> -10.0465 | D26: =$K$22+B26*$K$23 -> 138496.3
A27: 1976q2 | B27: =house_price_growth!B27 -> -4.8136 | D27: =$K$22+B27*$K$23 -> 176437.73
A28: 1976q3 | B28: =house_price_growth!B28 -> -4.1456 | D28: =$K$22+B28*$K$23 -> 181281.1
A29: 1976q4 | B29: =house_price_growth!B29 -> -4.2324 | D29: =$K$22+B29*$K$23 -> 180651.75
A30: 1977q1 | B30: =house_price_growth!B30 -> -7.4621 | D30: =$K$22+B30*$K$23 -> 157234.63
A31: 1977q2 | B31: =house_price_growth!B31 -> -8.9742 | D31: =$K$22+B31*$K$23 -> 146271.07
A32: 1977q3 | B32: =house_price_growth!B32 -> -7.7491 | D32: =$K$22+B32*$K$23 -> 155153.72
A33: 1977q4 | B33: =house_price_growth!B33 -> -3.3426 | D33: =$K$22+B33*$K$23 -> 187103.29
A34: 1978q1 | B34: =house_price_growth!B34 -> 1.4342 | D34: =$K$22+B34*$K$23 -> 221737.75
A35: 1978q2 | B35: =house_price_growth!B35 -> 6.3121 | D35: =$K$22+B35*$K$23 -> 257105.23
... A94: 1993q1 | B94: =house_price_growth!B94 -> -7.6128 | D94: =$K$22+B94*$K$23 -> 156141.97
A95: 1993q2 | B95: =house_price_growth!B95 -> -4.6303 | C95: 259144 | D95: =C95 -> 259144
A96: 1993q3 | B96: =house_price_growth!B96 -> -3.2724 | C96: 247303 | D96: =C96 -> 247303
A97: 1993q4 | B97: =house_price_growth!B97 -> -0.8863 | C97: 243875 | D97: =C97 -> 243875
A98: 1994q1 | B98: =house_price_growth!B98 -> -0.3898 | C98: 266887 | D98: =C98 -> 266887
A99: 1994q2 | B99: =house_price_growth!B99 -> 0.648 | C99: 258505 | D99: =C99 -> 258505
A100: 1994q3 | B100: =house_price_growth!B100 -> 0.6217 | C100: 241860 | D100: =C100 -> 241860
A101: 1994q4 | B101: =house_price_growth!B101 -> 1.7744 | C101: 249580 | D101: =C101 -> 249580
A102: 1995q1 | B102: =house_price_growth!B102 -> -0.9153 | C102: 234373 | D102: =C102 -> 234373
A103: 1995q2 | B103: =house_price_growth!B103 -> -1.0791 | C103: 214744 | D103: =C103 -> 214744
A104: 1995q3 | B104: =house_price_growth!B104 -> -2.2715 | C104: 222949 | D104: =C104 -> 222949
A105: 1995q4 | B105: =house_price_growth!B105 -> -3.2057 | C105: 244735 | D105: =C105 -> 244735
A106: 1996q1 | B106: =house_price_growth!B106 -> -0.639 | C106: 247838 | D106: =C106 -> 247838
... A223: 2025q2 | B223: =house_price_growth!B223 -> -0.636 | C223: 188787 | D223: =C223 -> 188787

Sheet g4rgdp_gap
B1: UK
A2: 1970q1 | B2: 123456789
A3: 1970q2 | B3: 123456789
A4: 1970q3 | B4: 123456789
A5: 1970q4 | B5: 123456789
A6: 1971q1 | B6: 123456789
A7: 1971q2 | B7: 123456789
A8: 1971q3 | B8: 123456789
A9: 1971q4 | B9: 123456789
A10: 1972q1 | B10: 123456789
A11: 1972q2 | B11: 123456789
A12: 1972q3 | B12: 123456789
A13: 1972q4 | B13: 123456789
... A224: 2025q3 | B224: -0.50763687

Sheet pmi_composite
B1: UK | C1: US | D1: EA
A2: 1970q1 | B2: 123456789 | C2: 123456789 | D2: 123456789
A3: 1970q2 | B3: 123456789 | C3: 123456789 | D3: 123456789
A4: 1970q3 | B4: 123456789 | C4: 123456789 | D4: 123456789
A5: 1970q4 | B5: 123456789 | C5: 123456789 | D5: 123456789
A6: 1971q1 | B6: 123456789 | C6: 123456789 | D6: 123456789
A7: 1971q2 | B7: 123456789 | C7: 123456789 | D7: 123456789
A8: 1971q3 | B8: 123456789 | C8: 123456789 | D8: 123456789
A9: 1971q4 | B9: 123456789 | C9: 123456789 | D9: 123456789
A10: 1972q1 | B10: 123456789 | C10: 123456789 | D10: 123456789
A11: 1972q2 | B11: 123456789 | C11: 123456789 | D11: 123456789
A12: 1972q3 | B12: 123456789 | C12: 123456789 | D12: 123456789
A13: 1972q4 | B13: 123456789 | C13: 123456789 | D13: 123456789
... A226: 2026q1 | B226: 65.22 | C226: 123456789 | D226: 123456789

Sheet pmi_employment
B1: UK | C1: US | D1: EA
A2: 1970q1 | B2: 123456789 | C2: 123456789 | D2: 123456789
A3: 1970q2 | B3: 123456789 | C3: 123456789 | D3: 123456789
A4: 1970q3 | B4: 123456789 | C4: 123456789 | D4: 123456789
A5: 1970q4 | B5: 123456789 | C5: 123456789 | D5: 123456789
A6: 1971q1 | B6: 123456789 | C6: 123456789 | D6: 123456789
A7: 1971q2 | B7: 123456789 | C7: 123456789 | D7: 123456789
A8: 1971q3 | B8: 123456789 | C8: 123456789 | D8: 123456789
A9: 1971q4 | B9: 123456789 | C9: 123456789 | D9: 123456789
A10: 1972q1 | B10: 123456789 | C10: 123456789 | D10: 123456789
A11: 1972q2 | B11: 123456789 | C11: 123456789 | D11: 123456789
A12: 1972q3 | B12: 123456789 | C12: 123456789 | D12: 123456789
A13: 1972q4 | B13: 123456789 | C13: 123456789 | D13: 123456789
... A226: 2026q1 | B226: 68.528528 | C226: 123456789 | D226: 123456789

Sheet labour
B1: UK | C1: US | D1: EA
A2: 1970q1 | B2: 123456789 | C2: 123456789 | D2: 123456789
A3: 1970q2 | B3: 123456789 | C3: 123456789 | D3: 123456789
A4: 1970q3 | B4: 123456789 | C4: 123456789 | D4: 123456789
A5: 1970q4 | B5: 123456789 | C5: 123456789 | D5: 123456789
A6: 1971q1 | B6: 123456789 | C6: 123456789 | D6: 123456789
A7: 1971q2 | B7: 123456789 | C7: 123456789 | D7: 123456789
A8: 1971q3 | B8: 123456789 | C8: 123456789 | D8: 123456789
A9: 1971q4 | B9: 123456789 | C9: 123456789 | D9: 123456789
A10: 1972q1 | B10: 123456789 | C10: 123456789 | D10: 123456789
A11: 1972q2 | B11: 123456789 | C11: 123456789 | D11: 123456789
A12: 1972q3 | B12: 123456789 | C12: 123456789 | D12: 123456789
A13: 1972q4 | B13: 123456789 | C13: 123456789 | D13: 123456789
... A226: 2026q1 | B226: 46.376463 | C226: 123456789 | D226: 123456789

Sheet spliced_house_appr_growth
B1: House_price | C1: Housing approvals
A2: 1970q1 | B2: =house_price_growth!B2 -> 0.1497 | D2: =$J$22+B2*$J$23 -> 30940.521
A3: 1970q2 | B3: =house_price_growth!B3 -> -3.1935 | D3: =$J$22+B3*$J$23 -> 30561.586
A4: 1970q3 | B4: =house_price_growth!B4 -> 0.6825 | D4: =$J$22+B4*$J$23 -> 31000.911
A5: 1970q4 | B5: =house_price_growth!B5 -> -2.3023 | D5: =$J$22+B5*$J$23 -> 30662.599
A6: 1971q1 | B6: =house_price_growth!B6 -> -0.8242 | D6: =$J$22+B6*$J$23 -> 30830.134 | I6: SUMMARY OUTPUT
A7: 1971q2 | B7: =house_price_growth!B7 -> 0.7281 | D7: =$J$22+B7*$J$23 -> 31006.079
A8: 1971q3 | B8: =house_price_growth!B8 -> 1.6004 | D8: =$J$22+B8*$J$23 -> 31104.95 | I8: Regression Statistics
A9: 1971q4 | B9: =house_price_growth!B9 -> 7.2469 | D9: =$J$22+B9*$J$23 -> 31744.952 | I9: Multiple R | J9: 0.065444656
A10: 1972q1 | B10: =house_price_growth!B10 -> 12.5296 | D10: =$J$22+B10*$J$23 -> 32343.719 | I10: R Square | J10: 0.0042830029
A11: 1972q2 | B11: =house_price_growth!B11 -> 22.093 | D11: =$J$22+B11*$J$23 -> 33427.681 | I11: Adjusted R Square | J11: -0.0050227634
A12: 1972q3 | B12: =house_price_growth!B12 -> 30.8904 | D12: =$J$22+B12*$J$23 -> 34424.821 | I12: Standard Error | J12: 12324.079
A13: 1972q4 | B13: =house_price_growth!B13 -> 33.2083 | D13: =$J$22+B13*$J$23 -> 34687.543 | I13: Observations | J13: 109
A14: 1973q1 | B14: =house_price_growth!B14 -> 40.0542 | D14: =$J$22+B14*$J$23 -> 35463.49
A15: 1973q2 | B15: =house_price_growth!B15 -> 32.385 | D15: =$J$22+B15*$J$23 -> 34594.226 | I15: ANOVA
A16: 1973q3 | B16: =house_price_growth!B16 -> 22.8971 | D16: =$J$22+B16*$J$23 -> 33518.821 | J16: df | K16: SS | L16: MS | M16: F | N16: Significance F
A17: 1973q4 | B17: =house_price_growth!B17 -> 13.7057 | D17: =$J$22+B17*$J$23 -> 32477.023 | I17: Regression | J17: 1 | K17: 69904507 | L17: 69904507 | M17: 0.46025258 | N17: 0.49897057
A18: 1974q1 | B18: =house_price_growth!B18 -> 0.8013 | D18: =$J$22+B18*$J$23 -> 31014.376 | I18: Residual | J18: 107 | K18: 1.6251473e+10 | L18: 1.5188292e+08
A19: 1974q2 | B19: =house_price_growth!B19 -> -6.0824 | D19: =$J$22+B19*$J$23 -> 30234.144 | I19: Total | J19: 108 | K19: 1.6321377e+10
A20: 1974q3 | B20: =house_price_growth!B20 -> -11.137 | D20: =$J$22+B20*$J$23 -> 29661.231
A21: 1974q4 | B21: =house_price_growth!B21 -> -11.7595 | D21: =$J$22+B21*$J$23 -> 29590.674 | J21: Coefficients | K21: Standard Error | L21: t Stat | M21: P-value | N21: Lower 95% | O21: Upper 95% | P21: Lower 95.0% | Q21: Upper 95.0%
A22: 1975q1 | B22: =house_price_growth!B22 -> -13.2102 | D22: =$J$22+B22*$J$23 -> 29426.245 | I22: Intercept | J22: 30923.553 | K22: 1311.8875 | L22: 23.571802 | M22: 3.6119914e-44 | N22: 28322.889 | O22: 33524.217 | P22: 28322.889 | Q22: 33524.217
A23: 1975q2 | B23: =house_price_growth!B23 -> -13.8772 | D23: =$J$22+B23*$J$23 -> 29350.644 | I23: X Variable 1 | J23: 113.34486 | K23: 167.07201 | L23: 0.67841918 | M23: 0.49897057 | N23: -217.85592 | O23: 444.54563 | P23: -217.85592 | Q23: 444.54563
A24: 1975q3 | B24: =house_price_growth!B24 -> -13.7387 | D24: =$J$22+B24*$J$23 -> 29366.342
A25: 1975q4 | B25: =house_price_growth!B25 -> -12.7939 | D25: =$J$22+B25*$J$23 -> 29473.43
A26: 1976q1 | B26: =house_price_growth!B26 -> -10.0465 | D26: =$J$22+B26*$J$23 -> 29784.834
A27: 1976q2 | B27: =house_price_growth!B27 -> -4.8136 | D27: =$J$22+B27*$J$23 -> 30377.956
A28: 1976q3 | B28: =house_price_growth!B28 -> -4.1456 | D28: =$J$22+B28*$J$23 -> 30453.67
A29: 1976q4 | B29: =house_price_growth!B29 -> -4.2324 | D29: =$J$22+B29*$J$23 -> 30443.832
A30: 1977q1 | B30: =house_price_growth!B30 -> -7.4621 | D30: =$J$22+B30*$J$23 -> 30077.762
A31: 1977q2 | B31: =house_price_growth!B31 -> -8.9742 | D31: =$J$22+B31*$J$23 -> 29906.373
A32: 1977q3 | B32: =house_price_growth!B32 -> -7.7491 | D32: =$J$22+B32*$J$23 -> 30045.232
A33: 1977q4 | B33: =house_price_growth!B33 -> -3.3426 | D33: =$J$22+B33*$J$23 -> 30544.686
A34: 1978q1 | B34: =house_price_growth!B34 -> 1.4342 | D34: =$J$22+B34*$J$23 -> 31086.112
A35: 1978q2 | B35: =house_price_growth!B35 -> 6.3121 | D35: =$J$22+B35*$J$23 -> 31638.997
... A112: 1997q3 | B112: =house_price_growth!B112 -> 8.3847 | D112: =$J$22+B112*$J$23 -> 31873.915
A113: 1997q4 | B113: =house_price_growth!B113 -> 6.0035 | C113: 10530 | D113: =C113 -> 10530
A114: 1998q1 | B114: =house_price_growth!B114 -> 7.4117 | C114: 10091 | D114: =C114 -> 10091
A115: 1998q2 | B115: =house_price_growth!B115 -> 10.7412 | C115: 10449 | D115: =C115 -> 10449
A116: 1998q3 | B116: =house_price_growth!B116 -> 10.4556 | C116: 10761 | D116: =C116 -> 10761
A117: 1998q4 | B117: =house_price_growth!B117 -> 10.4859 | C117: 10853 | D117: =C117 -> 10853
A118: 1999q1 | B118: =house_price_growth!B118 -> 8.3852 | C118: 12494 | D118: =C118 -> 12494
A119: 1999q2 | B119: =house_price_growth!B119 -> 7.285 | C119: 14387 | D119: =C119 -> 14387
A120: 1999q3 | B120: =house_price_growth!B120 -> 9.039 | C120: 15919 | D120: =C120 -> 15919
A121: 1999q4 | B121: =house_price_growth!B121 -> 12.7078 | C121: 15832 | D121: =C121 -> 15832
A122: 2000q1 | B122: =house_price_growth!B122 -> 15.0928 | C122: 14802 | D122: =C122 -> 14802
A123: 2000q2 | B123: =house_price_growth!B123 -> 16.6902 | C123: 14232 | D123: =C123 -> 14232
A124: 2000q3 | B124: =house_price_growth!B124 -> 12.2003 | C124: 13135 | D124: =C124 -> 13135
... A222: 2025q1 | B222: =house_price_growth!B222 -> 1.854 | C222: 47696 | D222: =C222 -> 47696
A223: 2025q2 | C223: 45897 | D223: =C223 -> 45897

Sheet qoqrgdp
