Workbook

Sheet read_me
A3: ctry | B3: sheet name | C3: description | D3: source | E3: time span | F3: note
A4: UK | B4: g4Infl | C4: CPIH ANNUAL RATE 00: ALL ITEMS 2015=100 | D4: ONS | E4: 1989m1:2025m8 | F4: https://www.ons.gov.uk/economy/inflationandpriceindices/timeseries/l55o/mm23
A5: UK | B5: avg12Infl | C5: Average inflation in the last 12 months (including the current) | D5: own computations | E5: 1989m12:2025m8 | F5: -
A6: UK | B6: infl1_m | C6: CPI expectations in next calendar year | D6: Consensus Economics | E6: 1989m10:2025m9 | F6: spliced series from 2004m1 (sheet spliced_infl1_m)
A7: UK | B7: Oil | C7: Crude Oil Prices: Brent - Europe | D7: FRED | E7: 1987m6:2025m9
A8: UK | B8: g12oil | C8: Crude Oil Prices Inflation: Brent - Europe | D8: FRED | E8: 1988m6:2025m9 | F8: percentage change from a year ago (dollars per barrel) https://fred.stlouisfed.org/series/DCOILBRENTEU
A9: UK | B9: g12cpicore_global | C9: Consumer price indices (CPIs, HICPs), COICOP 1999 - All items non-food non-energy | D9: OECD | E9: 1971m1:2025m8 | F9: freq: M | reference: G7 | methodology: National | measure: CPI | Unit: % per annum | expenditure: all items non-food non-energy | adjustment: neither seasonal nor calendar adj |transformation: growth rate over 1 y https://data-explorer.oecd.org/vis?pg=0&bp=true&snb=16&df[ds]=dsDisseminateFinalDMZ&df[id]=DSD_PRICES%40DF_PRICES_ALL&df[ag]=OECD.SDD.TPS&df[vs]=&pd=%2C&dq=G7.M.N.CPI.PA._TXCP01_NRG.N.GY&to[TIME_PERIOD]=false&vw=tb&lc=en
A10: UK | B10: vu tightness | C10: Ratio of vacancy over unemployment (labour market tightness) | D10: a-millennium-of-macroeconomic-data-for-the-uk | E10: 1971m2:2025m6 | F10: sheet M5. Administrative unemp 1881+ (ratio between colomn AB (spliced vacancy) and colomn K (LFS unemployment). The data end in 2016. they have been complemented with the following data (check vu_extra_data sheet) https://www.ons.gov.uk/employmentandlabourmarket/peoplenotinwork/unemployment/datasets/vacanciesandunemploymentvacs01 Notice that each datapoint refers to the MIDDLE month in a 3 month period
A11: UK | B11: delta1vu tightness | C11: Delta 12m of vu tightness | D11: own computations | E11: 1972m2:2025m6
A12: UK | B12: bond_spread | C12: Corporate bond spread | D12: a-millennium-of-macroeconomic-data-for-the-uk + own computations + countercyclical capital buffer.xslsx (BOE) | E12: 1970m1:2025m9 | F12: series is available also for early period. We use colomn D of sheet 7. Global corp. bond spreads fron countercyclical capita buffer.xlsx from 1997 m1 onward and before we spliced colomn AJ sheet M11. Mthly corp bond yields from a millenium of macro data (see spliced_corporate_spread). countercyclical capita buffer.xlsx are at the daily level. We calculate monthly series as the average daily value withing a month. Computations are in Codes--> Intermediate_codes other_series.do (stata file)
A13: UK | B13: ue | C13: Unemployment rate (aged 16 and over, seasonally adjusted): % | D13: ONS | E13: 1971m2:2025m6 | F13: https://www.ons.gov.uk/employmentandlabourmarket/peoplenotinwork/unemployment/timeseries/mgsx/lms
A14: UK | B14: g4cpi | C14: CPI ANNUAL RATE 00: ALL ITEMS 2015=100 | D14: ONS | E14: 1989m1:2025m8 | F14: https://www.ons.gov.uk/economy/inflationandpriceindices/timeseries/d7g7/mm23
A15: UK | B15: avgcpi | C15: Average cpi inflation in the last 12 months (including the current) | D15: own computations | E15: 1989m12:2025m8
A16: UK | B16: g4cpinoener | C16: CPI 12mth: Excluding energy (SP) 2015=100 | D16: ONS | E16: 1989m1:2025m8 | F16: https://www.ons.gov.uk/economy/inflationandpriceindices/timeseries/dko7/mm23
A17: UK | B17: avgcpinoener | C17: Average cpi inflation Excluding energy in the last 12 months (including the current) | D17: own computations | E17: 1989m12:2025m8
A18: UK | B18: import_deflator | C18: Total Trade (TT): WW: Imports: BOP: IDEF: SA | D18: ONS | E18: 1970m1:2025m7 | F18: For the period after 1997m1 we use the monthly data from https://www.ons.gov.uk/economy/nationalaccounts/balanceofpayments/timeseries/ctwk/mret (Giulia is cross-checking with stat department.). For the period pre 1997m1 we linearly interpolate the quarterly data from the following series: Imports of goods and services deflator:SA (https://www.ons.gov.uk/economy/grossdomesticproductgdp/timeseries/ybfz/ukea) Interpolation of the series is performed in stata (other_series,do). Note: we assign the quarterly value to the last quarter in the month. Aggregation of the monthly interpolated series and the monthly series is performed here in the sheet (import_defl_qm)
A19: UK | B19: yoy_growth_import_deflator | C19: y-o-y growth in import deflator | D19: own computations | E19: 1971m1:2025m7
A20: UK | B20: import_defl_FAME | C20: import deflator | D20: BOE (FAME) | E20: 1970m1:2025m7 | F20: from deflator_longerTS.xlsx Giulia's email 20/08 So the cool thing about what Carleton is proposing is that we can get a deflator from 1955, by dividing prices and volumes and interpolating which are quarterly and interpolating them to monthly. So we don’t have to estimate anything: This obtains the deflator by dividing imports in current prices (CP) over imports in volumes (CVM) Total Trade (TT): WW: Imports: BOP: CP: SA Total Trade (TT): WW: Imports: BOP: CVM: SA Deflator = CP/CVM Post-1997: we have monthly data Pre-1997, we have quarterly so do a fancy interpolation to get implied monthly estimates
A21: UK | B21: yoy_growth_import_defl_FAME | C21: y-o-y growth in import deflator FAME | D21: own computations | E21: 1971m1:2025m7
A22: UK | B22: vu_tight_hp_filter | C22: level of v/u tightness minus HP filtered level of v/u tightnes (one-side) | D22: this dataset + own calculations | E22: 1988m1:2025m3 | F22: available inside the folder intermediate_code "other_series_monthly.m | L22: series is available also for early period. We use colomn D of sheet 7. Global corp. bond spreads fron countercyclical capita buffer.xlsx from 1997 m1 onward and before we spliced colomn AJ sheet M11. Mthly corp bond yields from a millenium of macro data (see spliced_corporate_spread). countercyclical capita buffer.xlsx are at the daily level. We calculate monthly series as the average daily value withing a month. Computations are in Codes--> Intermediate_codes other_series.do (stata file)
A23: UK | B23: ugap_kalman_filter | C23: Unemployment gap (using unemployment rate derived with KF as natural rate of unemployemnt) | D23: own computations | E23: 1989m4:2025m3 | F23: available inside the folder intermediate_code "other_series_monthly.m
A24: UK | B24: ugap_hp_filter | C24: unemployment minus HP filtered unemployment (one-side) | D24: this dataset + own calculations | E24: 1988m1:2025m3 | F24: available inside the folder intermediate_code "other_series_monthly.m

Sheet FAME Persistence2
A1: 19 | B1: bond_spread
A2: Fame Links | B2: $A$5 | C2: A1:A685 | D2: famedate | E2: 46114.513 | F2: TRUE | G2: famedate | H2: 1970 | I2: 2026 | J2: 0 | K2: m | L2: FALSE | M2: TRUE | N2: FALSE
A3: Fame Links | B3: $I$5 | C3: A1:A8090 | D3: famedate | E3: 46114.513 | F3: TRUE | G3: famedate | H3: 1996 | I3: 2026 | J3: 0 | K3: b | L3: FALSE | M3: TRUE | N3: FALSE
A4: Fame Links | B4: $C$6 | C4: A1:A684 | E4: 46114.513 | F4: TRUE | G4: D7G7.m | H4: 1970 | I4: 2026 | J4: 0 | K4: m | L4: FALSE | M4: FALSE | N4: FALSE
A5: Fame Links | B5: $D$6 | C5: A1:A684 | E5: 46114.513 | F5: TRUE | G5: UKCCPHM1.M | H5: 1970 | I5: 2026 | J5: 0 | K5: m | L5: FALSE | M5: FALSE | N5: FALSE
A6: Fame Links | B6: $E$6 | C6: A1:A684 | E6: 46114.513 | F6: TRUE | G6: UKCCPHM2.M | H6: 1970 | I6: 2026 | J6: 0 | K6: m | L6: FALSE | M6: FALSE | N6: FALSE
A7: Fame Links | B7: $F$6 | C7: A1:A684 | E7: 46114.513 | F7: TRUE | G7: ap2y.m[t-1] | H7: 1970 | I7: 2026 | J7: 0 | K7: m | L7: FALSE | M7: FALSE | N7: FALSE
A8: Fame Links | B8: $G$6 | C8: A1:A684 | E8: 46114.513 | F8: TRUE | G8: mgsc_dp.m[t-1] | H8: 1970 | I8: 2026 | J8: 0 | K8: m | L8: FALSE | M8: FALSE | N8: FALSE
A9: Fame Links | B9: $J$6 | C9: A1:A8089 | E9: 46114.513 | F9: TRUE | G9: UR00_OAS.b | H9: 1996 | I9: 2026 | J9: 0 | K9: b | L9: FALSE | M9: FALSE | N9: FALSE
A10: Sheet2 | B10: $A$5 | C10: A1:A445 | D10: famedate | E10: 46114.508 | F10: TRUE | G10: famedate | H10: 1990 | I10: 2026 | J10: 0 | K10: m | L10: FALSE | M10: TRUE | N10: FALSE
A11: Sheet2 | B11: $B$5 | C11: A1:A445 | D11: bqat.m/bpic.m | E11: 46114.508 | F11: TRUE | G11: bqat.m/bpic.m | H11: 1990 | I11: 2026 | J11: 0 | K11: m | L11: FALSE | M11: TRUE | N11: FALSE
A12: Sheet2 | B12: $C$5 | C12: A1:A445 | D12: ikbi.m-bqat.m | E12: 46114.508 | F12: TRUE | G12: ikbi.m-bqat.m | H12: 1990 | I12: 2026 | J12: 0 | K12: m | L12: FALSE | M12: TRUE | N12: FALSE
A13: Sheet2 | B13: $D$5 | C13: A1:A445 | D13: ikbl.m-bpic.m | E13: 46114.508 | F13: TRUE | G13: ikbl.m-bpic.m | H13: 1990 | I13: 2026 | J13: 0 | K13: m | L13: FALSE | M13: TRUE | N13: FALSE
A14: Sheet2 | B14: $F$5 | C14: A1:A445 | D14: conv2ma(gsalspt.b/uss.b) | E14: 46114.508 | F14: TRUE | G14: conv2ma(gsalspt.b/uss.b) | H14: 1990 | I14: 2026 | J14: 0 | K14: m | L14: FALSE | M14: TRUE | N14: FALSE
A15: Imp_def_fameGM | B15: $A$5 | C15: A1:A685 | D15: famedate | E15: 46114.51 | F15: TRUE | G15: famedate | H15: 1970 | I15: 2026 | J15: 0 | K15: m | L15: FALSE | M15: TRUE | N15: FALSE
A16: Imp_def_fameGM | B16: $B$5 | C16: A1:A685 | D16: overlay(ikbi.m/ikbl.m*100,convgen(ikbi.q/ikbl.q*100,monthly,averaged,linear,yes)) | E16: 46114.51 | F16: TRUE | G16: overlay(ikbi.m/ikbl.m*100,convgen(ikbi.q/ikbl.q*100,monthly,averaged,linear,yes)) | H16: 1970 | I16: 2026 | J16: 0 | K16: m | L16: FALSE | M16: TRUE | N16: FALSE
A17: import_defl_FAME | B17: $B$5 | D17: #N/A | E17: 0
A18: import_defl_FAME | B18: $A$5 | D18: #N/A | E18: 0
A19: Sheet1 | B19: $A$5 | D19: #N/A | E19: 0 | F19: TRUE | G19: 1970m3 | I19: 1970m1 | J19: 0 | K19: 1970m2 | L19: FALSE | M19: TRUE | N19: FALSE
A20: Sheet1 | B20: $B$5 | D20: #N/A | E20: 0 | F20: TRUE | G20: overlay(ikbi.m/ikbl.m*100,convgen(ikbi.q/ikbl.q*100,monthly,averaged,linear,yes)) | I20: 1970m1 | J20: 0 | K20: 1970m2 | L20: FALSE | M20: TRUE | N20: FALSE

Sheet Fame Links
A1: 1970 | B1: 1970m1 | I1: 1996
A2: 2026 | B2: 2026m1 | I2: 2026 | M2: Note | N2: the latest ONS release is as Jun-Sep, and so on FAME its saved as the August number, but we treat it as September as it has september data. its unemployment in the 3 months to september and the t-1 is just to adjust for this
A3: m | B3: m | I3: b
A4: famedate | B4: 25599 | C4: CPI | D4: Consensus | E4: Consensus | F4: Vacancies | G4: Unemployment | I4: famedate
A5: =[1]!FAMEData($A$4, $A$1, $A$2, 0,$A$3,"Down","Heading","Normal") -> famedate | B5: 25627 | C5: D7G7.m | D5: UKCCPHM1.M | E5: UKCCPHM2.M | F5: ap2y.m[t-1] | G5: mgsc_dp.m[t-1] | I5: =[1]!FAMEData($I$4, $I$1, $I$2, 0,$I$3,"Down","Heading","Normal") -> famedate | J5: UR00_OAS.b
A6: 25599 | B6: 25658 | C6: =[1]!FAMEData($C$5, $A$1,$A$2, 0,$A$3, "Down", "No Heading", "Normal") | D6: =[1]!FAMEData(D5, $A$1, $A$2, 0, $A$3, "Down", "No Heading", "Normal") | E6: =[1]!FAMEData(E5, $A$1, $A$2, 0, $A$3, "Down", "No Heading", "Normal") | F6: =[1]!FAMEData(F5, $A$1, $A$2, 0, $A$3, "Down", "No Heading", "Normal") | G6: =[1]!FAMEData(G5, $A$1, $A$2, 0, $A$3, "Down", "No Heading", "Normal") | I6: 35065 | J6: =[1]!FAMEData(J5, $I$1, $I$2, 0, $I$3, "Down", "No Heading", "Normal")
A7: 25627 | B7: 25688 | I7: 35066
A8: 25658 | B8: 25719 | I8: 35067
A9: 25688 | B9: 25749 | I9: 35068
A10: 25719 | B10: 25780 | I10: 35069
A11: 25749 | B11: 25811 | I11: 35072
A12: 25780 | B12: 25841 | I12: 35073
A13: 25811 | B13: 25872 | I13: 35074
A14: 25841 | B14: 25902 | I14: 35075
A15: 25872 | B15: 25933 | I15: 35076
A16: 25902 | B16: 25964 | I16: 35079
A17: 25933 | B17: 25992 | I17: 35080
A18: 25964 | B18: 26023 | I18: 35081
A19: 25992 | B19: 26053 | I19: 35082
A20: 26023 | B20: 26084 | G20: 980 | I20: 35083
A21: 26053 | B21: 26114 | G21: 998 | I21: 35086
A22: 26084 | B22: 26145 | G22: 1023 | I22: 35087
A23: 26114 | B23: 26176 | G23: 1045 | I23: 35088
A24: 26145 | B24: 26206 | G24: 1062 | I24: 35089
A25: 26176 | B25: 26237 | G25: 1068 | I25: 35090
A26: 26206 | B26: 26267 | G26: 1076 | I26: 35093
A27: 26237 | B27: 26298 | G27: 1090 | I27: 35094
A28: 26267 | B28: 26329 | G28: 1113 | I28: 35095
A29: 26298 | B29: 26358 | G29: 1133 | I29: 35096
A30: 26329 | B30: 26389 | G30: 1143 | I30: 35097
A31: 26358 | B31: 26419 | G31: 1149 | I31: 35100
... A233: 32508 | B233: 32567 | G233: 2293 | I233: 35382
A234: 32539 | B234: 32598 | C234: 4.9 | G234: 2253 | I234: 35383
A235: 32567 | B235: 32628 | C235: 5 | G235: 2213 | I235: 35384
A236: 32598 | B236: 32659 | C236: 5 | G236: 2179 | I236: 35387
A237: 32628 | B237: 32689 | C237: 5.3 | G237: 2140 | I237: 35388
A238: 32659 | B238: 32720 | C238: 5.3 | G238: 2106 | I238: 35389
A239: 32689 | B239: 32751 | C239: 5.2 | G239: 2083 | I239: 35390
A240: 32720 | B240: 32781 | C240: 5.2 | G240: 2071 | I240: 35391
A241: 32751 | B241: 32812 | C241: 5 | G241: 2057 | I241: 35394
A242: 32781 | B242: 32842 | C242: 5.2 | G242: 2045 | I242: 35395
A243: 32812 | B243: 32873 | C243: 5.5 | G243: 2034 | I243: 35396
A244: 32842 | B244: 32904 | C244: 5.5 | G244: 2027 | I244: 35397
A245: 32873 | B245: 32932 | C245: 5.5 | G245: 2021 | I245: 35398
... A266: 33511 | B266: 33572 | C266: 7.1 | G266: 2624 | I266: 35429
A267: 33542 | B267: 33603 | C267: 6.8 | G267: 2652 | I267: 35430 | J267: 47
A268: 33572 | B268: 33634 | C268: 7.1 | G268: 2675 | I268: 35431 | J268: 47
A269: 33603 | B269: 33663 | C269: 7.2 | G269: 2697 | I269: 35432 | J269: 44
A270: 33634 | B270: 33694 | C270: 7 | G270: 2714 | I270: 35433 | J270: 46
A271: 33663 | B271: 33724 | C271: 6.9 | G271: 2735 | I271: 35436 | J271: 46
A272: 33694 | B272: 33755 | C272: 7.1 | G272: 2762 | I272: 35437 | J272: 46
A273: 33724 | B273: 33785 | C273: 4.7 | G273: 2782 | I273: 35438 | J273: 46
A274: 33755 | B274: 33816 | C274: 4.3 | G274: 2795.7384 | I274: 35439 | J274: 48
A275: 33785 | B275: 33847 | C275: 3.8 | G275: 2777.3677 | I275: 35440 | J275: 47
A276: 33816 | B276: 33877 | C276: 3.6 | G276: 2802.6249 | I276: 35443 | J276: 47
A277: 33847 | B277: 33908 | C277: 3 | G277: 2816.1258 | I277: 35444 | J277: 46
A278: 33877 | B278: 33938 | C278: 3 | G278: 2814.5248 | I278: 35445 | J278: 46
... A382: 37042 | B382: 37103 | C382: 1.7 | G382: 1430.5672 | I382: 35591 | J382: 47
A383: 37072 | B383: 37134 | C383: 1.7 | F383: 680 | G383: 1467.6873 | I383: 35592 | J383: 47
A384: 37103 | B384: 37164 | C384: 1.4 | F384: 674 | G384: 1472.0744 | I384: 35593 | J384: 48
A385: 37134 | B385: 37195 | C385: 1.8 | F385: 663 | G385: 1482.7334 | I385: 35594 | J385: 47
A386: 37164 | B386: 37225 | C386: 1.3 | F386: 663 | G386: 1487.3505 | I386: 35597 | J386: 47
A387: 37195 | B387: 37256 | C387: 1.2 | F387: 639 | G387: 1487.483 | I387: 35598 | J387: 45
A388: 37225 | B388: 37287 | C388: 0.8 | F388: 626 | G388: 1495.2676 | I388: 35599 | J388: 44
A389: 37256 | B389: 37315 | C389: 1.1 | F389: 601 | G389: 1519.6458 | I389: 35600 | J389: 44
A390: 37287 | B390: 37346 | C390: 1.6 | F390: 606 | G390: 1518.1791 | I390: 35601 | J390: 46
A391: 37315 | B391: 37376 | C391: 1.5 | F391: 616 | G391: 1507.6446 | I391: 35604 | J391: 44
A392: 37346 | B392: 37407 | C392: 1.5 | F392: 619 | G392: 1515.0891 | I392: 35605 | J392: 45
A393: 37376 | B393: 37437 | C393: 1.4 | F393: 619 | G393: 1522.3335 | I393: 35606 | J393: 45
A394: 37407 | B394: 37468 | C394: 0.8 | F394: 613 | G394: 1542.3181 | I394: 35607 | J394: 45
... A413: 37986 | B413: 38046 | C413: 1.3 | F413: 614 | G413: 1457.174 | I413: 35634 | J413: 47
A414: 38017 | B414: 38077 | C414: 1.4 | D414: 1.536 | E414: 1.777 | F414: 613 | G414: 1441.5869 | I414: 35635 | J414: 47
A415: 38046 | B415: 38107 | C415: 1.3 | D415: 1.576 | E415: 1.767 | F415: 617 | G415: 1436.1238 | I415: 35636 | J415: 48
A416: 38077 | B416: 38138 | C416: 1.1 | D416: 1.568 | E416: 1.738 | F416: 624 | G416: 1434.1465 | I416: 35639 | J416: 47
A417: 38107 | B417: 38168 | C417: 1.1 | D417: 1.518 | E417: 1.753 | F417: 630 | G417: 1437.4195 | I417: 35640 | J417: 48
A418: 38138 | B418: 38199 | C418: 1.5 | D418: 1.493 | E418: 1.768 | F418: 637 | G418: 1434.616 | I418: 35641 | J418: 49
A419: 38168 | B419: 38230 | C419: 1.6 | D419: 1.485 | E419: 1.78 | F419: 641 | G419: 1437.1087 | I419: 35642 | J419: 48
A420: 38199 | B420: 38260 | C420: 1.4 | D420: 1.499 | E420: 1.796 | F420: 652 | G420: 1423.0718 | I420: 35643 | J420: 47
A421: 38230 | B421: 38291 | C421: 1.3 | D421: 1.466 | E421: 1.78 | F421: 654 | G421: 1404.8597 | I421: 35646 | J421: 48
A422: 38260 | B422: 38321 | C422: 1.1 | D422: 1.457 | E422: 1.834 | F422: 654 | G422: 1401.3366 | I422: 35647 | J422: 48
A423: 38291 | B423: 38352 | C423: 1.2 | D423: 1.434 | E423: 1.768 | F423: 655 | G423: 1396.6358 | I423: 35648 | J423: 49
A424: 38321 | B424: 38383 | C424: 1.5 | D424: 1.354 | E424: 1.677 | F424: 658 | G424: 1406.8624 | I424: 35649 | J424: 50
A425: 38352 | B425: 38411 | C425: 1.7 | D425: 1.337 | E425: 1.672 | F425: 662 | G425: 1423.2374 | I425: 35650 | J425: 47
... A678: 46053 | B678: 46112 | C678: 3 | D678: 2.4228 | E678: 2.2294 | F678: 730 | G678: 1868.7158 | I678: 36005 | J678: 72
A679: 46081 | B679: 46142 | C679: 3 | D679: 2.4508 | E679: 2.225 | F679: 721 | I679: 36006 | J679: 68
A680: 46112 | B680: 46173 | D680: 2.5965 | E680: 2.2645 | I680: 36007 | J680: 72
A681: 46142 | B681: 46203 | I681: 36010 | J681: 71
A682: 46173 | B682: 46234 | I682: 36011 | J682: 70
A683: 46203 | B683: 46265 | I683: 36012 | J683: 70
A684: 46234 | B684: 46295 | I684: 36013 | J684: 71
A685: 46265 | B685: 46326 | I685: 36014 | J685: 71
A686: 46295 | B686: 46356 | I686: 36017 | J686: 71
A687: 46326 | B687: 46387 | I687: 36018 | J687: 71
A688: 46356 | I688: 36019 | J688: 72
A689: 46387 | I689: 36020 | J689: 70
I690: 36021 | J690: 72
I691: 36024 | J691: 71
I692: 36025 | J692: 72
I693: 36026 | J693: 73
I694: 36027 | J694: 77
...

Sheet Sheet2
A1: 1990
A2: 2026
A3: m
A4: famedate | B4: bqat.m/bpic.m | C4: ikbi.m-bqat.m | D4: ikbl.m-bpic.m | F4: conv2ma(gsalspt.b/uss.b)
A5: =[1]!FAMEData($A$4, $A$1, $A$2, 0,$A$3,"Down","Heading","Normal") -> famedate | B5: =[1]!FAMEData($B$4, $A$1, $A$2, 0,$A$3,"Down","Heading","Normal") -> bqat.m/bpic.m | C5: =[1]!FAMEData($C$4, $A$1, $A$2, 0,$A$3,"Down","Heading","Normal") -> ikbi.m-bqat.m | D5: =[1]!FAMEData($D$4, $A$1, $A$2, 0,$A$3,"Down","Heading","Normal") -> ikbl.m-bpic.m | F5: =[1]!FAMEData($F$4, $A$1, $A$2, 0,$A$3,"Down","Heading","Normal") -> conv2ma(gsalspt.b/uss.b)
A6: 32904 | B6: 0.3080855 | E6: =C6/D6 -> #DIV/0! | F6: 123.64496
A7: 32932 | B7: 0.30942133 | E7: =C7/D7 -> #DIV/0! | F7: 119.3997
A8: 32963 | B8: 0.30205415 | E8: =C8/D8 -> #DIV/0! | F8: 127.37489
A9: 32993 | B9: 0.28089888 | E9: =C9/D9 -> #DIV/0! | F9: 129.43937
A10: 33024 | B10: 0.27317956 | E10: =C10/D10 -> #DIV/0! | F10: 127.65673
A11: 33054 | B11: 0.27295163 | E11: =C11/D11 -> #DIV/0! | F11: 121.3704
A12: 33085 | B12: 0.26933702 | E12: =C12/D12 -> #DIV/0! | F12: 110.44262
A13: 33116 | B13: 0.28571429 | E13: =C13/D13 -> #DIV/0! | F13: 100.53098
A14: 33146 | B14: 0.32931354 | E14: =C14/D14 -> #DIV/0! | F14: 100.45201
A15: 33177 | B15: 0.37881508 | E15: =C15/D15 -> #DIV/0! | F15: 96.276237
A16: 33207 | B16: 0.3639407 | E16: =C16/D16 -> #DIV/0! | F16: 94.085349
A17: 33238 | B17: 0.34917556 | E17: =C17/D17 -> #DIV/0! | F17: 95.657377
... A29: 33603 | B29: 0.26077098 | E29: =C29/D29 -> #DIV/0! | F29: 102.33339
A30: 33634 | B30: 0.25940594 | C30: 11375 | E30: =C30/D30 -> #DIV/0! | F30: 105.30599
A31: 33663 | B31: 0.25418363 | C31: 11864 | E31: =C31/D31 -> #DIV/0! | F31: 109.16726
A32: 33694 | B32: 0.2641604 | C32: 11665 | E32: =C32/D32 -> #DIV/0! | F32: 111.15181
A33: 33724 | B33: 0.26225279 | C33: 12101 | E33: =C33/D33 -> #DIV/0! | F33: 107.74131
A34: 33755 | B34: 0.27118644 | C34: 12126 | E34: =C34/D34 -> #DIV/0! | F34: 103.28261
A35: 33785 | B35: 0.28658824 | C35: 11827 | E35: =C35/D35 -> #DIV/0! | F35: 100.86595
A36: 33816 | B36: 0.28594771 | C36: 11870 | E36: =C36/D36 -> #DIV/0! | F36: 93.476428
A37: 33847 | B37: 0.27167113 | C37: 12003 | E37: =C37/D37 -> #DIV/0! | F37: 89.514852
A38: 33877 | B38: 0.26490669 | C38: 11751 | E38: =C38/D38 -> #DIV/0! | F38: 95.148045
A39: 33908 | B39: 0.27842004 | C39: 12463 | E39: =C39/D39 -> #DIV/0! | F39: 107.01414
A40: 33938 | B40: 0.2839784 | C40: 12787 | E40: =C40/D40 -> #DIV/0! | F40: 118.81568
A41: 33969 | B41: 0.29509853 | C41: 13222 | E41: =C41/D41 -> #DIV/0! | F41: 117.76362
... A77: 35064 | B77: 0.30763984 | C77: 17491 | E77: =C77/D77 -> #DIV/0! | F77: 147.77629
A78: 35095 | B78: 0.31988636 | E78: =C78/D78 -> #DIV/0! | F78: 147.46285
A79: 35124 | B79: 0.31629756 | E79: =C79/D79 -> #DIV/0! | F79: 149.17095
A80: 35155 | B80: 0.33391204 | E80: =C80/D80 -> #DIV/0! | F80: 151.11239
A81: 35185 | B81: 0.34642857 | E81: =C81/D81 -> #DIV/0! | F81: 162.36849
A82: 35216 | B82: 0.32520776 | E82: =C82/D82 -> #DIV/0! | F82: 167.37782
A83: 35246 | B83: 0.3126935 | E83: =C83/D83 -> #DIV/0! | F83: 152.40667
A84: 35277 | B84: 0.32397408 | E84: =C84/D84 -> #DIV/0! | F84: 147.56072
A85: 35308 | B85: 0.33178923 | E85: =C85/D85 -> #DIV/0! | F85: 145.96132
A86: 35338 | B86: 0.35290664 | E86: =C86/D86 -> #DIV/0! | F86: 141.1382
A87: 35369 | B87: 0.37200223 | E87: =C87/D87 -> #DIV/0! | F87: 131.16548
A88: 35399 | B88: 0.34613361 | E88: =C88/D88 -> #DIV/0! | F88: 121.69215
A89: 35430 | B89: 0.35099715 | E89: =C89/D89 -> #DIV/0! | F89: 121.03971
A90: 35461 | B90: 0.19567151 | C90: 18943 | D90: 26716 | E90: =C90/D90 -> 0.70905076 | F90: 123.06931
A91: 35489 | B91: 0.1910847 | C91: 18765 | D91: 26544 | E91: =C91/D91 -> 0.70693942 | F91: 127.60447
A92: 35520 | B92: 0.18099688 | C92: 19347 | D92: 27654 | E92: =C92/D92 -> 0.69960946 | F92: 134.30704
A93: 35550 | B93: 0.16934903 | C93: 19721 | D93: 27516 | E93: =C93/D93 -> 0.71671028 | F93: 135.55016
A94: 35581 | B94: 0.16751269 | C94: 19375 | D94: 27656 | E94: =C94/D94 -> 0.7005713 | F94: 135.51466
A95: 35611 | B95: 0.16188738 | C95: 19753 | D95: 28410 | E95: =C95/D95 -> 0.69528335 | F95: 125.3633
A96: 35642 | B96: 0.16122121 | C96: 19758 | D96: 28261 | E96: =C96/D96 -> 0.699126 | F96: 119.82929
A97: 35673 | B97: 0.1651747 | C97: 18907 | D97: 27404 | E97: =C97/D97 -> 0.68993578 | F97: 129.02813
A98: 35703 | B98: 0.16781214 | C98: 19263 | D98: 27845 | E98: =C98/D98 -> 0.69179386 | F98: 128.15262
A99: 35734 | B99: 0.17784091 | C99: 19647 | D99: 28347 | E99: =C99/D99 -> 0.69308922 | F99: 124.08104
A100: 35764 | B100: 0.17541136 | C100: 19475 | D100: 28626 | E100: =C100/D100 -> 0.68032558 | F100: 120.47149
A101: 35795 | B101: 0.1648113 | C101: 20139 | D101: 29264 | E101: =C101/D101 -> 0.68818343 | F101: 119.98542
... A438: 46053 | B438: 0.72721519 | C438: 73990 | D438: 73149 | E438: =C438/D438 -> 1.0114971 | F438: 281.17105
A439: 46081 | E439: =C439/D439 -> #DIV/0! | F439: 281.53296
A440: 46112 | E440: =C440/D440 -> #DIV/0! | F440: 294.55219
A441: 46142 | E441: =C441/D441 -> #DIV/0!
A442: 46173 | E442: =C442/D442 -> #DIV/0!
A443: 46203 | E443: =C443/D443 -> #DIV/0!
A444: 46234 | E444: =C444/D444 -> #DIV/0!
A445: 46265 | E445: =C445/D445 -> #DIV/0!
A446: 46295 | E446: =C446/D446 -> #DIV/0!
A447: 46326 | E447: =C447/D447 -> #DIV/0!
A448: 46356 | E448: =C448/D448 -> #DIV/0!
A449: 46387 | E449: =C449/D449 -> #DIV/0!

Sheet g4Infl
B1: UK | C1: US | D1: EA
A2: 1970m1 | B2: 123456789 | C2: 123456789 | D2: 123456789
A3: 1970m2 | B3: 123456789 | C3: 123456789 | D3: 123456789
A4: 1970m3 | B4: 123456789 | C4: 123456789 | D4: 123456789
A5: 1970m4 | B5: 123456789 | C5: 123456789 | D5: 123456789
A6: 1970m5 | B6: 123456789 | C6: 123456789 | D6: 123456789
A7: 1970m6 | B7: 123456789 | C7: 123456789 | D7: 123456789
A8: 1970m7 | B8: 123456789 | C8: 123456789 | D8: 123456789
A9: 1970m8 | B9: 123456789 | C9: 123456789 | D9: 123456789
A10: 1970m9 | B10: 123456789 | C10: 123456789 | D10: 123456789
A11: 1970m10 | B11: 123456789 | C11: 123456789 | D11: 123456789
A12: 1970m11 | B12: 123456789 | C12: 123456789 | D12: 123456789
A13: 1970m12 | B13: 123456789 | C13: 123456789 | D13: 123456789
... A617: 2021m4 | B617: 1.6 | C617: 123456789 | D617: 123456789
A618: 2021m5 | B618: 2.1 | C618: 123456789 | D618: 123456789 | R618: =428-92 -> 336
A619: 2021m6 | B619: 2.4 | C619: 123456789 | D619: 123456789
A620: 2021m7 | B620: 2.1 | C620: 123456789 | D620: 123456789
A621: 2021m8 | B621: 3 | C621: 123456789 | D621: 123456789
A622: 2021m9 | B622: 2.9 | C622: 123456789 | D622: 123456789
A623: 2021m10 | B623: 3.8 | C623: 123456789 | D623: 123456789
A624: 2021m11 | B624: 4.6 | C624: 123456789 | D624: 123456789
A625: 2021m12 | B625: 4.8 | C625: 123456789 | D625: 123456789
A626: 2022m1 | B626: 4.9 | C626: 123456789 | D626: 123456789
A627: 2022m2 | B627: 5.5 | C627: 123456789 | D627: 123456789
A628: 2022m3 | B628: 6.2 | C628: 123456789 | D628: 123456789
A629: 2022m4 | B629: 7.8 | C629: 123456789 | D629: 123456789
A630: 2022m5 | B630: 7.9 | C630: 123456789 | D630: 123456789
... A654: 2024m5 | B654: 2.8 | C654: 123456789 | D654: 123456789
A655: 2024m6 | B655: 2.8 | C655: 123456789 | D655: 123456789 | R655: 4+R61828-92
A656: 2024m7 | B656: 3.1 | C656: 123456789 | D656: 123456789
A657: 2024m8 | B657: 3.1 | C657: 123456789 | D657: 123456789
A658: 2024m9 | B658: 2.6 | C658: 123456789 | D658: 123456789 | P658: 92
A659: 2024m10 | B659: 3.2 | C659: 123456789 | D659: 123456789
A660: 2024m11 | B660: 3.5 | C660: 123456789 | D660: 123456789
A661: 2024m12 | B661: 3.5 | C661: 123456789 | D661: 123456789
A662: 2025m1 | B662: 3.9 | C662: 123456789 | D662: 123456789
A663: 2025m2 | B663: 3.7 | C663: 123456789 | D663: 123456789
A664: 2025m3 | B664: 3.4 | C664: 123456789 | D664: 123456789
A665: 2025m4 | B665: 4.1 | C665: 123456789 | D665: 123456789
A666: 2025m5 | B666: 4 | C666: 123456789 | D666: 123456789
A667: 2025m6 | B667: 4.1 | C667: 123456789 | D667: 123456789
A668: 2025m7 | B668: 4.2 | C668: 123456789 | D668: 123456789
A669: 2025m8 | B669: 4.1 | C669: 123456789 | D669: 123456789
A670: 2025m9 | B670: 4.1 | C670: 123456789 | D670: 123456789
... A672: 2025m11 | B672: 3.5 | C672: 123456789 | D672: 123456789

Sheet g4cpi
B1: UK | C1: US | D1: EA
A2: 1970m1 | B2: 123456789 | C2: 123456789 | D2: 123456789
A3: 1970m2 | B3: 123456789 | C3: 123456789 | D3: 123456789
A4: 1970m3 | B4: 123456789 | C4: 123456789 | D4: 123456789
A5: 1970m4 | B5: 123456789 | C5: 123456789 | D5: 123456789
A6: 1970m5 | B6: 123456789 | C6: 123456789 | D6: 123456789
A7: 1970m6 | B7: 123456789 | C7: 123456789 | D7: 123456789
A8: 1970m7 | B8: 123456789 | C8: 123456789 | D8: 123456789
A9: 1970m8 | B9: 123456789 | C9: 123456789 | D9: 123456789
A10: 1970m9 | B10: 123456789 | C10: 123456789 | D10: 123456789
A11: 1970m10 | B11: 123456789 | C11: 123456789 | D11: 123456789
A12: 1970m11 | B12: 123456789 | C12: 123456789 | D12: 123456789
A13: 1970m12 | B13: 123456789 | C13: 123456789 | D13: 123456789
... A229: 1988m12 | B229: 123456789 | C229: 123456789 | D229: 123456789
A230: 1989m1 | B230: ='Fame Links'!C234 -> 4.9 | C230: 123456789 | D230: 123456789
A231: 1989m2 | B231: ='Fame Links'!C235 -> 5 | C231: 123456789 | D231: 123456789
A232: 1989m3 | B232: ='Fame Links'!C236 -> 5 | C232: 123456789 | D232: 123456789
A233: 1989m4 | B233: ='Fame Links'!C237 -> 5.3 | C233: 123456789 | D233: 123456789
A234: 1989m5 | B234: ='Fame Links'!C238 -> 5.3 | C234: 123456789 | D234: 123456789
A235: 1989m6 | B235: ='Fame Links'!C239 -> 5.2 | C235: 123456789 | D235: 123456789
A236: 1989m7 | B236: ='Fame Links'!C240 -> 5.2 | C236: 123456789 | D236: 123456789
A237: 1989m8 | B237: ='Fame Links'!C241 -> 5 | C237: 123456789 | D237: 123456789
A238: 1989m9 | B238: ='Fame Links'!C242 -> 5.2 | C238: 123456789 | D238: 123456789
A239: 1989m10 | B239: ='Fame Links'!C243 -> 5.5 | C239: 123456789 | D239: 123456789
A240: 1989m11 | B240: ='Fame Links'!C244 -> 5.5 | C240: 123456789 | D240: 123456789
A241: 1989m12 | B241: ='Fame Links'!C245 -> 5.5 | C241: 123456789 | D241: 123456789
... A670: 2025m9 | B670: ='Fame Links'!C674 -> 3.8 | C670: 123456789 | D670: 123456789
A671: 2025m10 | B671: 3.6 | C671: 123456789 | D671: 123456789
A672: 2025m11 | B672: 3.2 | C672: 123456789 | D672: 123456789
A673: 2025m12 | B673: 3.4 | C673: 123456789 | D673: 123456789
A674: 2026m1 | B674: 3 | C674: 123456789 | D674: 123456789
A675: 2026m2 | B675: 3 | C675: 123456789 | D675: 123456789

Sheet avgcpi
B1: UK | C1: US | D1: EA
A2: 1970m1 | B2: 123456789 | C2: 123456789 | D2: 123456789
A3: 1970m2 | B3: 123456789 | C3: 123456789 | D3: 123456789
A4: 1970m3 | B4: 123456789 | C4: 123456789 | D4: 123456789
A5: 1970m4 | B5: 123456789 | C5: 123456789 | D5: 123456789
A6: 1970m5 | B6: 123456789 | C6: 123456789 | D6: 123456789
A7: 1970m6 | B7: 123456789 | C7: 123456789 | D7: 123456789
A8: 1970m7 | B8: 123456789 | C8: 123456789 | D8: 123456789
A9: 1970m8 | B9: 123456789 | C9: 123456789 | D9: 123456789
A10: 1970m9 | B10: 123456789 | C10: 123456789 | D10: 123456789
A11: 1970m10 | B11: 123456789 | C11: 123456789 | D11: 123456789
A12: 1970m11 | B12: 123456789 | C12: 123456789 | D12: 123456789
A13: 1970m12 | B13: 123456789 | C13: 123456789 | D13: 123456789
... A240: 1989m11 | B240: 123456789 | C240: 123456789 | D240: 123456789
A241: 1989m12 | B241: =AVERAGE(g4cpi!B230:B241) -> 5.2166667 | C241: 123456789 | D241: 123456789
A242: 1990m1 | B242: =AVERAGE(g4cpi!B231:B242) -> 5.2833333 | C242: 123456789 | D242: 123456789
A243: 1990m2 | B243: =AVERAGE(g4cpi!B232:B243) -> 5.3583333 | C243: 123456789 | D243: 123456789
A244: 1990m3 | B244: =AVERAGE(g4cpi!B233:B244) -> 5.4416667 | C244: 123456789 | D244: 123456789
A245: 1990m4 | B245: =AVERAGE(g4cpi!B234:B245) -> 5.5333333 | C245: 123456789 | D245: 123456789
A246: 1990m5 | B246: =AVERAGE(g4cpi!B235:B246) -> 5.6583333 | C246: 123456789 | D246: 123456789
A247: 1990m6 | B247: =AVERAGE(g4cpi!B236:B247) -> 5.8 | C247: 123456789 | D247: 123456789
A248: 1990m7 | B248: =AVERAGE(g4cpi!B237:B248) -> 5.9333333 | C248: 123456789 | D248: 123456789
A249: 1990m8 | B249: =AVERAGE(g4cpi!B238:B249) -> 6.1583333 | C249: 123456789 | D249: 123456789
A250: 1990m9 | B250: =AVERAGE(g4cpi!B239:B250) -> 6.4 | C250: 123456789 | D250: 123456789
A251: 1990m10 | B251: =AVERAGE(g4cpi!B240:B251) -> 6.6166667 | C251: 123456789 | D251: 123456789
A252: 1990m11 | B252: =AVERAGE(g4cpi!B241:B252) -> 6.8083333 | C252: 123456789 | D252: 123456789
... A675: 2026m2 | B675: =AVERAGE(g4cpi!B664:B675) -> 3.3916667 | C675: 123456789 | D675: 123456789

Sheet infl1_m
B1: UK | C1: US | D1: EA
A2: 1970m1 | B2: 123456789 | C2: 123456789 | D2: 123456789
A3: 1970m2 | B3: 123456789 | C3: 123456789 | D3: 123456789
A4: 1970m3 | B4: 123456789 | C4: 123456789 | D4: 123456789
A5: 1970m4 | B5: 123456789 | C5: 123456789 | D5: 123456789
A6: 1970m5 | B6: 123456789 | C6: 123456789 | D6: 123456789
A7: 1970m6 | B7: 123456789 | C7: 123456789 | D7: 123456789
A8: 1970m7 | B8: 123456789 | C8: 123456789 | D8: 123456789
A9: 1970m8 | B9: 123456789 | C9: 123456789 | D9: 123456789
A10: 1970m9 | B10: 123456789 | C10: 123456789 | D10: 123456789
A11: 1970m10 | B11: 123456789 | C11: 123456789 | D11: 123456789
A12: 1970m11 | B12: 123456789 | C12: 123456789 | D12: 123456789
A13: 1970m12 | B13: 123456789 | C13: 123456789 | D13: 123456789
... A238: 1989m9 | B238: 123456789 | C238: 123456789 | D238: 123456789
A239: 1989m10 | B239: =spliced_infl1_m!E59 -> 4.3294451 | C239: 123456789 | D239: 123456789
A240: 1989m11 | B240: =spliced_infl1_m!E60 -> 4.4584389 | C240: 123456789 | D240: 123456789
A241: 1989m12 | B241: =spliced_infl1_m!E61 -> 4.6860313 | C241: 123456789 | D241: 123456789
A242: 1990m1 | B242: =spliced_infl1_m!E62 -> 4.7445974 | C242: 123456789 | D242: 123456789
A243: 1990m2 | B243: =spliced_infl1_m!E63 -> 3.6970793 | C243: 123456789 | D243: 123456789
A244: 1990m3 | B244: =spliced_infl1_m!E64 -> 3.9083621 | C244: 123456789 | D244: 123456789
A245: 1990m4 | B245: =spliced_infl1_m!E65 -> 4.0536654 | C245: 123456789 | D245: 123456789
A246: 1990m5 | B246: =spliced_infl1_m!E66 -> 4.1537468 | C246: 123456789 | D246: 123456789
A247: 1990m6 | B247: =spliced_infl1_m!E67 -> 4.223433 | C247: 123456789 | D247: 123456789
A248: 1990m7 | B248: =spliced_infl1_m!E68 -> 4.266431 | C248: 123456789 | D248: 123456789
A249: 1990m8 | B249: =spliced_infl1_m!E69 -> 4.2975674 | C249: 123456789 | D249: 123456789
A250: 1990m9 | B250: =spliced_infl1_m!E70 -> 4.661567 | C250: 123456789 | D250: 123456789
... A675: 2026m2 | B675: =spliced_infl1_m!E495 -> 2.225 | C675: 123456789 | D675: 123456789

Sheet delta1vu_tightness
B1: UK | C1: US | D1: EA
A2: 1970m1 | B2: 123456789 | C2: 123456789 | D2: 123456789
A3: 1970m2 | B3: 123456789 | C3: 123456789 | D3: 123456789
A4: 1970m3 | B4: 123456789 | C4: 123456789 | D4: 123456789
A5: 1970m4 | B5: 123456789 | C5: 123456789 | D5: 123456789
A6: 1970m5 | B6: 123456789 | C6: 123456789 | D6: 123456789
A7: 1970m6 | B7: 123456789 | C7: 123456789 | D7: 123456789
A8: 1970m7 | B8: 123456789 | C8: 123456789 | D8: 123456789
A9: 1970m8 | B9: 123456789 | C9: 123456789 | D9: 123456789
A10: 1970m9 | B10: 123456789 | C10: 123456789 | D10: 123456789
A11: 1970m10 | B11: 123456789 | C11: 123456789 | D11: 123456789
A12: 1970m11 | B12: 123456789 | C12: 123456789 | D12: 123456789
A13: 1970m12 | B13: 123456789 | C13: 123456789 | D13: 123456789
... A26: 1972m1 | B26: 123456789 | C26: 123456789 | D26: 123456789
A27: 1972m2 | B27: =vu_tightness!B27-vu_tightness!B15 -> -0.071985261 | C27: 123456789 | D27: 123456789
A28: 1972m3 | B28: =vu_tightness!B28-vu_tightness!B16 -> -0.043455634 | C28: 123456789 | D28: 123456789
A29: 1972m4 | B29: =vu_tightness!B29-vu_tightness!B17 -> -0.020486241 | C29: 123456789 | D29: 123456789
A30: 1972m5 | B30: =vu_tightness!B30-vu_tightness!B18 -> -0.0079784041 | C30: 123456789 | D30: 123456789
A31: 1972m6 | B31: =vu_tightness!B31-vu_tightness!B19 -> 0.0081541111 | C31: 123456789 | D31: 123456789
A32: 1972m7 | B32: =vu_tightness!B32-vu_tightness!B20 -> 0.02529586 | C32: 123456789 | D32: 123456789
A33: 1972m8 | B33: =vu_tightness!B33-vu_tightness!B21 -> 0.036417347 | C33: 123456789 | D33: 123456789
A34: 1972m9 | B34: =vu_tightness!B34-vu_tightness!B22 -> 0.047723138 | C34: 123456789 | D34: 123456789
A35: 1972m10 | B35: =vu_tightness!B35-vu_tightness!B23 -> 0.070341593 | C35: 123456789 | D35: 123456789
A36: 1972m11 | B36: =vu_tightness!B36-vu_tightness!B24 -> 0.096198225 | C36: 123456789 | D36: 123456789
A37: 1972m12 | B37: =vu_tightness!B37-vu_tightness!B25 -> 0.12423284 | C37: 123456789 | D37: 123456789
A38: 1973m1 | B38: =vu_tightness!B38-vu_tightness!B26 -> 0.14984419 | C38: 123456789 | D38: 123456789
... A674: 2026m1 | B674: =vu_tightness!B674-vu_tightness!B662 -> -0.12634607 | C674: 123456789 | D674: 123456789
A675: 2026m2 | B675: -0.12635 | C675: 123456789 | D675: 123456789

Sheet yoy_growth_import_deflator
B1: UK | C1: US | D1: EA
A2: 1970m1 | B2: 123456789 | C2: 123456789 | D2: 123456789
A3: 1970m2 | B3: 123456789 | C3: 123456789 | D3: 123456789
A4: 1970m3 | B4: 123456789 | C4: 123456789 | D4: 123456789
A5: 1970m4 | B5: 123456789 | C5: 123456789 | D5: 123456789
A6: 1970m5 | B6: 123456789 | C6: 123456789 | D6: 123456789
A7: 1970m6 | B7: 123456789 | C7: 123456789 | D7: 123456789
A8: 1970m7 | B8: 123456789 | C8: 123456789 | D8: 123456789
A9: 1970m8 | B9: 123456789 | C9: 123456789 | D9: 123456789
A10: 1970m9 | B10: 123456789 | C10: 123456789 | D10: 123456789
A11: 1970m10 | B11: 123456789 | C11: 123456789 | D11: 123456789
A12: 1970m11 | B12: 123456789 | C12: 123456789 | D12: 123456789
A13: 1970m12 | B13: 123456789 | C13: 123456789 | D13: 123456789
A14: 1971m1 | B14: =(Imp_def_fameGM!B18/Imp_def_fameGM!B6-1)*100 -> 4.6254237 | C14: 123456789 | D14: 123456789
A15: 1971m2 | B15: =(Imp_def_fameGM!B19/Imp_def_fameGM!B7-1)*100 -> 3.9026299 | C15: 123456789 | D15: 123456789
A16: 1971m3 | B16: =(Imp_def_fameGM!B20/Imp_def_fameGM!B8-1)*100 -> 4.3720623 | C16: 123456789 | D16: 123456789
A17: 1971m4 | B17: =(Imp_def_fameGM!B21/Imp_def_fameGM!B9-1)*100 -> 5.0481738 | C17: 123456789 | D17: 123456789
A18: 1971m5 | B18: =(Imp_def_fameGM!B22/Imp_def_fameGM!B10-1)*100 -> 5.5957605 | C18: 123456789 | D18: 123456789
A19: 1971m6 | B19: =(Imp_def_fameGM!B23/Imp_def_fameGM!B11-1)*100 -> 5.3866288 | C19: 123456789 | D19: 123456789
A20: 1971m7 | B20: =(Imp_def_fameGM!B24/Imp_def_fameGM!B12-1)*100 -> 5.0509502 | C20: 123456789 | D20: 123456789
A21: 1971m8 | B21: =(Imp_def_fameGM!B25/Imp_def_fameGM!B13-1)*100 -> 4.6739215 | C21: 123456789 | D21: 123456789
A22: 1971m9 | B22: =(Imp_def_fameGM!B26/Imp_def_fameGM!B14-1)*100 -> 4.0949646 | C22: 123456789 | D22: 123456789
A23: 1971m10 | B23: =(Imp_def_fameGM!B27/Imp_def_fameGM!B15-1)*100 -> 3.4878843 | C23: 123456789 | D23: 123456789
A24: 1971m11 | B24: =(Imp_def_fameGM!B28/Imp_def_fameGM!B16-1)*100 -> 2.9306073 | C24: 123456789 | D24: 123456789
A25: 1971m12 | B25: =(Imp_def_fameGM!B29/Imp_def_fameGM!B17-1)*100 -> 2.6485282 | C25: 123456789 | D25: 123456789
... A674: 2026m1 | B674: =(Imp_def_fameGM!B678/Imp_def_fameGM!B666-1)*100 -> -0.87387559 | C674: 123456789 | D674: 123456789
A675: 2026m2 | B675: -0.873876 | C675: 123456789 | D675: 123456789

Sheet bond_spread
B1: UK | C1: US | D1: EA
A2: 1970m1 | B2: =spliced_corporate_spread!E2 -> 150 | C2: 123456789 | D2: 123456789
A3: 1970m2 | B3: =spliced_corporate_spread!E3 -> 145 | C3: 123456789 | D3: 123456789
A4: 1970m3 | B4: =spliced_corporate_spread!E4 -> 123 | C4: 123456789 | D4: 123456789
A5: 1970m4 | B5: =spliced_corporate_spread!E5 -> 123 | C5: 123456789 | D5: 123456789
A6: 1970m5 | B6: =spliced_corporate_spread!E6 -> 132 | C6: 123456789 | D6: 123456789
A7: 1970m6 | B7: =spliced_corporate_spread!E7 -> 134 | C7: 123456789 | D7: 123456789
A8: 1970m7 | B8: =spliced_corporate_spread!E8 -> 148 | C8: 123456789 | D8: 123456789
A9: 1970m8 | B9: =spliced_corporate_spread!E9 -> 122 | C9: 123456789 | D9: 123456789
A10: 1970m9 | B10: =spliced_corporate_spread!E10 -> 120 | C10: 123456789 | D10: 123456789
A11: 1970m10 | B11: =spliced_corporate_spread!E11 -> 112 | C11: 123456789 | D11: 123456789
A12: 1970m11 | B12: =spliced_corporate_spread!E12 -> 105 | C12: 123456789 | D12: 123456789
A13: 1970m12 | B13: =spliced_corporate_spread!E13 -> 120 | C13: 123456789 | D13: 123456789
... A675: 2026m2 | B675: =spliced_corporate_spread!E675 -> 81.4 | C675: 123456789 | D675: 123456789

Sheet vu_tightness
B1: UK | C1: US | D1: EA
A2: 1970m1 | B2: 123456789 | C2: 123456789 | D2: 123456789
A3: 1970m2 | B3: 123456789 | C3: 123456789 | D3: 123456789
A4: 1970m3 | B4: 123456789 | C4: 123456789 | D4: 123456789
A5: 1970m4 | B5: 123456789 | C5: 123456789 | D5: 123456789
A6: 1970m5 | B6: 123456789 | C6: 123456789 | D6: 123456789
A7: 1970m6 | B7: 123456789 | C7: 123456789 | D7: 123456789
A8: 1970m7 | B8: 123456789 | C8: 123456789 | D8: 123456789
A9: 1970m8 | B9: 123456789 | C9: 123456789 | D9: 123456789
A10: 1970m9 | B10: 123456789 | C10: 123456789 | D10: 123456789
A11: 1970m10 | B11: 123456789 | C11: 123456789 | D11: 123456789
A12: 1970m11 | B12: 123456789 | C12: 123456789 | D12: 123456789
A13: 1970m12 | B13: 123456789 | C13: 123456789 | D13: 123456789
... A378: 2001m5 | B378: 0.4763018 | C378: 123456789 | D378: 123456789
A379: 2001m6 | B379: =vu_extra_data!F368 -> 0.46331396 | C379: 123456789 | D379: 123456789
A380: 2001m7 | B380: =vu_extra_data!F369 -> 0.45785729 | C380: 123456789 | D380: 123456789
A381: 2001m8 | B381: =vu_extra_data!F370 -> 0.44714714 | C381: 123456789 | D381: 123456789
A382: 2001m9 | B382: =vu_extra_data!F371 -> 0.44575909 | C382: 123456789 | D382: 123456789
A383: 2001m10 | B383: =vu_extra_data!F372 -> 0.42958476 | C383: 123456789 | D383: 123456789
A384: 2001m11 | B384: =vu_extra_data!F373 -> 0.41865416 | C384: 123456789 | D384: 123456789
A385: 2001m12 | B385: =vu_extra_data!F374 -> 0.39548691 | C385: 123456789 | D385: 123456789
A386: 2002m1 | B386: =vu_extra_data!F375 -> 0.3991624 | C386: 123456789 | D386: 123456789
A387: 2002m2 | B387: =vu_extra_data!F376 -> 0.40858435 | C387: 123456789 | D387: 123456789
A388: 2002m3 | B388: =vu_extra_data!F377 -> 0.40855682 | C388: 123456789 | D388: 123456789
A389: 2002m4 | B389: =vu_extra_data!F378 -> 0.4066126 | C389: 123456789 | D389: 123456789
A390: 2002m5 | B390: =vu_extra_data!F379 -> 0.39745369 | C390: 123456789 | D390: 123456789
... A674: 2026m1 | B674: =vu_extra_data!F663 -> 0.3906426 | C674: 123456789 | D674: 123456789

Sheet vu_extra_data
B1: LFS unempl old | C1: ONS_vacancy_old | D1: ONS_vacancy_new | E1: LFS unempl new | F1: v/u
G2: ap2y.m[t-1] | H2: mgsc_dp.m[t-1]
A3: 1971m1
A4: 1971m2 | B4: 980
A5: 1971m3 | B5: 998
A6: 1971m4 | B6: 1023
A7: 1971m5 | B7: 1045
A8: 1971m6 | B8: 1062
A9: 1971m7 | B9: 1068
A10: 1971m8 | B10: 1076
A11: 1971m9 | B11: 1090
A12: 1971m10 | B12: 1113
A13: 1971m11 | B13: 1133
A14: 1971m12 | B14: 1143
A15: 1972m1 | B15: 1149
... A366: 2001m4 | B366: 1431
A367: 2001m5 | B367: 1468 | C367: 680 | D367: ='Fame Links'!F382 -> 0 | E367: ='Fame Links'!G382 -> 1430.5672 | F367: =D367/E367 -> 0
A368: 2001m6 | B368: 1472 | C368: 673 | D368: ='Fame Links'!F383 -> 680 | E368: ='Fame Links'!G383 -> 1467.6873 | F368: =D368/E368 -> 0.46331396
A369: 2001m7 | B369: 1483 | C369: 661 | D369: ='Fame Links'!F384 -> 674 | E369: ='Fame Links'!G384 -> 1472.0744 | F369: =D369/E369 -> 0.45785729
A370: 2001m8 | B370: 1487 | C370: 661 | D370: ='Fame Links'!F385 -> 663 | E370: ='Fame Links'!G385 -> 1482.7334 | F370: =D370/E370 -> 0.44714714
A371: 2001m9 | B371: 1487 | C371: 637 | D371: ='Fame Links'!F386 -> 663 | E371: ='Fame Links'!G386 -> 1487.3505 | F371: =D371/E371 -> 0.44575909
A372: 2001m10 | B372: 1495 | C372: 625 | D372: ='Fame Links'!F387 -> 639 | E372: ='Fame Links'!G387 -> 1487.483 | F372: =D372/E372 -> 0.42958476
A373: 2001m11 | B373: 1520 | C373: 602 | D373: ='Fame Links'!F388 -> 626 | E373: ='Fame Links'!G388 -> 1495.2676 | F373: =D373/E373 -> 0.41865416
A374: 2001m12 | B374: 1518 | C374: 607 | D374: ='Fame Links'!F389 -> 601 | E374: ='Fame Links'!G389 -> 1519.6458 | F374: =D374/E374 -> 0.39548691
A375: 2002m1 | B375: 1508 | C375: 616 | D375: ='Fame Links'!F390 -> 606 | E375: ='Fame Links'!G390 -> 1518.1791 | F375: =D375/E375 -> 0.3991624
A376: 2002m2 | B376: 1515 | C376: 619 | D376: ='Fame Links'!F391 -> 616 | E376: ='Fame Links'!G391 -> 1507.6446 | F376: =D376/E376 -> 0.40858435
A377: 2002m3 | B377: 1522 | C377: 619 | D377: ='Fame Links'!F392 -> 619 | E377: ='Fame Links'!G392 -> 1515.0891 | F377: =D377/E377 -> 0.40855682
A378: 2002m4 | B378: 1542 | C378: 612 | D378: ='Fame Links'!F393 -> 619 | E378: ='Fame Links'!G393 -> 1522.3335 | F378: =D378/E378 -> 0.4066126
... A555: 2017m1 | B555: 1559 | C555: 761 | D555: ='Fame Links'!F570 -> 748 | E555: ='Fame Links'!G570 -> 1575.3416 | F555: =D555/E555 -> 0.47481766
A556: 2017m2 | C556: 770 | D556: ='Fame Links'!F571 -> 764 | E556: ='Fame Links'!G571 -> 1552.7917 | F556: =D556/E556 -> 0.49201706
A557: 2017m3 | C557: 784 | D557: ='Fame Links'!F572 -> 771 | E557: ='Fame Links'!G572 -> 1530.0311 | F557: =D557/E557 -> 0.50391133
A558: 2017m4 | C558: 781 | D558: ='Fame Links'!F573 -> 791 | E558: ='Fame Links'!G573 -> 1522.609 | F558: =D558/E558 -> 0.51950303
A559: 2017m5 | C559: 780 | D559: ='Fame Links'!F574 -> 786 | E559: ='Fame Links'!G574 -> 1492.0005 | F559: =D559/E559 -> 0.52680947
A560: 2017m6 | C560: 774 | D560: ='Fame Links'!F575 -> 786 | E560: ='Fame Links'!G575 -> 1487.7081 | F560: =D560/E560 -> 0.52832945
A561: 2017m7 | C561: 781 | D561: ='Fame Links'!F576 -> 784 | E561: ='Fame Links'!G576 -> 1460.2758 | F561: =D561/E561 -> 0.53688487
A562: 2017m8 | C562: 786 | D562: ='Fame Links'!F577 -> 793 | E562: ='Fame Links'!G577 -> 1455.6207 | F562: =D562/E562 -> 0.54478478
A563: 2017m9 | C563: 780 | D563: ='Fame Links'!F578 -> 800 | E563: ='Fame Links'!G578 -> 1432.4556 | F563: =D563/E563 -> 0.55848152
A564: 2017m10 | D564: ='Fame Links'!F579 -> 812 | E564: ='Fame Links'!G579 -> 1425.7463 | F564: =D564/E564 -> 0.56952629
A565: 2017m11 | D565: ='Fame Links'!F580 -> 819 | E565: ='Fame Links'!G580 -> 1441.2187 | F565: =D565/E565 -> 0.56826906
A566: 2017m12 | D566: ='Fame Links'!F581 -> 820 | E566: ='Fame Links'!G581 -> 1466.9411 | F566: =D566/E566 -> 0.55898631
A567: 2018m1 | D567: ='Fame Links'!F582 -> 817 | E567: ='Fame Links'!G582 -> 1454.896 | F567: =D567/E567 -> 0.56155218
A568: 2018m2 | D568: ='Fame Links'!F583 -> 814 | E568: ='Fame Links'!G583 -> 1423.2842 | F568: =D568/E568 -> 0.57191669
A569: 2018m3 | D569: ='Fame Links'!F584 -> 815 | E569: ='Fame Links'!G584 -> 1421.6657 | F569: =D569/E569 -> 0.5732712
A570: 2018m4 | D570: ='Fame Links'!F585 -> 811 | E570: ='Fame Links'!G585 -> 1420.5257 | F570: =D570/E570 -> 0.5709154
A571: 2018m5 | D571: ='Fame Links'!F586 -> 821 | E571: ='Fame Links'!G586 -> 1412.5457 | F571: =D571/E571 -> 0.58122013
A572: 2018m6 | D572: ='Fame Links'!F587 -> 832 | E572: ='Fame Links'!G587 -> 1366.9203 | F572: =D572/E572 -> 0.60866751
A573: 2018m7 | D573: ='Fame Links'!F588 -> 837 | E573: ='Fame Links'!G588 -> 1362.5288 | F573: =D573/E573 -> 0.61429893
A574: 2018m8 | D574: ='Fame Links'!F589 -> 842 | E574: ='Fame Links'!G589 -> 1367.6682 | F574: =D574/E574 -> 0.61564638
A575: 2018m9 | D575: ='Fame Links'!F590 -> 846 | E575: ='Fame Links'!G590 -> 1382.3592 | F575: =D575/E575 -> 0.61199722
... A661: 2025m11 | D661: ='Fame Links'!F676 -> 727 | E661: ='Fame Links'!G676 -> 1839.8623 | F661: =D661/E661 -> 0.39513826
A662: 2025m12 | D662: ='Fame Links'!F677 -> 736 | E662: 1882.8868 | F662: =D662/E662 -> 0.39088913
A663: 2026m1 | D663: ='Fame Links'!F678 -> 730 | E663: 1868.7158 | F663: =D663/E663 -> 0.3906426

Sheet spliced_infl1_m
A1: FAMEDATE | B1: old_infl1_m | C1: growrh_old_inf | D1: new_infl1_m | E1: infl1_m_spliced | G1: note: new_inf1_m from simon email 13/06/2025 at 16:56
A2: 31078
A3: 31106
A4: 31137
A5: 31167
A6: 31198
A7: 31228
A8: 31259
A9: 31290
A10: 31320
A11: 31351
A12: 31381
A13: 31412
... A58: 32781
A59: 32812 | B59: 5.84 | E59: =E60/(1+C60) -> 4.3294451
A60: 32842 | B60: 6.014 | C60: =B60/B59-1 -> 0.029794521 | E60: =E61/(1+C61) -> 4.4584389
A61: 32873 | B61: 6.321 | C61: =B61/B60-1 -> 0.051047556 | E61: =E62/(1+C62) -> 4.6860313
A62: 32904 | B62: 6.4 | C62: =B62/B61-1 -> 0.012498022 | E62: =E63/(1+C63) -> 4.7445974
A63: 32932 | B63: 4.987 | C63: =B63/B62-1 -> -0.22078125 | E63: =E64/(1+C64) -> 3.6970793
A64: 32963 | B64: 5.272 | C64: =B64/B63-1 -> 0.057148586 | E64: =E65/(1+C65) -> 3.9083621
A65: 32993 | B65: 5.468 | C65: =B65/B64-1 -> 0.037177542 | E65: =E66/(1+C66) -> 4.0536654
A66: 33024 | B66: 5.603 | C66: =B66/B65-1 -> 0.0246891 | E66: =E67/(1+C67) -> 4.1537468
A67: 33054 | B67: 5.697 | C67: =B67/B66-1 -> 0.016776727 | E67: =E68/(1+C68) -> 4.223433
A68: 33085 | B68: 5.755 | C68: =B68/B67-1 -> 0.010180797 | E68: =E69/(1+C69) -> 4.266431
A69: 33116 | B69: 5.797 | C69: =B69/B68-1 -> 0.0072980017 | E69: =E70/(1+C70) -> 4.2975674
A70: 33146 | B70: 6.288 | C70: =B70/B69-1 -> 0.084698982 | E70: =E71/(1+C71) -> 4.661567
A71: 33177 | B71: 6.683 | C71: =B71/B70-1 -> 0.062818066 | E71: =E72/(1+C72) -> 4.9543976
... A229: 37986 | B229: 2.483 | C229: =B229/B228-1 -> 0.00080612656 | E229: =E230/(1+C230) -> 1.8407555
A230: 38017 | B230: 2.397 | C230: =B230/B229-1 -> -0.034635522 | D230: ='Fame Links'!E414 -> 1.777 | E230: =D230 -> 1.777
A231: 38046 | B231: 2.366 | C231: =B231/B230-1 -> -0.012932833 | D231: ='Fame Links'!E415 -> 1.767 | E231: =D231 -> 1.767
A232: 38077 | B232: 2.389 | C232: =B232/B231-1 -> 0.0097210482 | D232: ='Fame Links'!E416 -> 1.738 | E232: =D232 -> 1.738
A233: 38107 | B233: 2.368 | C233: =B233/B232-1 -> -0.0087902888 | D233: ='Fame Links'!E417 -> 1.753 | E233: =D233 -> 1.753
A234: 38138 | B234: 2.432 | C234: =B234/B233-1 -> 0.027027027 | D234: ='Fame Links'!E418 -> 1.768 | E234: =D234 -> 1.768
A235: 38168 | B235: 2.444 | C235: =B235/B234-1 -> 0.0049342105 | D235: ='Fame Links'!E419 -> 1.78 | E235: =D235 -> 1.78
A236: 38199 | B236: 2.443 | C236: =B236/B235-1 -> -0.0004091653 | D236: ='Fame Links'!E420 -> 1.796 | E236: =D236 -> 1.796
A237: 38230 | B237: 2.427 | C237: =B237/B236-1 -> -0.0065493246 | D237: ='Fame Links'!E421 -> 1.78 | E237: =D237 -> 1.78
A238: 38260 | B238: 2.41 | C238: =B238/B237-1 -> -0.0070045323 | D238: ='Fame Links'!E422 -> 1.834 | E238: =D238 -> 1.834
A239: 38291 | B239: 2.408 | C239: =B239/B238-1 -> -0.00082987552 | D239: ='Fame Links'!E423 -> 1.768 | E239: =D239 -> 1.768
A240: 38321 | B240: 2.326 | C240: =B240/B239-1 -> -0.034053156 | D240: ='Fame Links'!E424 -> 1.677 | E240: =D240 -> 1.677
A241: 38352 | B241: 2.313 | C241: =B241/B240-1 -> -0.005588994 | D241: ='Fame Links'!E425 -> 1.672 | E241: =D241 -> 1.672
... A457: 44926 | B457: 8.759 | C457: =B457/B456-1 -> -0.01958809 | D457: ='Fame Links'!E641 -> 7.2704 | E457: =D457 -> 7.2704
A458: 44957 | D458: ='Fame Links'!E642 -> 3.1233 | E458: =D458 -> 3.1233
A459: 44985 | D459: ='Fame Links'!E643 -> 2.9282 | E459: =D459 -> 2.9282
A460: 45016 | D460: ='Fame Links'!E644 -> 2.9258 | E460: =D460 -> 2.9258
A461: 45046 | D461: ='Fame Links'!E645 -> 2.8099 | E461: =D461 -> 2.8099
A462: 45077 | D462: ='Fame Links'!E646 -> 2.7734 | E462: =D462 -> 2.7734
A463: 45107 | D463: ='Fame Links'!E647 -> 3.171 | E463: =D463 -> 3.171
A464: 45138 | D464: ='Fame Links'!E648 -> 3.202 | E464: =D464 -> 3.202
A465: 45169 | D465: ='Fame Links'!E649 -> 3.0302 | E465: =D465 -> 3.0302
A466: 45199 | D466: ='Fame Links'!E650 -> 3.1369 | E466: =D466 -> 3.1369
A467: 45230 | D467: ='Fame Links'!E651 -> 3.1293 | E467: =D467 -> 3.1293
A468: 45260 | D468: ='Fame Links'!E652 -> 3.1297 | E468: =D468 -> 3.1297
A469: 45291 | D469: ='Fame Links'!E653 -> 3.073 | E469: =D469 -> 3.073
... A506: 46418 | D506: ='Fame Links'!E690 -> 0 | E506: =D506 -> 0

Sheet Imp_def_fameGM
A1: 1970
A2: 2026
A3: m
A4: famedate | B4: overlay(ikbi.m/ikbl.m*100,convgen(ikbi.q/ikbl.q*100,monthly,averaged,linear,yes))
A5: =[1]!FAMEData($A$4, $A$1, $A$2, 0,$A$3,"Down","Heading","Normal") -> famedate | B5: =[1]!FAMEData(B4, $A$1, $A$2, 0,$A$3,"Down","Heading","Normal") -> overlay(ikbi.m/ikbl.m*100,convgen(ikbi.q/ikbl.q*100,monthly,averaged,linear,yes)) | L5: quarterly_series_interpolated | M5: monthly_series | N5: final_series
A6: 25599 | B6: 9.7098762 | K6: 25569 | L6: 9.9 | N6: =L6 -> 9.9
A7: 25627 | B7: 9.8195451 | K7: 25600 | L7: 10 | N7: =L7 -> 10
A8: 25658 | B8: 9.8310413 | K8: 25628 | L8: 10.1 | N8: =L8 -> 10.1
A9: 25688 | B9: 9.8271383 | K9: 25659 | L9: 10.133333 | N9: =L9 -> 10.133333
A10: 25719 | B10: 9.8284068 | K10: 25689 | L10: 10.166667 | N10: =L10 -> 10.166667
A11: 25749 | B11: 9.8600376 | K11: 25720 | L11: 10.2 | N11: =L11 -> 10.2
A12: 25780 | B12: 9.8968401 | K12: 25750 | L12: 10.233333 | N12: =L12 -> 10.233333
A13: 25811 | B13: 9.9354913 | K13: 25781 | L13: 10.266667 | N13: =L13 -> 10.266667
A14: 25841 | B14: 9.9803989 | K14: 25812 | L14: 10.3 | N14: =L14 -> 10.3
A15: 25872 | B15: 10.026401 | K15: 25842 | L15: 10.333333 | N15: =L15 -> 10.333333
A16: 25902 | B16: 10.072028 | K16: 25873 | L16: 10.366667 | N16: =L16 -> 10.366667
A17: 25933 | B17: 10.115349 | K17: 25903 | L17: 10.4 | N17: =L17 -> 10.4
... A329: 35430 | B329: 66.616568 | K329: 35400 | L329: 69.5 | N329: =L329 -> 69.5
A330: 35461 | B330: 65.150055 | K330: 35431 | L330: 68.733333 | M330: =B330 -> 65.150055 | N330: =M330 -> 65.150055
A331: 35489 | B331: 64.890167 | K331: 35462 | L331: 67.966667 | M331: =B331 -> 64.890167 | N331: =M331 -> 64.890167
A332: 35520 | B332: 64.567133 | K332: 35490 | L332: 67.2 | M332: =B332 -> 64.567133 | N332: =M332 -> 64.567133
A333: 35550 | B333: 64.478045 | K333: 35521 | L333: 66.733333 | M333: =B333 -> 64.478045 | N333: =M333 -> 64.478045
A334: 35581 | B334: 63.999103 | K334: 35551 | L334: 66.266667 | M334: =B334 -> 63.999103 | N334: =M334 -> 63.999103
A335: 35611 | B335: 63.18303 | K335: 35582 | L335: 65.8 | M335: =B335 -> 63.18303 | N335: =M335 -> 63.18303
A336: 35642 | B336: 63.634943 | K336: 35612 | L336: 65.666667 | M336: =B336 -> 63.634943 | N336: =M336 -> 63.634943
A337: 35673 | B337: 63.10623 | K337: 35643 | L337: 65.533333 | M337: =B337 -> 63.10623 | N337: =M337 -> 63.10623
A338: 35703 | B338: 63.34046 | K338: 35674 | L338: 65.4 | M338: =B338 -> 63.34046 | N338: =M338 -> 63.34046
A339: 35734 | B339: 63.617535 | K339: 35704 | L339: 65.366667 | M339: =B339 -> 63.617535 | N339: =M339 -> 63.617535
A340: 35764 | B340: 62.925864 | K340: 35735 | L340: 65.333333 | M340: =B340 -> 62.925864 | N340: =M340 -> 62.925864
A341: 35795 | B341: 62.967797 | K341: 35765 | L341: 65.3 | M341: =B341 -> 62.967797 | N341: =M341 -> 62.967797
... A668: 45747 | B668: 99.387565 | K668: 45717 | L668: 101.6 | M668: =B668 -> 99.387565 | N668: =M668 -> 99.387565
A669: 45777 | B669: 99.569105 | K669: 45748 | M669: =B669 -> 99.569105 | N669: =M669 -> 99.569105
A670: 45808 | B670: 98.90699 | K670: 45778 | M670: =B670 -> 98.90699 | N670: =M670 -> 98.90699
A671: 45838 | B671: 99.261722 | K671: 45809 | M671: =B671 -> 99.261722 | N671: =M671 -> 99.261722
A672: 45869 | B672: 99.26283 | K672: 45839 | M672: =B672 -> 99.26283 | N672: =M672 -> 99.26283
A673: 45900 | B673: 98.03154 | K673: 45870 | M673: =B673 -> 98.03154 | N673: =M673 -> 98.03154
A674: 45930 | B674: 98.735175 | K674: 45901 | M674: =B674 -> 98.735175 | N674: =M674 -> 98.735175
A675: 45961 | B675: 100.60753 | K675: 45931 | M675: =B675 -> 100.60753 | N675: =M675 -> 100.60753
A676: 45991 | B676: 101.36143 | K676: 45962 | M676: =B676 -> 101.36143 | N676: =M676 -> 101.36143
A677: 46022 | B677: 100.12932 | K677: 45992 | M677: =B677 -> 100.12932 | N677: =M677 -> 100.12932
A678: 46053 | B678: 98.888875 | K678: 46023 | M678: =B678 -> 98.888875 | N678: =M678 -> 98.888875
A679: 46081 | K679: 46054 | M679: =B679 -> 0 | N679: =M679 -> 0
A680: 46112 | K680: 46082 | M680: =B680 -> 0 | N680: =M680 -> 0
A681: 46142
A682: 46173
A683: 46203
A684: 46234
A685: 46265
A686: 46295
A687: 46326
A688: 46356
A689: 46387

Sheet avg12Infl
B1: UK | C1: US | D1: EA
A2: 1970m1 | B2: 123456789 | C2: 123456789 | D2: 123456789
A3: 1970m2 | B3: 123456789 | C3: 123456789 | D3: 123456789
A4: 1970m3 | B4: 123456789 | C4: 123456789 | D4: 123456789
A5: 1970m4 | B5: 123456789 | C5: 123456789 | D5: 123456789
A6: 1970m5 | B6: 123456789 | C6: 123456789 | D6: 123456789
A7: 1970m6 | B7: 123456789 | C7: 123456789 | D7: 123456789
A8: 1970m7 | B8: 123456789 | C8: 123456789 | D8: 123456789
A9: 1970m8 | B9: 123456789 | C9: 123456789 | D9: 123456789
A10: 1970m9 | B10: 123456789 | C10: 123456789 | D10: 123456789
A11: 1970m10 | B11: 123456789 | C11: 123456789 | D11: 123456789
A12: 1970m11 | B12: 123456789 | C12: 123456789 | D12: 123456789
A13: 1970m12 | B13: 123456789 | C13: 123456789 | D13: 123456789
... A240: 1989m11 | B240: 123456789 | C240: 123456789 | D240: 123456789
A241: 1989m12 | B241: =AVERAGE(g4Infl!B230:B241) -> 5.7416667 | C241: 123456789 | D241: 123456789
A242: 1990m1 | B242: =AVERAGE(g4Infl!B231:B242) -> 5.7583333 | C242: 123456789 | D242: 123456789
A243: 1990m2 | B243: =AVERAGE(g4Infl!B232:B243) -> 5.8 | C243: 123456789 | D243: 123456789
A244: 1990m3 | B244: =AVERAGE(g4Infl!B233:B244) -> 5.825 | C244: 123456789 | D244: 123456789
A245: 1990m4 | B245: =AVERAGE(g4Infl!B234:B245) -> 6 | C245: 123456789 | D245: 123456789
A246: 1990m5 | B246: =AVERAGE(g4Infl!B235:B246) -> 6.1916667 | C246: 123456789 | D246: 123456789
A247: 1990m6 | B247: =AVERAGE(g4Infl!B236:B247) -> 6.3916667 | C247: 123456789 | D247: 123456789
A248: 1990m7 | B248: =AVERAGE(g4Infl!B237:B248) -> 6.6 | C248: 123456789 | D248: 123456789
A249: 1990m8 | B249: =AVERAGE(g4Infl!B238:B249) -> 6.8833333 | C249: 123456789 | D249: 123456789
A250: 1990m9 | B250: =AVERAGE(g4Infl!B239:B250) -> 7.175 | C250: 123456789 | D250: 123456789
A251: 1990m10 | B251: =AVERAGE(g4Infl!B240:B251) -> 7.4583333 | C251: 123456789 | D251: 123456789
A252: 1990m11 | B252: =AVERAGE(g4Infl!B241:B252) -> 7.75 | C252: 123456789 | D252: 123456789
... A670: 2025m9 | B670: =AVERAGE(g4Infl!B659:B670) -> 3.8166667 | C670: 123456789 | D670: 123456789

Sheet Oil
B1: UK | C1: US | D1: EA
A2: 1970m1 | B2: 123456789 | C2: 123456789 | D2: 123456789
A3: 1970m2 | B3: 123456789 | C3: 123456789 | D3: 123456789
A4: 1970m3 | B4: 123456789 | C4: 123456789 | D4: 123456789
A5: 1970m4 | B5: 123456789 | C5: 123456789 | D5: 123456789
A6: 1970m5 | B6: 123456789 | C6: 123456789 | D6: 123456789
A7: 1970m6 | B7: 123456789 | C7: 123456789 | D7: 123456789
A8: 1970m7 | B8: 123456789 | C8: 123456789 | D8: 123456789
A9: 1970m8 | B9: 123456789 | C9: 123456789 | D9: 123456789
A10: 1970m9 | B10: 123456789 | C10: 123456789 | D10: 123456789
A11: 1970m10 | B11: 123456789 | C11: 123456789 | D11: 123456789
A12: 1970m11 | B12: 123456789 | C12: 123456789 | D12: 123456789
A13: 1970m12 | B13: 123456789 | C13: 123456789 | D13: 123456789
... A673: 2025m12 | B673: 62.54 | C673: 123456789 | D673: 123456789

Sheet g4oil
B1: UK | C1: US | D1: EA
A2: 1970m1 | B2: 123456789 | C2: 123456789 | D2: 123456789
A3: 1970m2 | B3: 123456789 | C3: 123456789 | D3: 123456789
A4: 1970m3 | B4: 123456789 | C4: 123456789 | D4: 123456789
A5: 1970m4 | B5: 123456789 | C5: 123456789 | D5: 123456789
A6: 1970m5 | B6: 123456789 | C6: 123456789 | D6: 123456789
A7: 1970m6 | B7: 123456789 | C7: 123456789 | D7: 123456789
A8: 1970m7 | B8: 123456789 | C8: 123456789 | D8: 123456789
A9: 1970m8 | B9: 123456789 | C9: 123456789 | D9: 123456789
A10: 1970m9 | B10: 123456789 | C10: 123456789 | D10: 123456789
A11: 1970m10 | B11: 123456789 | C11: 123456789 | D11: 123456789
A12: 1970m11 | B12: 123456789 | C12: 123456789 | D12: 123456789
A13: 1970m12 | B13: 123456789 | C13: 123456789 | D13: 123456789
... A675: 2026m2 | B675: -6.03277 | C675: 123456789 | D675: 123456789

Sheet g4cpicore_global
B1: UK | C1: US | D1: EA
A2: 1970m1 | B2: 123456789 | C2: 123456789 | D2: 123456789
A3: 1970m2 | B3: 123456789 | C3: 123456789 | D3: 123456789
A4: 1970m3 | B4: 123456789 | C4: 123456789 | D4: 123456789
A5: 1970m4 | B5: 123456789 | C5: 123456789 | D5: 123456789
A6: 1970m5 | B6: 123456789 | C6: 123456789 | D6: 123456789
A7: 1970m6 | B7: 123456789 | C7: 123456789 | D7: 123456789
A8: 1970m7 | B8: 123456789 | C8: 123456789 | D8: 123456789
A9: 1970m8 | B9: 123456789 | C9: 123456789 | D9: 123456789
A10: 1970m9 | B10: 123456789 | C10: 123456789 | D10: 123456789
A11: 1970m10 | B11: 123456789 | C11: 123456789 | D11: 123456789
A12: 1970m11 | B12: 123456789 | C12: 123456789 | D12: 123456789
A13: 1970m12 | B13: 123456789 | C13: 123456789 | D13: 123456789
... A670: 2025m9 | B670: 2.98 | C670: 123456789 | D670: 123456789

Sheet ue
B1: UK | C1: US | D1: EA
A2: 1970m1 | B2: 123456789 | C2: 123456789 | D2: 123456789
A3: 1970m2 | B3: 123456789 | C3: 123456789 | D3: 123456789
A4: 1970m3 | B4: 123456789 | C4: 123456789 | D4: 123456789
A5: 1970m4 | B5: 123456789 | C5: 123456789 | D5: 123456789
A6: 1970m5 | B6: 123456789 | C6: 123456789 | D6: 123456789
A7: 1970m6 | B7: 123456789 | C7: 123456789 | D7: 123456789
A8: 1970m7 | B8: 123456789 | C8: 123456789 | D8: 123456789
A9: 1970m8 | B9: 123456789 | C9: 123456789 | D9: 123456789
A10: 1970m9 | B10: 123456789 | C10: 123456789 | D10: 123456789
A11: 1970m10 | B11: 123456789 | C11: 123456789 | D11: 123456789
A12: 1970m11 | B12: 123456789 | C12: 123456789 | D12: 123456789
A13: 1970m12 | B13: 123456789 | C13: 123456789 | D13: 123456789
... A675: 2026m2 | B675: 5 | C675: 123456789 | D675: 123456789

Sheet g4cpinoener
B1: UK | C1: US | D1: EA
A2: 1970m1 | B2: 123456789 | C2: 123456789 | D2: 123456789
A3: 1970m2 | B3: 123456789 | C3: 123456789 | D3: 123456789
A4: 1970m3 | B4: 123456789 | C4: 123456789 | D4: 123456789
A5: 1970m4 | B5: 123456789 | C5: 123456789 | D5: 123456789
A6: 1970m5 | B6: 123456789 | C6: 123456789 | D6: 123456789
A7: 1970m6 | B7: 123456789 | C7: 123456789 | D7: 123456789
A8: 1970m7 | B8: 123456789 | C8: 123456789 | D8: 123456789
A9: 1970m8 | B9: 123456789 | C9: 123456789 | D9: 123456789
A10: 1970m9 | B10: 123456789 | C10: 123456789 | D10: 123456789
A11: 1970m10 | B11: 123456789 | C11: 123456789 | D11: 123456789
A12: 1970m11 | B12: 123456789 | C12: 123456789 | D12: 123456789
A13: 1970m12 | B13: 123456789 | C13: 123456789 | D13: 123456789
... A670: 2025m9 | B670: 3.9 | C670: 123456789 | D670: 123456789

Sheet avgcpinoener
B1: UK | C1: US | D1: EA
A2: 1970m1 | B2: 123456789 | C2: 123456789 | D2: 123456789
A3: 1970m2 | B3: 123456789 | C3: 123456789 | D3: 123456789
A4: 1970m3 | B4: 123456789 | C4: 123456789 | D4: 123456789
A5: 1970m4 | B5: 123456789 | C5: 123456789 | D5: 123456789
A6: 1970m5 | B6: 123456789 | C6: 123456789 | D6: 123456789
A7: 1970m6 | B7: 123456789 | C7: 123456789 | D7: 123456789
A8: 1970m7 | B8: 123456789 | C8: 123456789 | D8: 123456789
A9: 1970m8 | B9: 123456789 | C9: 123456789 | D9: 123456789
A10: 1970m9 | B10: 123456789 | C10: 123456789 | D10: 123456789
A11: 1970m10 | B11: 123456789 | C11: 123456789 | D11: 123456789
A12: 1970m11 | B12: 123456789 | C12: 123456789 | D12: 123456789
A13: 1970m12 | B13: 123456789 | C13: 123456789 | D13: 123456789
... A240: 1989m11 | B240: 123456789 | C240: 123456789 | D240: 123456789
A241: 1989m12 | B241: =AVERAGE(g4cpinoener!B230:B241) -> 5.0833333 | C241: 123456789 | D241: 123456789
A242: 1990m1 | B242: =AVERAGE(g4cpinoener!B231:B242) -> 5.125 | C242: 123456789 | D242: 123456789
A243: 1990m2 | B243: =AVERAGE(g4cpinoener!B232:B243) -> 5.2 | C243: 123456789 | D243: 123456789
A244: 1990m3 | B244: =AVERAGE(g4cpinoener!B233:B244) -> 5.2916667 | C244: 123456789 | D244: 123456789
A245: 1990m4 | B245: =AVERAGE(g4cpinoener!B234:B245) -> 5.4083333 | C245: 123456789 | D245: 123456789
A246: 1990m5 | B246: =AVERAGE(g4cpinoener!B235:B246) -> 5.5666667 | C246: 123456789 | D246: 123456789
A247: 1990m6 | B247: =AVERAGE(g4cpinoener!B236:B247) -> 5.725 | C247: 123456789 | D247: 123456789
A248: 1990m7 | B248: =AVERAGE(g4cpinoener!B237:B248) -> 5.8833333 | C248: 123456789 | D248: 123456789
A249: 1990m8 | B249: =AVERAGE(g4cpinoener!B238:B249) -> 6.0833333 | C249: 123456789 | D249: 123456789
A250: 1990m9 | B250: =AVERAGE(g4cpinoener!B239:B250) -> 6.275 | C250: 123456789 | D250: 123456789
A251: 1990m10 | B251: =AVERAGE(g4cpinoener!B240:B251) -> 6.425 | C251: 123456789 | D251: 123456789
A252: 1990m11 | B252: =AVERAGE(g4cpinoener!B241:B252) -> 6.575 | C252: 123456789 | D252: 123456789
... A670: 2025m9 | B670: =AVERAGE(g4cpinoener!B659:B670) -> 3.65 | C670: 123456789 | D670: 123456789

Sheet import_deflator
B1: UK | C1: US | D1: EA
A2: 1970m1 | B2: =import_defl_qm!D2 -> 9.9 | C2: 123456789 | D2: 123456789
A3: 1970m2 | B3: =import_defl_qm!D3 -> 10 | C3: 123456789 | D3: 123456789
A4: 1970m3 | B4: =import_defl_qm!D4 -> 10.1 | C4: 123456789 | D4: 123456789
A5: 1970m4 | B5: =import_defl_qm!D5 -> 10.133333 | C5: 123456789 | D5: 123456789
A6: 1970m5 | B6: =import_defl_qm!D6 -> 10.166667 | C6: 123456789 | D6: 123456789
A7: 1970m6 | B7: =import_defl_qm!D7 -> 10.2 | C7: 123456789 | D7: 123456789
A8: 1970m7 | B8: =import_defl_qm!D8 -> 10.233333 | C8: 123456789 | D8: 123456789
A9: 1970m8 | B9: =import_defl_qm!D9 -> 10.266667 | C9: 123456789 | D9: 123456789
A10: 1970m9 | B10: =import_defl_qm!D10 -> 10.3 | C10: 123456789 | D10: 123456789
A11: 1970m10 | B11: =import_defl_qm!D11 -> 10.333333 | C11: 123456789 | D11: 123456789
A12: 1970m11 | B12: =import_defl_qm!D12 -> 10.366667 | C12: 123456789 | D12: 123456789
A13: 1970m12 | B13: =import_defl_qm!D13 -> 10.4 | C13: 123456789 | D13: 123456789
... A325: 1996m12 | B325: =import_defl_qm!D325 -> 69.5 | C325: 123456789 | D325: 123456789
A326: 1997m1 | B326: 65.1 | C326: 123456789 | D326: 123456789
A327: 1997m2 | B327: 64.9 | C327: 123456789 | D327: 123456789
A328: 1997m3 | B328: 64.6 | C328: 123456789 | D328: 123456789
A329: 1997m4 | B329: 64.5 | C329: 123456789 | D329: 123456789
A330: 1997m5 | B330: 64 | C330: 123456789 | D330: 123456789
A331: 1997m6 | B331: 63.2 | C331: 123456789 | D331: 123456789
A332: 1997m7 | B332: 63.6 | C332: 123456789 | D332: 123456789
A333: 1997m8 | B333: 63.1 | C333: 123456789 | D333: 123456789
A334: 1997m9 | B334: 63.4 | C334: 123456789 | D334: 123456789
A335: 1997m10 | B335: 63.6 | C335: 123456789 | D335: 123456789
A336: 1997m11 | B336: 62.9 | C336: 123456789 | D336: 123456789
A337: 1997m12 | B337: 63 | C337: 123456789 | D337: 123456789
... A670: 2025m9 | B670: 98.2 | C670: 123456789 | D670: 123456789

Sheet import_defl_FAME
B1: UK | C1: US | D1: EA
A2: 1970m1 | B2: 9.7098762 | C2: 123456789 | D2: 123456789
A3: 1970m2 | B3: 9.8195451 | C3: 123456789 | D3: 123456789
A4: 1970m3 | B4: 9.8310413 | C4: 123456789 | D4: 123456789
A5: 1970m4 | B5: 9.8271383 | C5: 123456789 | D5: 123456789
A6: 1970m5 | B6: 9.8284068 | C6: 123456789 | D6: 123456789
A7: 1970m6 | B7: 9.8600376 | C7: 123456789 | D7: 123456789
A8: 1970m7 | B8: 9.8968401 | C8: 123456789 | D8: 123456789
A9: 1970m8 | B9: 9.9354913 | C9: 123456789 | D9: 123456789
A10: 1970m9 | B10: 9.9803989 | C10: 123456789 | D10: 123456789
A11: 1970m10 | B11: 10.026401 | C11: 123456789 | D11: 123456789
A12: 1970m11 | B12: 10.072028 | C12: 123456789 | D12: 123456789
A13: 1970m12 | B13: 10.115349 | C13: 123456789 | D13: 123456789
... A671: 2025m10 | B671: 99.60316 | C671: 123456789 | D671: 123456789

Sheet import_defl_qm
B1: quarterly_series_interpolated | C1: monthly_series | D1: final_series | F1: the linearly interpolated quarterly series comes from other_series.do
A2: 25569 | B2: 9.9 | D2: =B2 -> 9.9
A3: 25600 | B3: 10 | D3: =B3 -> 10
A4: 25628 | B4: 10.1 | D4: =B4 -> 10.1
A5: 25659 | B5: 10.133333 | D5: =B5 -> 10.133333
A6: 25689 | B6: 10.166667 | D6: =B6 -> 10.166667
A7: 25720 | B7: 10.2 | D7: =B7 -> 10.2
A8: 25750 | B8: 10.233333 | D8: =B8 -> 10.233333
A9: 25781 | B9: 10.266667 | D9: =B9 -> 10.266667
A10: 25812 | B10: 10.3 | D10: =B10 -> 10.3
A11: 25842 | B11: 10.333333 | D11: =B11 -> 10.333333
A12: 25873 | B12: 10.366667 | D12: =B12 -> 10.366667
A13: 25903 | B13: 10.4 | D13: =B13 -> 10.4
... A307: 34851 | B307: 70.4 | D307: =B307 -> 70.4
A308: 34881 | B308: 70.766667 | D308: =B308 -> 70.766667 | H308: CORREL | I308: =CORREL(B326:B664,C326:C664) -> 0.99830556
A309: 34912 | B309: 71.133333 | D309: =B309 -> 71.133333
A310: 34943 | B310: 71.5 | D310: =B310 -> 71.5
A311: 34973 | B311: 71.5 | D311: =B311 -> 71.5
A312: 35004 | B312: 71.5 | D312: =B312 -> 71.5
A313: 35034 | B313: 71.5 | D313: =B313 -> 71.5
A314: 35065 | B314: 71.666667 | D314: =B314 -> 71.666667
A315: 35096 | B315: 71.833333 | D315: =B315 -> 71.833333
A316: 35125 | B316: 72 | D316: =B316 -> 72
A317: 35156 | B317: 72 | D317: =B317 -> 72
A318: 35186 | B318: 72 | D318: =B318 -> 72
A319: 35217 | B319: 72 | D319: =B319 -> 72
A320: 35247 | B320: 71.5 | D320: =B320 -> 71.5
... A325: 35400 | B325: 69.5 | D325: =B325 -> 69.5
A326: 35431 | B326: 68.733333 | C326: =Imp_def_fameGM!B330 -> 65.150055 | D326: =C326 -> 65.150055
A327: 35462 | B327: 67.966667 | C327: =Imp_def_fameGM!B331 -> 64.890167 | D327: =C327 -> 64.890167
A328: 35490 | B328: 67.2 | C328: =Imp_def_fameGM!B332 -> 64.567133 | D328: =C328 -> 64.567133
A329: 35521 | B329: 66.733333 | C329: =Imp_def_fameGM!B333 -> 64.478045 | D329: =C329 -> 64.478045
A330: 35551 | B330: 66.266667 | C330: =Imp_def_fameGM!B334 -> 63.999103 | D330: =C330 -> 63.999103
A331: 35582 | B331: 65.8 | C331: =Imp_def_fameGM!B335 -> 63.18303 | D331: =C331 -> 63.18303
A332: 35612 | B332: 65.666667 | C332: =Imp_def_fameGM!B336 -> 63.634943 | D332: =C332 -> 63.634943
A333: 35643 | B333: 65.533333 | C333: =Imp_def_fameGM!B337 -> 63.10623 | D333: =C333 -> 63.10623
A334: 35674 | B334: 65.4 | C334: =Imp_def_fameGM!B338 -> 63.34046 | D334: =C334 -> 63.34046
A335: 35704 | B335: 65.366667 | C335: =Imp_def_fameGM!B339 -> 63.617535 | D335: =C335 -> 63.617535
A336: 35735 | B336: 65.333333 | C336: =Imp_def_fameGM!B340 -> 62.925864 | D336: =C336 -> 62.925864
A337: 35765 | B337: 65.3 | C337: =Imp_def_fameGM!B341 -> 62.967797 | D337: =C337 -> 62.967797
... A664: 45717 | B664: 101.6 | C664: =Imp_def_fameGM!B668 -> 99.387565 | D664: =C664 -> 99.387565
A665: 45748 | C665: =Imp_def_fameGM!B669 -> 99.569105 | D665: =C665 -> 99.569105
A666: 45778 | C666: =Imp_def_fameGM!B670 -> 98.90699 | D666: =C666 -> 98.90699
A667: 45809 | C667: =Imp_def_fameGM!B671 -> 99.261722 | D667: =C667 -> 99.261722
A668: 45839 | C668: =Imp_def_fameGM!B672 -> 99.26283 | D668: =C668 -> 99.26283
A669: 45870 | C669: =Imp_def_fameGM!B673 -> 98.03154 | D669: =C669 -> 98.03154

Sheet Sheet1
A1: 1950
A2: 2025
A3: m
A4: famedate | B4: overlay(ikbi.m/ikbl.m*100,convgen(ikbi.q/ikbl.q*100,monthly,averaged,linear,yes))
A5: =[1]!FAMEData(import_defl_FAME!$A$4, import_defl_FAME!$A$1, import_defl_FAME!$A$2, 0,import_defl_FAME!$A$3,"Down","Heading","Normal") -> #N/A | B5: =[1]!FAMEData(B4, import_defl_FAME!$A$1, import_defl_FAME!$A$2, 0,import_defl_FAME!$A$3,"Down","Heading","Normal") -> #N/A

Sheet yoy_growth_import_defl_FAME
B1: UK | C1: US | D1: EA
A2: 1970m1 | B2: 123456789 | C2: 123456789 | D2: 123456789
A3: 1970m2 | B3: 123456789 | C3: 123456789 | D3: 123456789
A4: 1970m3 | B4: 123456789 | C4: 123456789 | D4: 123456789
A5: 1970m4 | B5: 123456789 | C5: 123456789 | D5: 123456789
A6: 1970m5 | B6: 123456789 | C6: 123456789 | D6: 123456789
A7: 1970m6 | B7: 123456789 | C7: 123456789 | D7: 123456789
A8: 1970m7 | B8: 123456789 | C8: 123456789 | D8: 123456789
A9: 1970m8 | B9: 123456789 | C9: 123456789 | D9: 123456789
A10: 1970m9 | B10: 123456789 | C10: 123456789 | D10: 123456789
A11: 1970m10 | B11: 123456789 | C11: 123456789 | D11: 123456789
A12: 1970m11 | B12: 123456789 | C12: 123456789 | D12: 123456789
A13: 1970m12 | B13: 123456789 | C13: 123456789 | D13: 123456789
A14: 1971m1 | B14: =(import_defl_FAME!B14/import_defl_FAME!B2-1)*100 -> 4.6254237 | C14: 123456789 | D14: 123456789
A15: 1971m2 | B15: =(import_defl_FAME!B15/import_defl_FAME!B3-1)*100 -> 3.9026299 | C15: 123456789 | D15: 123456789
A16: 1971m3 | B16: =(import_defl_FAME!B16/import_defl_FAME!B4-1)*100 -> 4.3720623 | C16: 123456789 | D16: 123456789
A17: 1971m4 | B17: =(import_defl_FAME!B17/import_defl_FAME!B5-1)*100 -> 5.0481738 | C17: 123456789 | D17: 123456789
A18: 1971m5 | B18: =(import_defl_FAME!B18/import_defl_FAME!B6-1)*100 -> 5.5957605 | C18: 123456789 | D18: 123456789
A19: 1971m6 | B19: =(import_defl_FAME!B19/import_defl_FAME!B7-1)*100 -> 5.3866288 | C19: 123456789 | D19: 123456789
A20: 1971m7 | B20: =(import_defl_FAME!B20/import_defl_FAME!B8-1)*100 -> 5.0509502 | C20: 123456789 | D20: 123456789
A21: 1971m8 | B21: =(import_defl_FAME!B21/import_defl_FAME!B9-1)*100 -> 4.6739215 | C21: 123456789 | D21: 123456789
A22: 1971m9 | B22: =(import_defl_FAME!B22/import_defl_FAME!B10-1)*100 -> 4.0949646 | C22: 123456789 | D22: 123456789
A23: 1971m10 | B23: =(import_defl_FAME!B23/import_defl_FAME!B11-1)*100 -> 3.4878843 | C23: 123456789 | D23: 123456789
A24: 1971m11 | B24: =(import_defl_FAME!B24/import_defl_FAME!B12-1)*100 -> 2.9306073 | C24: 123456789 | D24: 123456789
A25: 1971m12 | B25: =(import_defl_FAME!B25/import_defl_FAME!B13-1)*100 -> 2.6485282 | C25: 123456789 | D25: 123456789
... A671: 2025m10 | B671: =(import_defl_FAME!B671/import_defl_FAME!B659-1)*100 -> 2.7507829 | C671: 123456789 | D671: 123456789
A672: 2025m11 | B672: 2.7507829 | C672: 123456789 | D672: 123456789

Sheet vu_tight_hp_filter
B1: UK | C1: US | D1: EA
A2: 1970m1 | B2: 123456789 | C2: 123456789 | D2: 123456789
A3: 1970m2 | B3: 123456789 | C3: 123456789 | D3: 123456789
A4: 1970m3 | B4: 123456789 | C4: 123456789 | D4: 123456789
A5: 1970m4 | B5: 123456789 | C5: 123456789 | D5: 123456789
A6: 1970m5 | B6: 123456789 | C6: 123456789 | D6: 123456789
A7: 1970m6 | B7: 123456789 | C7: 123456789 | D7: 123456789
A8: 1970m7 | B8: 123456789 | C8: 123456789 | D8: 123456789
A9: 1970m8 | B9: 123456789 | C9: 123456789 | D9: 123456789
A10: 1970m9 | B10: 123456789 | C10: 123456789 | D10: 123456789
A11: 1970m10 | B11: 123456789 | C11: 123456789 | D11: 123456789
A12: 1970m11 | B12: 123456789 | C12: 123456789 | D12: 123456789
A13: 1970m12 | B13: 123456789 | C13: 123456789 | D13: 123456789
... A666: 2025m5 | B666: 123456789 | C666: 123456789 | D666: 123456789

Sheet ugap_hp_filter_lambda_129600
B1: UK | C1: US | D1: EA
A2: 1970m1 | B2: 123456789 | C2: 123456789 | D2: 123456789
A3: 1970m2 | B3: 123456789 | C3: 123456789 | D3: 123456789
A4: 1970m3 | B4: 123456789 | C4: 123456789 | D4: 123456789
A5: 1970m4 | B5: 123456789 | C5: 123456789 | D5: 123456789
A6: 1970m5 | B6: 123456789 | C6: 123456789 | D6: 123456789
A7: 1970m6 | B7: 123456789 | C7: 123456789 | D7: 123456789
A8: 1970m7 | B8: 123456789 | C8: 123456789 | D8: 123456789
A9: 1970m8 | B9: 123456789 | C9: 123456789 | D9: 123456789
A10: 1970m9 | B10: 123456789 | C10: 123456789 | D10: 123456789
A11: 1970m10 | B11: 123456789 | C11: 123456789 | D11: 123456789
A12: 1970m11 | B12: 123456789 | C12: 123456789 | D12: 123456789
A13: 1970m12 | B13: 123456789 | C13: 123456789 | D13: 123456789
... A666: 2025m5 | B666: 123456789 | C666: 123456789 | D666: 123456789

Sheet inter_vu_tightness
B1: UK | C1: US | D1: EA
A2: 1970m1 | B2: =covid_gdp!B2*vu_tightness!B2 -> 0 | C2: 0 | D2: 0
A3: 1970m2 | B3: =covid_gdp!B3*vu_tightness!B3 -> 0 | C3: 0 | D3: 0
A4: 1970m3 | B4: =covid_gdp!B4*vu_tightness!B4 -> 0 | C4: 0 | D4: 0
A5: 1970m4 | B5: =covid_gdp!B5*vu_tightness!B5 -> 0 | C5: 0 | D5: 0
A6: 1970m5 | B6: =covid_gdp!B6*vu_tightness!B6 -> 0 | C6: 0 | D6: 0
A7: 1970m6 | B7: =covid_gdp!B7*vu_tightness!B7 -> 0 | C7: 0 | D7: 0
A8: 1970m7 | B8: =covid_gdp!B8*vu_tightness!B8 -> 0 | C8: 0 | D8: 0
A9: 1970m8 | B9: =covid_gdp!B9*vu_tightness!B9 -> 0 | C9: 0 | D9: 0
A10: 1970m9 | B10: =covid_gdp!B10*vu_tightness!B10 -> 0 | C10: 0 | D10: 0
A11: 1970m10 | B11: =covid_gdp!B11*vu_tightness!B11 -> 0 | C11: 0 | D11: 0
A12: 1970m11 | B12: =covid_gdp!B12*vu_tightness!B12 -> 0 | C12: 0 | D12: 0
A13: 1970m12 | B13: =covid_gdp!B13*vu_tightness!B13 -> 0 | C13: 0 | D13: 0
... A666: 2025m5 | B666: =covid_gdp!B666*vu_tightness!B666 -> 0 | C666: 0 | D666: 0

Sheet covid
B1: UK | C1: US | D1: EA
A2: 1970m1 | B2: 0 | C2: 0 | D2: 0
A3: 1970m2 | B3: 0 | C3: 0 | D3: 0
A4: 1970m3 | B4: 0 | C4: 0 | D4: 0
A5: 1970m4 | B5: 0 | C5: 0 | D5: 0
A6: 1970m5 | B6: 0 | C6: 0 | D6: 0
A7: 1970m6 | B7: 0 | C7: 0 | D7: 0
A8: 1970m7 | B8: 0 | C8: 0 | D8: 0
A9: 1970m8 | B9: 0 | C9: 0 | D9: 0
A10: 1970m9 | B10: 0 | C10: 0 | D10: 0
A11: 1970m10 | B11: 0 | C11: 0 | D11: 0
A12: 1970m11 | B12: 0 | C12: 0 | D12: 0
A13: 1970m12 | B13: 0 | C13: 0 | D13: 0
... A666: 2025m5 | B666: 0 | C666: 0 | D666: 0

Sheet covid_gdp
B1: UK | C1: US | D1: EA
A2: 1970m1 | B2: 0 | C2: 0 | D2: 0
A3: 1970m2 | B3: 0 | C3: 0 | D3: 0
A4: 1970m3 | B4: 0 | C4: 0 | D4: 0
A5: 1970m4 | B5: 0 | C5: 0 | D5: 0
A6: 1970m5 | B6: 0 | C6: 0 | D6: 0
A7: 1970m6 | B7: 0 | C7: 0 | D7: 0
A8: 1970m7 | B8: 0 | C8: 0 | D8: 0
A9: 1970m8 | B9: 0 | C9: 0 | D9: 0
A10: 1970m9 | B10: 0 | C10: 0 | D10: 0
A11: 1970m10 | B11: 0 | C11: 0 | D11: 0
A12: 1970m11 | B12: 0 | C12: 0 | D12: 0
A13: 1970m12 | B13: 0 | C13: 0 | D13: 0
... A666: 2025m5 | B666: 0 | C666: 0 | D666: 0

Sheet Sheet3
A3: Years (daily data) | B3: Months (daily data) | C3: Average of bond
A4: 1996 | B4: Jan | C4: 0
B5: Feb | C5: 0
B6: Mar | C6: 0
B7: Apr | C7: 0
B8: May | C8: 0
B9: Jun | C9: 0
B10: Jul | C10: 0
B11: Aug | C11: 0
B12: Sep | C12: 0
B13: Oct | C13: 0
B14: Nov | C14: 0
B15: Dec | C15: 2.1363636
A16: 1997 | B16: Jan | C16: 46.130435
B17: Feb | C17: 47.95
B18: Mar | C18: 43.952381
B19: Apr | C19: 44.272727
B20: May | C20: 46.727273
B21: Jun | C21: 46.190476
B22: Jul | C22: 45.347826
B23: Aug | C23: 48.47619
B24: Sep | C24: 51
B25: Oct | C25: 49.217391
B26: Nov | C26: 57.2
B27: Dec | C27: 57.304348
A28: 1998 | B28: Jan | C28: 60.772727
B29: Feb | C29: 61.4
B30: Mar | C30: 61.818182
B31: Apr | C31: 64.727273
B32: May | C32: 62.857143
B33: Jun | C33: 65.272727
B34: Jul | C34: 68.347826
B35: Aug | C35: 76.095238
B36: Sep | C36: 104.13636
B37: Oct | C37: 141.09091
B38: Nov | C38: 123.57143
B39: Dec | C39: 123.26087
A40: 1999 | B40: Jan | C40: 118.90476
B41: Feb | C41: 106.7
B42: Mar | C42: 102.86957
B43: Apr | C43: 105.18182
B44: May | C44: 104.66667
B45: Jun | C45: 108.63636
B46: Jul | C46: 109.36364
B47: Aug | C47: 114.81818
B48: Sep | C48: 115
B49: Oct | C49: 116.38095
B50: Nov | C50: 121.40909
B51: Dec | C51: 122.52174
A52: 2000 | B52: Jan | C52: 123.47619
B53: Feb | C53: 124.80952
B54: Mar | C54: 127.26087
B55: Apr | C55: 133.15
B56: May | C56: 144.34783
B57: Jun | C57: 151.59091
B58: Jul | C58: 148.19048
B59: Aug | C59: 145.91304
B60: Sep | C60: 139.19048
B61: Oct | C61: 132.22727
B62: Nov | C62: 130.45455
B63: Dec | C63: 130.14286
A64: 2001 | B64: Jan | C64: 121.08696
B65: Feb | C65: 126.35
B66: Mar | C66: 134.13636
B67: Apr | C67: 125.28571
B68: May | C68: 117
B69: Jun | C69: 114.66667
B70: Jul | C70: 112.5
B71: Aug | C71: 109
B72: Sep | C72: 123.45
B73: Oct | C73: 127.82609
B74: Nov | C74: 123.09091
B75: Dec | C75: 116.85714
A76: 2002 | B76: Jan | C76: 110.56522
B77: Feb | C77: 109
B78: Mar | C78: 103
B79: Apr | C79: 96.772727
B80: May | C80: 100.65217
B81: Jun | C81: 102.8
B82: Jul | C82: 117.21739
B83: Aug | C83: 129.72727
B84: Sep | C84: 130.57143
B85: Oct | C85: 144.52174
B86: Nov | C86: 134.57143
B87: Dec | C87: 127.09091
A88: 2003 | B88: Jan | C88: 125.43478
B89: Feb | C89: 130.15
B90: Mar | C90: 128.66667
B91: Apr | C91: 117.45455
B92: May | C92: 107.27273
B93: Jun | C93: 100.66667
B94: Jul | C94: 89.913043
B95: Aug | C95: 89.333333
B96: Sep | C96: 82.5
B97: Oct | C97: 77.173913
B98: Nov | C98: 76.2
B99: Dec | C99: 73.347826
A100: 2004 | B100: Jan | C100: 73.5
B101: Feb | C101: 78.9
B102: Mar | C102: 83.826087
...

Sheet spliced_corporate_spread
B1: GBP investment-grade | C1: spread_millenium_macro_data | D1: gr_spread_millenium_macro_data | E1: spliced GBP investment-grade | J1: daily data | K1: bond
A2: 25569 | C2: 1.5 | E2: =C2*100 -> 150 | J2: ='Fame Links'!I6 -> 35065 | K2: ='Fame Links'!J6
A3: 25600 | C3: 1.45 | E3: =C3*100 -> 145 | J3: ='Fame Links'!I7 -> 35066 | K3: ='Fame Links'!J7 -> 0
A4: 25628 | C4: 1.23 | E4: =C4*100 -> 123 | J4: ='Fame Links'!I8 -> 35067 | K4: ='Fame Links'!J8 -> 0
A5: 25659 | C5: 1.23 | E5: =C5*100 -> 123 | J5: ='Fame Links'!I9 -> 35068 | K5: ='Fame Links'!J9 -> 0
A6: 25689 | C6: 1.32 | E6: =C6*100 -> 132 | J6: ='Fame Links'!I10 -> 35069 | K6: ='Fame Links'!J10 -> 0
A7: 25720 | C7: 1.34 | E7: =C7*100 -> 134 | J7: ='Fame Links'!I11 -> 35072 | K7: ='Fame Links'!J11 -> 0
A8: 25750 | C8: 1.48 | E8: =C8*100 -> 148 | J8: ='Fame Links'!I12 -> 35073 | K8: ='Fame Links'!J12 -> 0
A9: 25781 | C9: 1.22 | E9: =C9*100 -> 122 | J9: ='Fame Links'!I13 -> 35074 | K9: ='Fame Links'!J13 -> 0
A10: 25812 | C10: 1.2 | E10: =C10*100 -> 120 | J10: ='Fame Links'!I14 -> 35075 | K10: ='Fame Links'!J14 -> 0
A11: 25842 | C11: 1.12 | E11: =C11*100 -> 112 | J11: ='Fame Links'!I15 -> 35076 | K11: ='Fame Links'!J15 -> 0
A12: 25873 | C12: 1.05 | E12: =C12*100 -> 105 | J12: ='Fame Links'!I16 -> 35079 | K12: ='Fame Links'!J16 -> 0
A13: 25903 | C13: 1.2 | E13: =C13*100 -> 120 | J13: ='Fame Links'!I17 -> 35080 | K13: ='Fame Links'!J17 -> 0
... A122: 29221 | C122: 0.56 | E122: =C122*100 -> 56 | J122: ='Fame Links'!I126 -> 35233 | K122: ='Fame Links'!J126 -> 0
A123: 29252 | C123: 0 | E123: 0 | J123: ='Fame Links'!I127 -> 35234 | K123: ='Fame Links'!J127 -> 0
A124: 29281 | C124: 0.14 | D124: =C124/C123-1 -> #DIV/0! | E124: =E125/(1+D125) -> 12.365688 | J124: ='Fame Links'!I128 -> 35235 | K124: ='Fame Links'!J128 -> 0
A125: 29312 | C125: 0.59 | D125: =C125/C124-1 -> 3.2142857 | E125: =E126/(1+D126) -> 52.112542 | J125: ='Fame Links'!I129 -> 35236 | K125: ='Fame Links'!J129 -> 0
A126: 29342 | C126: 0.47 | D126: =C126/C125-1 -> -0.20338983 | E126: =E127/(1+D127) -> 41.513381 | J126: ='Fame Links'!I130 -> 35237 | K126: ='Fame Links'!J130 -> 0
A127: 29373 | C127: 0.42 | D127: =C127/C126-1 -> -0.10638298 | E127: =E128/(1+D128) -> 37.097064 | J127: ='Fame Links'!I131 -> 35240 | K127: ='Fame Links'!J131 -> 0
A128: 29403 | C128: 0.61 | D128: =C128/C127-1 -> 0.45238095 | E128: =E129/(1+D129) -> 53.879069 | J128: ='Fame Links'!I132 -> 35241 | K128: ='Fame Links'!J132 -> 0
A129: 29434 | C129: 0.07 | D129: =C129/C128-1 -> -0.8852459 | E129: =E130/(1+D130) -> 6.182844 | J129: ='Fame Links'!I133 -> 35242 | K129: ='Fame Links'!J133 -> 0
A130: 29465 | C130: 0.47 | D130: =C130/C129-1 -> 5.7142857 | E130: =E131/(1+D131) -> 41.513381 | J130: ='Fame Links'!I134 -> 35243 | K130: ='Fame Links'!J134 -> 0
A131: 29495 | C131: 0.56 | D131: =C131/C130-1 -> 0.19148936 | E131: =E132/(1+D132) -> 49.462752 | J131: ='Fame Links'!I135 -> 35244 | K131: ='Fame Links'!J135 -> 0
A132: 29526 | C132: 0.43 | D132: =C132/C131-1 -> -0.23214286 | E132: =E133/(1+D133) -> 37.980327 | J132: ='Fame Links'!I136 -> 35247 | K132: ='Fame Links'!J136 -> 0
A133: 29556 | C133: 0.18 | D133: =C133/C132-1 -> -0.58139535 | E133: =E134/(1+D134) -> 15.898742 | J133: ='Fame Links'!I137 -> 35248 | K133: ='Fame Links'!J137 -> 0
A134: 29587 | C134: 0.26 | D134: =C134/C133-1 -> 0.44444444 | E134: =E135/(1+D135) -> 22.964849 | J134: ='Fame Links'!I138 -> 35249 | K134: ='Fame Links'!J138 -> 0
A135: 29618 | C135: 0.29 | D135: =C135/C134-1 -> 0.11538462 | E135: =E136/(1+D136) -> 25.614639 | J135: ='Fame Links'!I139 -> 35250 | K135: ='Fame Links'!J139 -> 0
... A313: 35034 | C313: 0.58 | D313: =C313/C312-1 -> 0.28888889 | E313: =E314/(1+D314) -> 51.229279 | J313: ='Fame Links'!I317 -> 35500 | K313: ='Fame Links'!J317 -> 43
A314: 35065 | C314: 0.63 | D314: =C314/C313-1 -> 0.086206897 | E314: =E315/(1+D315) -> 55.645596 | I314: 0 | J314: ='Fame Links'!I318 -> 35501 | K314: ='Fame Links'!J318 -> 44
A315: 35096 | C315: 0.11 | D315: =C315/C314-1 -> -0.82539683 | E315: =E316/(1+D316) -> 9.7158977 | I315: 0 | J315: ='Fame Links'!I319 -> 35502 | K315: ='Fame Links'!J319 -> 44
A316: 35125 | C316: 0.67 | D316: =C316/C315-1 -> 5.0909091 | E316: =E317/(1+D317) -> 59.17865 | I316: 0 | J316: ='Fame Links'!I320 -> 35503 | K316: ='Fame Links'!J320 -> 45
A317: 35156 | C317: 0.63 | D317: =C317/C316-1 -> -0.059701493 | E317: =E318/(1+D318) -> 55.645596 | I317: 0 | J317: ='Fame Links'!I321 -> 35506 | K317: ='Fame Links'!J321 -> 44
A318: 35186 | C318: 0.58 | D318: =C318/C317-1 -> -0.079365079 | E318: =E319/(1+D319) -> 51.229279 | I318: 0 | J318: ='Fame Links'!I322 -> 35507 | K318: ='Fame Links'!J322 -> 44
A319: 35217 | C319: 0.5 | D319: =C319/C318-1 -> -0.13793103 | E319: =E320/(1+D320) -> 44.163171 | I319: 0 | J319: ='Fame Links'!I323 -> 35508 | K319: ='Fame Links'!J323 -> 43
A320: 35247 | C320: 0.56 | D320: =C320/C319-1 -> 0.12 | E320: =E321/(1+D321) -> 49.462752 | I320: 0 | J320: ='Fame Links'!I324 -> 35509 | K320: ='Fame Links'!J324 -> 38
A321: 35278 | C321: 0.65 | D321: =C321/C320-1 -> 0.16071429 | E321: =E322/(1+D322) -> 57.412123 | I321: 0 | J321: ='Fame Links'!I325 -> 35510 | K321: ='Fame Links'!J325 -> 45
A322: 35309 | C322: 0.48 | D322: =C322/C321-1 -> -0.26153846 | E322: =E323/(1+D323) -> 42.396645 | I322: 0 | J322: ='Fame Links'!I326 -> 35513 | K322: ='Fame Links'!J326 -> 46
A323: 35339 | C323: 0.5 | D323: =C323/C322-1 -> 0.041666667 | E323: =E324/(1+D324) -> 44.163171 | I323: 0 | J323: ='Fame Links'!I327 -> 35514 | K323: ='Fame Links'!J327 -> 46
A324: 35370 | C324: 0.35 | D324: =C324/C323-1 -> -0.3 | E324: =E325/(1+D325) -> 30.91422 | I324: 0 | J324: ='Fame Links'!I328 -> 35515 | K324: ='Fame Links'!J328 -> 45
A325: 35400 | C325: 0.53 | D325: =C325/C324-1 -> 0.51428571 | E325: =E326/(1+D326) -> 46.812962 | I325: 2.1363636 | J325: ='Fame Links'!I329 -> 35516 | K325: ='Fame Links'!J329 -> 45
A326: 35431 | B326: 46.13044 | C326: 0.52227273 | D326: =C326/C325-1 -> -0.01457976 | E326: =B326 -> 46.13044 | I326: 46.130435 | J326: ='Fame Links'!I330 -> 35517 | K326: ='Fame Links'!J330 -> 45
A327: 35462 | B327: 47.95 | C327: 0.52105263 | D327: =C327/C326-1 -> -0.0023361275 | E327: =B327 -> 47.95 | I327: 47.95 | J327: ='Fame Links'!I331 -> 35520 | K327: ='Fame Links'!J331 -> 44
A328: 35490 | B328: 43.95238 | C328: 0.507 | D328: =C328/C327-1 -> -0.026969697 | E328: =B328 -> 43.95238 | I328: 43.952381 | J328: ='Fame Links'!I332 -> 35521 | K328: ='Fame Links'!J332 -> 38
A329: 35521 | B329: 44.27273 | C329: 0.49636364 | D329: =C329/C328-1 -> -0.020979021 | E329: =B329 -> 44.27273 | I329: 44.272727 | J329: ='Fame Links'!I333 -> 35522 | K329: ='Fame Links'!J333 -> 45
A330: 35551 | B330: 46.72727 | C330: 0.51590909 | D330: =C330/C329-1 -> 0.039377289 | E330: =B330 -> 46.72727 | I330: 46.727273 | J330: ='Fame Links'!I334 -> 35523 | K330: ='Fame Links'!J334 -> 44
A331: 35582 | B331: 46.19048 | C331: 0.51285714 | D331: =C331/C330-1 -> -0.0059156702 | E331: =B331 -> 46.19048 | I331: 46.190476 | J331: ='Fame Links'!I335 -> 35524 | K331: ='Fame Links'!J335 -> 45
A332: 35612 | B332: 45.34783 | C332: 0.49409091 | D332: =C332/C331-1 -> -0.036591542 | E332: =B332 -> 45.34783 | I332: 45.347826 | J332: ='Fame Links'!I336 -> 35527 | K332: ='Fame Links'!J336 -> 45
A333: 35643 | B333: 48.47619 | C333: 0.52454545 | D333: =C333/C332-1 -> 0.061637534 | E333: =B333 -> 48.47619 | I333: 48.47619 | J333: ='Fame Links'!I337 -> 35528 | K333: ='Fame Links'!J337 -> 45
A334: 35674 | B334: 51 | C334: 0.5552381 | D334: =C334/C333-1 -> 0.058512833 | E334: =B334 -> 51 | I334: 51 | J334: ='Fame Links'!I338 -> 35529 | K334: ='Fame Links'!J338 -> 45
A335: 35704 | B335: 49.21739 | C335: 0.53608696 | D335: =C335/C334-1 -> -0.034491759 | E335: =B335 -> 49.21739 | I335: 49.217391 | J335: ='Fame Links'!I339 -> 35530 | K335: ='Fame Links'!J339 -> 45
A336: 35735 | B336: 57.2 | C336: 0.60714286 | D336: =C336/C335-1 -> 0.13254548 | E336: =B336 -> 57.2 | I336: 57.2 | J336: ='Fame Links'!I340 -> 35531 | K336: ='Fame Links'!J340 -> 44
A337: 35765 | B337: 57.30435 | C337: 0.61409091 | D337: =C337/C336-1 -> 0.01144385 | E337: =B337 -> 57.30435 | I337: 57.304348 | J337: ='Fame Links'!I341 -> 35534 | K337: ='Fame Links'!J341 -> 44
... A565: 42705 | B565: 150.3636 | C565: 1.225 | D565: =C565/C564-1 -> -0.04296875 | E565: =B565 -> 150.3636 | I565: 150.36364 | J565: ='Fame Links'!I569 -> 35852 | K565: ='Fame Links'!J569 -> 61
A566: 42736 | B566: 144.3636 | E566: =B566 -> 144.3636 | I566: 144.36364 | J566: ='Fame Links'!I570 -> 35853 | K566: ='Fame Links'!J570 -> 60
A567: 42767 | B567: 146.55 | E567: =B567 -> 146.55 | I567: 146.55 | J567: ='Fame Links'!I571 -> 35856 | K567: ='Fame Links'!J571 -> 61
A568: 42795 | B568: 144.3044 | E568: =B568 -> 144.3044 | I568: 144.30435 | J568: ='Fame Links'!I572 -> 35857 | K568: ='Fame Links'!J572 -> 60
A569: 42826 | B569: 146.45 | E569: =B569 -> 146.45 | I569: 146.45 | J569: ='Fame Links'!I573 -> 35858 | K569: ='Fame Links'!J573 -> 61
A570: 42856 | B570: 137.3478 | E570: =B570 -> 137.3478 | I570: 137.34783 | J570: ='Fame Links'!I574 -> 35859 | K570: ='Fame Links'!J574 -> 62
A571: 42887 | B571: 131.7273 | E571: =B571 -> 131.7273 | I571: 131.72727 | J571: ='Fame Links'!I575 -> 35860 | K571: ='Fame Links'!J575 -> 62
A572: 42917 | B572: 128.4762 | E572: =B572 -> 128.4762 | I572: 128.47619 | J572: ='Fame Links'!I576 -> 35863 | K572: ='Fame Links'!J576 -> 63
A573: 42948 | B573: 127.913 | E573: =B573 -> 127.913 | I573: 127.91304 | J573: ='Fame Links'!I577 -> 35864 | K573: ='Fame Links'!J577 -> 61
A574: 42979 | B574: 128.1905 | E574: =B574 -> 128.1905 | I574: 128.19048 | J574: ='Fame Links'!I578 -> 35865 | K574: ='Fame Links'!J578 -> 62
A575: 43009 | B575: 124.1364 | E575: =B575 -> 124.1364 | I575: 124.13636 | J575: ='Fame Links'!I579 -> 35866 | K575: ='Fame Links'!J579 -> 62
A576: 43040 | B576: 124.5909 | E576: =B576 -> 124.5909 | I576: 124.59091 | J576: ='Fame Links'!I580 -> 35867 | K576: ='Fame Links'!J580 -> 61
A577: 43070 | B577: 123.9524 | E577: =B577 -> 123.9524 | I577: 123.95238 | J577: ='Fame Links'!I581 -> 35870 | K577: ='Fame Links'!J581 -> 62
... A670: 45901 | B670: 85.5 | E670: =B670 -> 85.5 | I670: 85.5 | J670: ='Fame Links'!I674 -> 35999 | K670: ='Fame Links'!J674 -> 68
A671: 45931 | B671: =I671 -> 81.347826 | E671: =B671 -> 81.347826 | I671: 81.347826 | J671: ='Fame Links'!I675 -> 36000 | K671: ='Fame Links'!J675 -> 66
A672: 45962 | B672: =I672 -> 54.25 | E672: 83.85 | I672: 54.25 | J672: ='Fame Links'!I676 -> 36003 | K672: ='Fame Links'!J676 -> 69
A673: 45992 | E673: 79.57 | I673: 0 | J673: ='Fame Links'!I677 -> 36004 | K673: ='Fame Links'!J677 -> 71
A674: 46023 | E674: 78.18 | I674: 0 | J674: ='Fame Links'!I678 -> 36005 | K674: ='Fame Links'!J678 -> 72
A675: 46054 | E675: 81.4 | I675: 0 | J675: ='Fame Links'!I679 -> 36006 | K675: ='Fame Links'!J679 -> 68
A676: 46082 | E676: 92.48 | I676: 0 | J676: ='Fame Links'!I680 -> 36007 | K676: ='Fame Links'!J680 -> 72
A677: 46113 | I677: 0 | J677: ='Fame Links'!I681 -> 36010 | K677: ='Fame Links'!J681 -> 71
A678: 46143 | I678: 0 | J678: ='Fame Links'!I682 -> 36011 | K678: ='Fame Links'!J682 -> 70
I679: 0 | J679: ='Fame Links'!I683 -> 36012 | K679: ='Fame Links'!J683 -> 70
I680: 0 | J680: ='Fame Links'!I684 -> 36013 | K680: ='Fame Links'!J684 -> 71
I681: 0 | J681: ='Fame Links'!I685 -> 36014 | K681: ='Fame Links'!J685 -> 71
I682: 0 | J682: ='Fame Links'!I686 -> 36017 | K682: ='Fame Links'!J686 -> 71
I683: 0 | J683: ='Fame Links'!I687 -> 36018 | K683: ='Fame Links'!J687 -> 71
I684: 0 | J684: ='Fame Links'!I688 -> 36019 | K684: ='Fame Links'!J688 -> 72
I685: 0 | J685: ='Fame Links'!I689 -> 36020 | K685: ='Fame Links'!J689 -> 70
J686: ='Fame Links'!I690 -> 36021 | K686: ='Fame Links'!J690 -> 72
J687: ='Fame Links'!I691 -> 36024 | K687: ='Fame Links'!J691 -> 71
J688: ='Fame Links'!I692 -> 36025 | K688: ='Fame Links'!J692 -> 72
J689: ='Fame Links'!I693 -> 36026 | K689: ='Fame Links'!J693 -> 73
J690: ='Fame Links'!I694 -> 36027 | K690: ='Fame Links'!J694 -> 77
J691: ='Fame Links'!I695 -> 36028 | K691: ='Fame Links'!J695 -> 77
J692: ='Fame Links'!I696 -> 36031 | K692: ='Fame Links'!J696 -> 81
J693: ='Fame Links'!I697 -> 36032 | K693: ='Fame Links'!J697 -> 85
J694: ='Fame Links'!I698 -> 36033 | K694: ='Fame Links'!J698 -> 84
J695: ='Fame Links'!I699 -> 36034 | K695: ='Fame Links'!J699 -> 88
J696: ='Fame Links'!I700 -> 36035 | K696: ='Fame Links'!J700 -> 90
J697: ='Fame Links'!I701 -> 36038 | K697: ='Fame Links'!J701 -> 91
... J8090: ='Fame Links'!I8094 -> 46387 | K8090: ='Fame Links'!J8094 -> 0

Sheet ugap_kalman_filter
B1: UK | C1: US | D1: EA
A2: 1970m1 | B2: 123456789 | C2: 123456789 | D2: 123456789
A3: 1970m2 | B3: 123456789 | C3: 123456789 | D3: 123456789
A4: 1970m3 | B4: 123456789 | C4: 123456789 | D4: 123456789
A5: 1970m4 | B5: 123456789 | C5: 123456789 | D5: 123456789
A6: 1970m5 | B6: 123456789 | C6: 123456789 | D6: 123456789
A7: 1970m6 | B7: 123456789 | C7: 123456789 | D7: 123456789
A8: 1970m7 | B8: 123456789 | C8: 123456789 | D8: 123456789
A9: 1970m8 | B9: 123456789 | C9: 123456789 | D9: 123456789
A10: 1970m9 | B10: 123456789 | C10: 123456789 | D10: 123456789
A11: 1970m10 | B11: 123456789 | C11: 123456789 | D11: 123456789
A12: 1970m11 | B12: 123456789 | C12: 123456789 | D12: 123456789
A13: 1970m12 | B13: 123456789 | C13: 123456789 | D13: 123456789
... A666: 2025m5 | B666: 123456789 | C666: 123456789 | D666: 123456789

Sheet ugap_hp_filter
B1: UK | C1: US | D1: EA
A2: 1970m1 | B2: 123456789 | C2: 123456789 | D2: 123456789
A3: 1970m2 | B3: 123456789 | C3: 123456789 | D3: 123456789
A4: 1970m3 | B4: 123456789 | C4: 123456789 | D4: 123456789
A5: 1970m4 | B5: 123456789 | C5: 123456789 | D5: 123456789
A6: 1970m5 | B6: 123456789 | C6: 123456789 | D6: 123456789
A7: 1970m6 | B7: 123456789 | C7: 123456789 | D7: 123456789
A8: 1970m7 | B8: 123456789 | C8: 123456789 | D8: 123456789
A9: 1970m8 | B9: 123456789 | C9: 123456789 | D9: 123456789
A10: 1970m9 | B10: 123456789 | C10: 123456789 | D10: 123456789
A11: 1970m10 | B11: 123456789 | C11: 123456789 | D11: 123456789
A12: 1970m11 | B12: 123456789 | C12: 123456789 | D12: 123456789
A13: 1970m12 | B13: 123456789 | C13: 123456789 | D13: 123456789
... A666: 2025m5 | B666: 123456789 | C666: 123456789 | D666: 123456789
